package io.reactivex.processors;

import io.reactivex.annotations.CheckReturnValue;
import io.reactivex.annotations.Experimental;
import io.reactivex.annotations.NonNull;
import io.reactivex.annotations.Nullable;
import io.reactivex.exceptions.MissingBackpressureException;
import io.reactivex.internal.functions.ObjectHelper;
import io.reactivex.internal.subscriptions.SubscriptionHelper;
import io.reactivex.internal.util.AppendOnlyLinkedArrayList;
import io.reactivex.internal.util.BackpressureHelper;
import io.reactivex.internal.util.ExceptionHelper;
import io.reactivex.internal.util.NotificationLite;
import io.reactivex.plugins.RxJavaPlugins;
import java.lang.reflect.Array;
import java.util.concurrent.atomic.AtomicLong;
import java.util.concurrent.atomic.AtomicReference;
import java.util.concurrent.locks.Lock;
import java.util.concurrent.locks.ReadWriteLock;
import java.util.concurrent.locks.ReentrantReadWriteLock;
import org.reactivestreams.Subscriber;
import org.reactivestreams.Subscription;

public final class BehaviorProcessor<T> extends FlowableProcessor<T> {
  static final BehaviorSubscription[] EMPTY;
  
  static final Object[] EMPTY_ARRAY = new Object[0];
  
  static final BehaviorSubscription[] TERMINATED;
  
  long index;
  
  final ReadWriteLock lock = new ReentrantReadWriteLock();
  
  final Lock readLock = this.lock.readLock();
  
  final AtomicReference<BehaviorSubscription<T>[]> subscribers = new AtomicReference(EMPTY);
  
  final AtomicReference<Throwable> terminalEvent = new AtomicReference<Throwable>();
  
  final AtomicReference<Object> value = new AtomicReference();
  
  final Lock writeLock = this.lock.writeLock();
  
  static {
    EMPTY = new BehaviorSubscription[0];
    TERMINATED = new BehaviorSubscription[0];
  }
  
  BehaviorProcessor() {}
  
  BehaviorProcessor(T paramT) {
    this();
    this.value.lazySet(ObjectHelper.requireNonNull(paramT, "defaultValue is null"));
  }
  
  @CheckReturnValue
  @NonNull
  public static <T> BehaviorProcessor<T> create() {
    return new BehaviorProcessor<T>();
  }
  
  @CheckReturnValue
  @NonNull
  public static <T> BehaviorProcessor<T> createDefault(T paramT) {
    ObjectHelper.requireNonNull(paramT, "defaultValue is null");
    return new BehaviorProcessor<T>(paramT);
  }
  
  boolean add(BehaviorSubscription<T> paramBehaviorSubscription) {
    while (true) {
      BehaviorSubscription[] arrayOfBehaviorSubscription1 = (BehaviorSubscription[])this.subscribers.get();
      if (arrayOfBehaviorSubscription1 == TERMINATED)
        return false; 
      int i = arrayOfBehaviorSubscription1.length;
      BehaviorSubscription[] arrayOfBehaviorSubscription2 = new BehaviorSubscription[i + 1];
      System.arraycopy(arrayOfBehaviorSubscription1, 0, arrayOfBehaviorSubscription2, 0, i);
      arrayOfBehaviorSubscription2[i] = paramBehaviorSubscription;
      if (this.subscribers.compareAndSet(arrayOfBehaviorSubscription1, arrayOfBehaviorSubscription2))
        return true; 
    } 
  }
  
  @Nullable
  public Throwable getThrowable() {
    Object object = this.value.get();
    return NotificationLite.isError(object) ? NotificationLite.getError(object) : null;
  }
  
  @Nullable
  public T getValue() {
    Object object = this.value.get();
    return (T)((NotificationLite.isComplete(object) || NotificationLite.isError(object)) ? null : NotificationLite.getValue(object));
  }
  
  @Deprecated
  public Object[] getValues() {
    T[] arrayOfT = getValues((T[])EMPTY_ARRAY);
    return (Object[])((arrayOfT == EMPTY_ARRAY) ? new Object[0] : (Object)arrayOfT);
  }
  
  @Deprecated
  public T[] getValues(T[] paramArrayOfT) {
    Object object1 = this.value.get();
    if (object1 == null || NotificationLite.isComplete(object1) || NotificationLite.isError(object1)) {
      if (paramArrayOfT.length != 0)
        paramArrayOfT[0] = null; 
      return paramArrayOfT;
    } 
    Object object2 = NotificationLite.getValue(object1);
    if (paramArrayOfT.length != 0) {
      paramArrayOfT[0] = (T)object2;
      object1 = paramArrayOfT;
      if (paramArrayOfT.length != 1) {
        paramArrayOfT[1] = null;
        object1 = paramArrayOfT;
      } 
    } else {
      object1 = Array.newInstance(paramArrayOfT.getClass().getComponentType(), 1);
      object1[0] = object2;
    } 
    return (T[])object1;
  }
  
  public boolean hasComplete() {
    return NotificationLite.isComplete(this.value.get());
  }
  
  public boolean hasSubscribers() {
    boolean bool;
    if (((BehaviorSubscription[])this.subscribers.get()).length != 0) {
      bool = true;
    } else {
      bool = false;
    } 
    return bool;
  }
  
  public boolean hasThrowable() {
    return NotificationLite.isError(this.value.get());
  }
  
  public boolean hasValue() {
    boolean bool;
    Object object = this.value.get();
    if (object != null && !NotificationLite.isComplete(object) && !NotificationLite.isError(object)) {
      bool = true;
    } else {
      bool = false;
    } 
    return bool;
  }
  
  @Experimental
  public boolean offer(T paramT) {
    if (paramT == null) {
      onError(new NullPointerException("onNext called with null. Null values are generally not allowed in 2.x operators and sources."));
      return true;
    } 
    BehaviorSubscription[] arrayOfBehaviorSubscription = (BehaviorSubscription[])this.subscribers.get();
    int i = arrayOfBehaviorSubscription.length;
    boolean bool = false;
    byte b;
    for (b = 0; b < i; b++) {
      if (arrayOfBehaviorSubscription[b].isFull())
        return false; 
    } 
    paramT = (T)NotificationLite.next(paramT);
    setCurrent(paramT);
    i = arrayOfBehaviorSubscription.length;
    for (b = bool; b < i; b++)
      arrayOfBehaviorSubscription[b].emitNext(paramT, this.index); 
    return true;
  }
  
  public void onComplete() {
    if (!this.terminalEvent.compareAndSet(null, ExceptionHelper.TERMINATED))
      return; 
    Object object = NotificationLite.complete();
    BehaviorSubscription[] arrayOfBehaviorSubscription = (BehaviorSubscription[])terminate(object);
    int i = arrayOfBehaviorSubscription.length;
    for (byte b = 0; b < i; b++)
      arrayOfBehaviorSubscription[b].emitNext(object, this.index); 
  }
  
  public void onError(Throwable paramThrowable) {
    ObjectHelper.requireNonNull(paramThrowable, "onError called with null. Null values are generally not allowed in 2.x operators and sources.");
    if (!this.terminalEvent.compareAndSet(null, paramThrowable)) {
      RxJavaPlugins.onError(paramThrowable);
      return;
    } 
    Object object = NotificationLite.error(paramThrowable);
    BehaviorSubscription[] arrayOfBehaviorSubscription = (BehaviorSubscription[])terminate(object);
    int i = arrayOfBehaviorSubscription.length;
    for (byte b = 0; b < i; b++)
      arrayOfBehaviorSubscription[b].emitNext(object, this.index); 
  }
  
  public void onNext(T paramT) {
    ObjectHelper.requireNonNull(paramT, "onNext called with null. Null values are generally not allowed in 2.x operators and sources.");
    if (this.terminalEvent.get() != null)
      return; 
    Object object = NotificationLite.next(paramT);
    setCurrent(object);
    BehaviorSubscription[] arrayOfBehaviorSubscription = (BehaviorSubscription[])this.subscribers.get();
    int i = arrayOfBehaviorSubscription.length;
    for (byte b = 0; b < i; b++)
      arrayOfBehaviorSubscription[b].emitNext(object, this.index); 
  }
  
  public void onSubscribe(Subscription paramSubscription) {
    if (this.terminalEvent.get() != null) {
      paramSubscription.cancel();
      return;
    } 
    paramSubscription.request(Long.MAX_VALUE);
  }
  
  void remove(BehaviorSubscription<T> paramBehaviorSubscription) {
    BehaviorSubscription[] arrayOfBehaviorSubscription1;
    BehaviorSubscription[] arrayOfBehaviorSubscription2;
    do {
      byte b2;
      arrayOfBehaviorSubscription1 = (BehaviorSubscription[])this.subscribers.get();
      int i = arrayOfBehaviorSubscription1.length;
      if (i == 0)
        return; 
      byte b1 = -1;
      byte b = 0;
      while (true) {
        b2 = b1;
        if (b < i) {
          if (arrayOfBehaviorSubscription1[b] == paramBehaviorSubscription) {
            b2 = b;
            break;
          } 
          b++;
          continue;
        } 
        break;
      } 
      if (b2 < 0)
        return; 
      if (i == 1) {
        arrayOfBehaviorSubscription2 = EMPTY;
      } else {
        arrayOfBehaviorSubscription2 = new BehaviorSubscription[i - 1];
        System.arraycopy(arrayOfBehaviorSubscription1, 0, arrayOfBehaviorSubscription2, 0, b2);
        System.arraycopy(arrayOfBehaviorSubscription1, b2 + 1, arrayOfBehaviorSubscription2, b2, i - b2 - 1);
      } 
    } while (!this.subscribers.compareAndSet(arrayOfBehaviorSubscription1, arrayOfBehaviorSubscription2));
  }
  
  void setCurrent(Object paramObject) {
    Lock lock = this.writeLock;
    lock.lock();
    this.index++;
    this.value.lazySet(paramObject);
    lock.unlock();
  }
  
  protected void subscribeActual(Subscriber<? super T> paramSubscriber) {
    BehaviorSubscription<T> behaviorSubscription = new BehaviorSubscription<T>(paramSubscriber, this);
    paramSubscriber.onSubscribe(behaviorSubscription);
    if (add(behaviorSubscription)) {
      if (behaviorSubscription.cancelled) {
        remove(behaviorSubscription);
      } else {
        behaviorSubscription.emitFirst();
      } 
    } else {
      Throwable throwable = this.terminalEvent.get();
      if (throwable == ExceptionHelper.TERMINATED) {
        paramSubscriber.onComplete();
      } else {
        paramSubscriber.onError(throwable);
      } 
    } 
  }
  
  int subscriberCount() {
    return ((BehaviorSubscription[])this.subscribers.get()).length;
  }
  
  BehaviorSubscription<T>[] terminate(Object paramObject) {
    BehaviorSubscription[] arrayOfBehaviorSubscription1 = (BehaviorSubscription[])this.subscribers.get();
    BehaviorSubscription[] arrayOfBehaviorSubscription2 = TERMINATED;
    BehaviorSubscription[] arrayOfBehaviorSubscription3 = arrayOfBehaviorSubscription1;
    if (arrayOfBehaviorSubscription1 != arrayOfBehaviorSubscription2) {
      arrayOfBehaviorSubscription1 = (BehaviorSubscription[])this.subscribers.getAndSet(arrayOfBehaviorSubscription2);
      arrayOfBehaviorSubscription3 = arrayOfBehaviorSubscription1;
      if (arrayOfBehaviorSubscription1 != TERMINATED) {
        setCurrent(paramObject);
        arrayOfBehaviorSubscription3 = arrayOfBehaviorSubscription1;
      } 
    } 
    return (BehaviorSubscription<T>[])arrayOfBehaviorSubscription3;
  }
  
  static final class BehaviorSubscription<T> extends AtomicLong implements Subscription, AppendOnlyLinkedArrayList.NonThrowingPredicate<Object> {
    private static final long serialVersionUID = 3293175281126227086L;
    
    final Subscriber<? super T> actual;
    
    volatile boolean cancelled;
    
    boolean emitting;
    
    boolean fastPath;
    
    long index;
    
    boolean next;
    
    AppendOnlyLinkedArrayList<Object> queue;
    
    final BehaviorProcessor<T> state;
    
    BehaviorSubscription(Subscriber<? super T> param1Subscriber, BehaviorProcessor<T> param1BehaviorProcessor) {
      this.actual = param1Subscriber;
      this.state = param1BehaviorProcessor;
    }
    
    public void cancel() {
      if (!this.cancelled) {
        this.cancelled = true;
        this.state.remove(this);
      } 
    }
    
    void emitFirst() {
      // Byte code:
      //   0: aload_0
      //   1: getfield cancelled : Z
      //   4: ifeq -> 8
      //   7: return
      //   8: aload_0
      //   9: monitorenter
      //   10: aload_0
      //   11: getfield cancelled : Z
      //   14: ifeq -> 20
      //   17: aload_0
      //   18: monitorexit
      //   19: return
      //   20: aload_0
      //   21: getfield next : Z
      //   24: ifeq -> 30
      //   27: aload_0
      //   28: monitorexit
      //   29: return
      //   30: aload_0
      //   31: getfield state : Lio/reactivex/processors/BehaviorProcessor;
      //   34: astore_1
      //   35: aload_1
      //   36: getfield readLock : Ljava/util/concurrent/locks/Lock;
      //   39: astore_2
      //   40: aload_2
      //   41: invokeinterface lock : ()V
      //   46: aload_0
      //   47: aload_1
      //   48: getfield index : J
      //   51: putfield index : J
      //   54: aload_1
      //   55: getfield value : Ljava/util/concurrent/atomic/AtomicReference;
      //   58: invokevirtual get : ()Ljava/lang/Object;
      //   61: astore_1
      //   62: aload_2
      //   63: invokeinterface unlock : ()V
      //   68: aload_1
      //   69: ifnull -> 77
      //   72: iconst_1
      //   73: istore_3
      //   74: goto -> 79
      //   77: iconst_0
      //   78: istore_3
      //   79: aload_0
      //   80: iload_3
      //   81: putfield emitting : Z
      //   84: aload_0
      //   85: iconst_1
      //   86: putfield next : Z
      //   89: aload_0
      //   90: monitorexit
      //   91: aload_1
      //   92: ifnull -> 108
      //   95: aload_0
      //   96: aload_1
      //   97: invokevirtual test : (Ljava/lang/Object;)Z
      //   100: ifeq -> 104
      //   103: return
      //   104: aload_0
      //   105: invokevirtual emitLoop : ()V
      //   108: return
      //   109: astore_2
      //   110: aload_0
      //   111: monitorexit
      //   112: aload_2
      //   113: athrow
      // Exception table:
      //   from	to	target	type
      //   10	19	109	finally
      //   20	29	109	finally
      //   30	68	109	finally
      //   79	91	109	finally
      //   110	112	109	finally
    }
    
    void emitLoop() {
      // Byte code:
      //   0: aload_0
      //   1: getfield cancelled : Z
      //   4: ifeq -> 8
      //   7: return
      //   8: aload_0
      //   9: monitorenter
      //   10: aload_0
      //   11: getfield queue : Lio/reactivex/internal/util/AppendOnlyLinkedArrayList;
      //   14: astore_1
      //   15: aload_1
      //   16: ifnonnull -> 27
      //   19: aload_0
      //   20: iconst_0
      //   21: putfield emitting : Z
      //   24: aload_0
      //   25: monitorexit
      //   26: return
      //   27: aload_0
      //   28: aconst_null
      //   29: putfield queue : Lio/reactivex/internal/util/AppendOnlyLinkedArrayList;
      //   32: aload_0
      //   33: monitorexit
      //   34: aload_1
      //   35: aload_0
      //   36: invokevirtual forEachWhile : (Lio/reactivex/internal/util/AppendOnlyLinkedArrayList$NonThrowingPredicate;)V
      //   39: goto -> 0
      //   42: astore_1
      //   43: aload_0
      //   44: monitorexit
      //   45: aload_1
      //   46: athrow
      // Exception table:
      //   from	to	target	type
      //   10	15	42	finally
      //   19	26	42	finally
      //   27	34	42	finally
      //   43	45	42	finally
    }
    
    void emitNext(Object param1Object, long param1Long) {
      // Byte code:
      //   0: aload_0
      //   1: getfield cancelled : Z
      //   4: ifeq -> 8
      //   7: return
      //   8: aload_0
      //   9: getfield fastPath : Z
      //   12: ifne -> 107
      //   15: aload_0
      //   16: monitorenter
      //   17: aload_0
      //   18: getfield cancelled : Z
      //   21: ifeq -> 27
      //   24: aload_0
      //   25: monitorexit
      //   26: return
      //   27: aload_0
      //   28: getfield index : J
      //   31: lload_2
      //   32: lcmp
      //   33: ifne -> 39
      //   36: aload_0
      //   37: monitorexit
      //   38: return
      //   39: aload_0
      //   40: getfield emitting : Z
      //   43: ifeq -> 87
      //   46: aload_0
      //   47: getfield queue : Lio/reactivex/internal/util/AppendOnlyLinkedArrayList;
      //   50: astore #4
      //   52: aload #4
      //   54: astore #5
      //   56: aload #4
      //   58: ifnonnull -> 78
      //   61: new io/reactivex/internal/util/AppendOnlyLinkedArrayList
      //   64: astore #5
      //   66: aload #5
      //   68: iconst_4
      //   69: invokespecial <init> : (I)V
      //   72: aload_0
      //   73: aload #5
      //   75: putfield queue : Lio/reactivex/internal/util/AppendOnlyLinkedArrayList;
      //   78: aload #5
      //   80: aload_1
      //   81: invokevirtual add : (Ljava/lang/Object;)V
      //   84: aload_0
      //   85: monitorexit
      //   86: return
      //   87: aload_0
      //   88: iconst_1
      //   89: putfield next : Z
      //   92: aload_0
      //   93: monitorexit
      //   94: aload_0
      //   95: iconst_1
      //   96: putfield fastPath : Z
      //   99: goto -> 107
      //   102: astore_1
      //   103: aload_0
      //   104: monitorexit
      //   105: aload_1
      //   106: athrow
      //   107: aload_0
      //   108: aload_1
      //   109: invokevirtual test : (Ljava/lang/Object;)Z
      //   112: pop
      //   113: return
      // Exception table:
      //   from	to	target	type
      //   17	26	102	finally
      //   27	38	102	finally
      //   39	52	102	finally
      //   61	78	102	finally
      //   78	86	102	finally
      //   87	94	102	finally
      //   103	105	102	finally
    }
    
    public boolean isFull() {
      boolean bool;
      if (get() == 0L) {
        bool = true;
      } else {
        bool = false;
      } 
      return bool;
    }
    
    public void request(long param1Long) {
      if (SubscriptionHelper.validate(param1Long))
        BackpressureHelper.add(this, param1Long); 
    }
    
    public boolean test(Object param1Object) {
      if (this.cancelled)
        return true; 
      if (NotificationLite.isComplete(param1Object)) {
        this.actual.onComplete();
        return true;
      } 
      if (NotificationLite.isError(param1Object)) {
        this.actual.onError(NotificationLite.getError(param1Object));
        return true;
      } 
      long l = get();
      if (l != 0L) {
        this.actual.onNext(NotificationLite.getValue(param1Object));
        if (l != Long.MAX_VALUE)
          decrementAndGet(); 
        return false;
      } 
      cancel();
      this.actual.onError((Throwable)new MissingBackpressureException("Could not deliver value due to lack of requests"));
      return true;
    }
  }
}


/* Location:              Y:\classes2-dex2jar.jar!\io\reactivex\processors\BehaviorProcessor.class
 * Java compiler version: 6 (50.0)
 * JD-Core Version:       1.1.3
 */