package com.google.android.gms.measurement.internal;

import android.content.Context;
import com.google.android.gms.common.GoogleApiAvailabilityLight;
import com.google.android.gms.common.util.VisibleForTesting;
import com.google.android.gms.internal.measurement.zzcl;
import com.google.android.gms.internal.measurement.zzcv;
import com.google.android.gms.internal.measurement.zzcw;
import com.google.android.gms.internal.measurement.zzdc;
import java.util.ArrayList;
import java.util.List;
import java.util.Map;

@VisibleForTesting
public final class zzal {
  static zzq zzfq;
  
  static List<zza<Integer>> zzfr = new ArrayList<zza<Integer>>();
  
  static List<zza<Long>> zzfs = new ArrayList<zza<Long>>();
  
  static List<zza<Boolean>> zzft = new ArrayList<zza<Boolean>>();
  
  static List<zza<String>> zzfu = new ArrayList<zza<String>>();
  
  static List<zza<Double>> zzfv = new ArrayList<zza<Double>>();
  
  private static final zzdc zzfw = new zzdc(zzcv.zzcd("com.google.android.gms.measurement"));
  
  @VisibleForTesting
  private static Boolean zzfx;
  
  private static zza<Boolean> zzfy = zza.zza("measurement.log_third_party_store_events_enabled", false, false);
  
  private static zza<Boolean> zzfz = zza.zza("measurement.log_installs_enabled", false, false);
  
  private static zza<Boolean> zzga = zza.zza("measurement.log_upgrades_enabled", false, false);
  
  public static zza<Boolean> zzgb = zza.zza("measurement.log_androidId_enabled", false, false);
  
  public static zza<Boolean> zzgc = zza.zza("measurement.upload_dsid_enabled", false, false);
  
  public static zza<String> zzgd = zza.zzc("measurement.log_tag", "FA", "FA-SVC");
  
  public static zza<Long> zzge = zza.zza("measurement.ad_id_cache_time", 10000L, 10000L);
  
  public static zza<Long> zzgf = zza.zza("measurement.monitoring.sample_period_millis", 86400000L, 86400000L);
  
  public static zza<Long> zzgg = zza.zza("measurement.config.cache_time", 86400000L, 3600000L);
  
  public static zza<String> zzgh = zza.zzc("measurement.config.url_scheme", "https", "https");
  
  public static zza<String> zzgi = zza.zzc("measurement.config.url_authority", "app-measurement.com", "app-measurement.com");
  
  public static zza<Integer> zzgj = zza.zzb("measurement.upload.max_bundles", 100, 100);
  
  public static zza<Integer> zzgk = zza.zzb("measurement.upload.max_batch_size", 65536, 65536);
  
  public static zza<Integer> zzgl = zza.zzb("measurement.upload.max_bundle_size", 65536, 65536);
  
  public static zza<Integer> zzgm = zza.zzb("measurement.upload.max_events_per_bundle", 1000, 1000);
  
  public static zza<Integer> zzgn = zza.zzb("measurement.upload.max_events_per_day", 100000, 100000);
  
  public static zza<Integer> zzgo = zza.zzb("measurement.upload.max_error_events_per_day", 1000, 1000);
  
  public static zza<Integer> zzgp = zza.zzb("measurement.upload.max_public_events_per_day", 50000, 50000);
  
  public static zza<Integer> zzgq = zza.zzb("measurement.upload.max_conversions_per_day", 500, 500);
  
  public static zza<Integer> zzgr = zza.zzb("measurement.upload.max_realtime_events_per_day", 10, 10);
  
  public static zza<Integer> zzgs = zza.zzb("measurement.store.max_stored_events_per_app", 100000, 100000);
  
  public static zza<String> zzgt = zza.zzc("measurement.upload.url", "https://app-measurement.com/a", "https://app-measurement.com/a");
  
  public static zza<Long> zzgu = zza.zza("measurement.upload.backoff_period", 43200000L, 43200000L);
  
  public static zza<Long> zzgv = zza.zza("measurement.upload.window_interval", 3600000L, 3600000L);
  
  public static zza<Long> zzgw = zza.zza("measurement.upload.interval", 3600000L, 3600000L);
  
  public static zza<Long> zzgx = zza.zza("measurement.upload.realtime_upload_interval", 10000L, 10000L);
  
  public static zza<Long> zzgy = zza.zza("measurement.upload.debug_upload_interval", 1000L, 1000L);
  
  public static zza<Long> zzgz = zza.zza("measurement.upload.minimum_delay", 500L, 500L);
  
  public static zza<Long> zzha = zza.zza("measurement.alarm_manager.minimum_interval", 60000L, 60000L);
  
  public static zza<Long> zzhb = zza.zza("measurement.upload.stale_data_deletion_interval", 86400000L, 86400000L);
  
  public static zza<Long> zzhc = zza.zza("measurement.upload.refresh_blacklisted_config_interval", 604800000L, 604800000L);
  
  public static zza<Long> zzhd = zza.zza("measurement.upload.initial_upload_delay_time", 15000L, 15000L);
  
  public static zza<Long> zzhe = zza.zza("measurement.upload.retry_time", 1800000L, 1800000L);
  
  public static zza<Integer> zzhf = zza.zzb("measurement.upload.retry_count", 6, 6);
  
  public static zza<Long> zzhg = zza.zza("measurement.upload.max_queue_time", 2419200000L, 2419200000L);
  
  public static zza<Integer> zzhh = zza.zzb("measurement.lifetimevalue.max_currency_tracked", 4, 4);
  
  public static zza<Integer> zzhi = zza.zzb("measurement.audience.filter_result_max_count", 200, 200);
  
  public static zza<Long> zzhj = zza.zza("measurement.service_client.idle_disconnect_millis", 5000L, 5000L);
  
  public static zza<Boolean> zzhk = zza.zza("measurement.test.boolean_flag", false, false);
  
  public static zza<String> zzhl = zza.zzc("measurement.test.string_flag", "---", "---");
  
  public static zza<Long> zzhm = zza.zza("measurement.test.long_flag", -1L, -1L);
  
  public static zza<Integer> zzhn = zza.zzb("measurement.test.int_flag", -2, -2);
  
  public static zza<Double> zzho = zza.zza("measurement.test.double_flag", -3.0D, -3.0D);
  
  public static zza<Integer> zzhp = zza.zzb("measurement.experiment.max_ids", 50, 50);
  
  public static zza<Boolean> zzhq = zza.zza("measurement.lifetimevalue.user_engagement_tracking_enabled", true, true);
  
  public static zza<Boolean> zzhr = zza.zza("measurement.audience.complex_param_evaluation", true, true);
  
  public static zza<Boolean> zzhs = zza.zza("measurement.validation.internal_limits_internal_event_params", false, false);
  
  public static zza<Boolean> zzht = zza.zza("measurement.quality.unsuccessful_update_retry_counter", true, true);
  
  public static zza<Boolean> zzhu = zza.zza("measurement.iid.disable_on_collection_disabled", true, true);
  
  public static zza<Boolean> zzhv = zza.zza("measurement.app_launch.call_only_when_enabled", true, true);
  
  public static zza<Boolean> zzhw = zza.zza("measurement.run_on_worker_inline", true, true);
  
  public static zza<Boolean> zzhx = zza.zza("measurement.audience.dynamic_filters", true, true);
  
  public static zza<Boolean> zzhy = zza.zza("measurement.reset_analytics.persist_time", false, false);
  
  public static zza<Boolean> zzhz = zza.zza("measurement.validation.value_and_currency_params", false, false);
  
  public static zza<Boolean> zzia = zza.zza("measurement.sampling.time_zone_offset_enabled", false, false);
  
  public static zza<Boolean> zzib = zza.zza("measurement.referrer.enable_logging_install_referrer_cmp_from_apk", false, false);
  
  public static zza<Boolean> zzic = zza.zza("measurement.fetch_config_with_admob_app_id", true, true);
  
  public static zza<Boolean> zzid = zza.zza("measurement.client.sessions.session_id_enabled", false, false);
  
  public static zza<Boolean> zzie = zza.zza("measurement.service.sessions.session_number_enabled", false, false);
  
  public static zza<Boolean> zzif = zza.zza("measurement.client.sessions.immediate_start_enabled", false, false);
  
  public static zza<Boolean> zzig = zza.zza("measurement.client.sessions.background_sessions_enabled", false, false);
  
  public static zza<Boolean> zzih = zza.zza("measurement.client.sessions.remove_expired_session_properties_enabled", false, false);
  
  public static zza<Boolean> zzii = zza.zza("measurement.service.sessions.session_number_backfill_enabled", false, false);
  
  public static zza<Boolean> zzij = zza.zza("measurement.service.sessions.remove_disabled_session_number", false, false);
  
  public static zza<Boolean> zzik = zza.zza("measurement.collection.firebase_global_collection_flag_enabled", true, true);
  
  public static zza<Boolean> zzil = zza.zza("measurement.collection.efficient_engagement_reporting_enabled", false, false);
  
  public static zza<Boolean> zzim = zza.zza("measurement.collection.redundant_engagement_removal_enabled", false, false);
  
  public static zza<Boolean> zzin = zza.zza("measurement.personalized_ads_signals_collection_enabled", false, false);
  
  public static zza<Boolean> zzio = zza.zza("measurement.collection.init_params_control_enabled", true, true);
  
  public static zza<Boolean> zzip = zza.zza("measurement.upload.disable_is_uploader", false, false);
  
  public static zza<Boolean> zziq = zza.zza("measurement.experiment.enable_experiment_reporting", false, false);
  
  public static zza<Boolean> zzir = zza.zza("measurement.collection.log_event_and_bundle_v2", true, true);
  
  public static zza<Boolean> zzis = zza.zza("measurement.collection.null_empty_event_name_fix", true, true);
  
  public static zza<Boolean> zzit = zza.zza("measurement.audience.sequence_filters", false, false);
  
  public static zza<Boolean> zziu = zza.zza("measurement.quality.checksum", false, false);
  
  public static zza<Boolean> zziv = zza.zza("measurement.module.collection.conditionally_omit_admob_app_id", true, true);
  
  public static zza<Boolean> zziw = zza.zza("measurement.sdk.dynamite.use_dynamite", false, false);
  
  public static zza<Boolean> zzix = zza.zza("measurement.sdk.dynamite.allow_remote_dynamite", false, false);
  
  public static zza<Boolean> zziy = zza.zza("measurement.sdk.collection.validate_param_names_alphabetical", false, false);
  
  private static zza<Boolean> zziz = zza.zza("measurement.collection.event_safelist", false, false);
  
  private static zza<Boolean> zzja = zza.zza("measurement.service.audience.scoped_filters", false, false);
  
  private static volatile zzby zzl;
  
  static void zza(zzby paramzzby) {
    zzl = paramzzby;
  }
  
  static void zza(zzq paramzzq) {
    zzfq = paramzzq;
    zza.zzcv();
  }
  
  @VisibleForTesting
  static void zza(Exception paramException) {
    if (zzl == null)
      return; 
    Context context = zzl.getContext();
    if (zzfx == null) {
      boolean bool;
      if (GoogleApiAvailabilityLight.getInstance().isGooglePlayServicesAvailable(context, 12451000) == 0) {
        bool = true;
      } else {
        bool = false;
      } 
      zzfx = Boolean.valueOf(bool);
    } 
    if (zzfx.booleanValue())
      zzl.zzad().zzda().zza("Got Exception on PhenotypeFlag.get on Play device", paramException); 
  }
  
  public static Map<String, String> zzk(Context paramContext) {
    return zzcl.zza(paramContext.getContentResolver(), zzcv.zzcd("com.google.android.gms.measurement")).zzjj();
  }
  
  @VisibleForTesting
  public static final class zza<V> {
    private zzcw<V> zzjb;
    
    private final V zzjc;
    
    private final V zzjd;
    
    private volatile V zzje;
    
    private final String zzjf;
    
    private zza(String param1String, V param1V1, V param1V2) {
      this.zzjf = param1String;
      this.zzjd = param1V1;
      this.zzjc = param1V2;
    }
    
    static zza<Double> zza(String param1String, double param1Double1, double param1Double2) {
      zza<Double> zza1 = new zza<Double>(param1String, Double.valueOf(-3.0D), Double.valueOf(-3.0D));
      zzal.zzfv.add(zza1);
      return zza1;
    }
    
    static zza<Long> zza(String param1String, long param1Long1, long param1Long2) {
      zza<Long> zza1 = new zza<Long>(param1String, Long.valueOf(param1Long1), Long.valueOf(param1Long2));
      zzal.zzfs.add(zza1);
      return zza1;
    }
    
    static zza<Boolean> zza(String param1String, boolean param1Boolean1, boolean param1Boolean2) {
      zza<Boolean> zza1 = new zza<Boolean>(param1String, Boolean.valueOf(param1Boolean1), Boolean.valueOf(param1Boolean2));
      zzal.zzft.add(zza1);
      return zza1;
    }
    
    private static void zzai() {
      // Byte code:
      //   0: ldc com/google/android/gms/measurement/internal/zzal$zza
      //   2: monitorenter
      //   3: getstatic com/google/android/gms/measurement/internal/zzal.zzft : Ljava/util/List;
      //   6: invokeinterface iterator : ()Ljava/util/Iterator;
      //   11: astore_0
      //   12: aload_0
      //   13: invokeinterface hasNext : ()Z
      //   18: ifeq -> 67
      //   21: aload_0
      //   22: invokeinterface next : ()Ljava/lang/Object;
      //   27: checkcast com/google/android/gms/measurement/internal/zzal$zza
      //   30: astore_1
      //   31: invokestatic zzcu : ()Lcom/google/android/gms/internal/measurement/zzdc;
      //   34: astore_2
      //   35: aload_1
      //   36: getfield zzjf : Ljava/lang/String;
      //   39: astore_3
      //   40: getstatic com/google/android/gms/measurement/internal/zzal.zzfq : Lcom/google/android/gms/measurement/internal/zzq;
      //   43: astore #4
      //   45: aload_1
      //   46: aload_2
      //   47: aload_3
      //   48: aload_1
      //   49: getfield zzjd : Ljava/lang/Object;
      //   52: checkcast java/lang/Boolean
      //   55: invokevirtual booleanValue : ()Z
      //   58: invokevirtual zzb : (Ljava/lang/String;Z)Lcom/google/android/gms/internal/measurement/zzcw;
      //   61: putfield zzjb : Lcom/google/android/gms/internal/measurement/zzcw;
      //   64: goto -> 12
      //   67: getstatic com/google/android/gms/measurement/internal/zzal.zzfu : Ljava/util/List;
      //   70: invokeinterface iterator : ()Ljava/util/Iterator;
      //   75: astore_0
      //   76: aload_0
      //   77: invokeinterface hasNext : ()Z
      //   82: ifeq -> 128
      //   85: aload_0
      //   86: invokeinterface next : ()Ljava/lang/Object;
      //   91: checkcast com/google/android/gms/measurement/internal/zzal$zza
      //   94: astore_2
      //   95: invokestatic zzcu : ()Lcom/google/android/gms/internal/measurement/zzdc;
      //   98: astore_3
      //   99: aload_2
      //   100: getfield zzjf : Ljava/lang/String;
      //   103: astore_1
      //   104: getstatic com/google/android/gms/measurement/internal/zzal.zzfq : Lcom/google/android/gms/measurement/internal/zzq;
      //   107: astore #4
      //   109: aload_2
      //   110: aload_3
      //   111: aload_1
      //   112: aload_2
      //   113: getfield zzjd : Ljava/lang/Object;
      //   116: checkcast java/lang/String
      //   119: invokevirtual zzt : (Ljava/lang/String;Ljava/lang/String;)Lcom/google/android/gms/internal/measurement/zzcw;
      //   122: putfield zzjb : Lcom/google/android/gms/internal/measurement/zzcw;
      //   125: goto -> 76
      //   128: getstatic com/google/android/gms/measurement/internal/zzal.zzfs : Ljava/util/List;
      //   131: invokeinterface iterator : ()Ljava/util/Iterator;
      //   136: astore_0
      //   137: aload_0
      //   138: invokeinterface hasNext : ()Z
      //   143: ifeq -> 193
      //   146: aload_0
      //   147: invokeinterface next : ()Ljava/lang/Object;
      //   152: checkcast com/google/android/gms/measurement/internal/zzal$zza
      //   155: astore_2
      //   156: invokestatic zzcu : ()Lcom/google/android/gms/internal/measurement/zzdc;
      //   159: astore_1
      //   160: aload_2
      //   161: getfield zzjf : Ljava/lang/String;
      //   164: astore #4
      //   166: getstatic com/google/android/gms/measurement/internal/zzal.zzfq : Lcom/google/android/gms/measurement/internal/zzq;
      //   169: astore_3
      //   170: aload_2
      //   171: aload_1
      //   172: aload #4
      //   174: aload_2
      //   175: getfield zzjd : Ljava/lang/Object;
      //   178: checkcast java/lang/Long
      //   181: invokevirtual longValue : ()J
      //   184: invokevirtual zze : (Ljava/lang/String;J)Lcom/google/android/gms/internal/measurement/zzcw;
      //   187: putfield zzjb : Lcom/google/android/gms/internal/measurement/zzcw;
      //   190: goto -> 137
      //   193: getstatic com/google/android/gms/measurement/internal/zzal.zzfr : Ljava/util/List;
      //   196: invokeinterface iterator : ()Ljava/util/Iterator;
      //   201: astore_2
      //   202: aload_2
      //   203: invokeinterface hasNext : ()Z
      //   208: ifeq -> 258
      //   211: aload_2
      //   212: invokeinterface next : ()Ljava/lang/Object;
      //   217: checkcast com/google/android/gms/measurement/internal/zzal$zza
      //   220: astore_0
      //   221: invokestatic zzcu : ()Lcom/google/android/gms/internal/measurement/zzdc;
      //   224: astore_3
      //   225: aload_0
      //   226: getfield zzjf : Ljava/lang/String;
      //   229: astore #4
      //   231: getstatic com/google/android/gms/measurement/internal/zzal.zzfq : Lcom/google/android/gms/measurement/internal/zzq;
      //   234: astore_1
      //   235: aload_0
      //   236: aload_3
      //   237: aload #4
      //   239: aload_0
      //   240: getfield zzjd : Ljava/lang/Object;
      //   243: checkcast java/lang/Integer
      //   246: invokevirtual intValue : ()I
      //   249: invokevirtual zza : (Ljava/lang/String;I)Lcom/google/android/gms/internal/measurement/zzcw;
      //   252: putfield zzjb : Lcom/google/android/gms/internal/measurement/zzcw;
      //   255: goto -> 202
      //   258: getstatic com/google/android/gms/measurement/internal/zzal.zzfv : Ljava/util/List;
      //   261: invokeinterface iterator : ()Ljava/util/Iterator;
      //   266: astore_1
      //   267: aload_1
      //   268: invokeinterface hasNext : ()Z
      //   273: ifeq -> 325
      //   276: aload_1
      //   277: invokeinterface next : ()Ljava/lang/Object;
      //   282: checkcast com/google/android/gms/measurement/internal/zzal$zza
      //   285: astore #4
      //   287: invokestatic zzcu : ()Lcom/google/android/gms/internal/measurement/zzdc;
      //   290: astore_3
      //   291: aload #4
      //   293: getfield zzjf : Ljava/lang/String;
      //   296: astore_2
      //   297: getstatic com/google/android/gms/measurement/internal/zzal.zzfq : Lcom/google/android/gms/measurement/internal/zzq;
      //   300: astore_0
      //   301: aload #4
      //   303: aload_3
      //   304: aload_2
      //   305: aload #4
      //   307: getfield zzjd : Ljava/lang/Object;
      //   310: checkcast java/lang/Double
      //   313: invokevirtual doubleValue : ()D
      //   316: invokevirtual zza : (Ljava/lang/String;D)Lcom/google/android/gms/internal/measurement/zzcw;
      //   319: putfield zzjb : Lcom/google/android/gms/internal/measurement/zzcw;
      //   322: goto -> 267
      //   325: ldc com/google/android/gms/measurement/internal/zzal$zza
      //   327: monitorexit
      //   328: return
      //   329: astore_0
      //   330: ldc com/google/android/gms/measurement/internal/zzal$zza
      //   332: monitorexit
      //   333: aload_0
      //   334: athrow
      // Exception table:
      //   from	to	target	type
      //   3	12	329	finally
      //   12	64	329	finally
      //   67	76	329	finally
      //   76	125	329	finally
      //   128	137	329	finally
      //   137	190	329	finally
      //   193	202	329	finally
      //   202	255	329	finally
      //   258	267	329	finally
      //   267	322	329	finally
      //   325	328	329	finally
      //   330	333	329	finally
    }
    
    static zza<Integer> zzb(String param1String, int param1Int1, int param1Int2) {
      zza<Integer> zza1 = new zza<Integer>(param1String, Integer.valueOf(param1Int1), Integer.valueOf(param1Int2));
      zzal.zzfr.add(zza1);
      return zza1;
    }
    
    static zza<String> zzc(String param1String1, String param1String2, String param1String3) {
      zza<String> zza1 = new zza<String>(param1String1, param1String2, param1String3);
      zzal.zzfu.add(zza1);
      return zza1;
    }
    
    public final V get(V param1V) {
      // Byte code:
      //   0: aload_1
      //   1: ifnull -> 6
      //   4: aload_1
      //   5: areturn
      //   6: getstatic com/google/android/gms/measurement/internal/zzal.zzfq : Lcom/google/android/gms/measurement/internal/zzq;
      //   9: ifnonnull -> 17
      //   12: aload_0
      //   13: getfield zzjd : Ljava/lang/Object;
      //   16: areturn
      //   17: getstatic com/google/android/gms/measurement/internal/zzal.zzfq : Lcom/google/android/gms/measurement/internal/zzq;
      //   20: astore_1
      //   21: invokestatic isMainThread : ()Z
      //   24: ifeq -> 44
      //   27: aload_0
      //   28: getfield zzje : Ljava/lang/Object;
      //   31: ifnonnull -> 39
      //   34: aload_0
      //   35: getfield zzjd : Ljava/lang/Object;
      //   38: areturn
      //   39: aload_0
      //   40: getfield zzje : Ljava/lang/Object;
      //   43: areturn
      //   44: ldc com/google/android/gms/measurement/internal/zzal$zza
      //   46: monitorenter
      //   47: invokestatic isMainThread : ()Z
      //   50: ifne -> 298
      //   53: getstatic com/google/android/gms/measurement/internal/zzal.zzfq : Lcom/google/android/gms/measurement/internal/zzq;
      //   56: astore_1
      //   57: getstatic com/google/android/gms/measurement/internal/zzal.zzft : Ljava/util/List;
      //   60: invokeinterface iterator : ()Ljava/util/Iterator;
      //   65: astore_2
      //   66: aload_2
      //   67: invokeinterface hasNext : ()Z
      //   72: ifeq -> 99
      //   75: aload_2
      //   76: invokeinterface next : ()Ljava/lang/Object;
      //   81: checkcast com/google/android/gms/measurement/internal/zzal$zza
      //   84: astore_1
      //   85: aload_1
      //   86: aload_1
      //   87: getfield zzjb : Lcom/google/android/gms/internal/measurement/zzcw;
      //   90: invokevirtual get : ()Ljava/lang/Object;
      //   93: putfield zzje : Ljava/lang/Object;
      //   96: goto -> 66
      //   99: getstatic com/google/android/gms/measurement/internal/zzal.zzfu : Ljava/util/List;
      //   102: invokeinterface iterator : ()Ljava/util/Iterator;
      //   107: astore_1
      //   108: aload_1
      //   109: invokeinterface hasNext : ()Z
      //   114: ifeq -> 141
      //   117: aload_1
      //   118: invokeinterface next : ()Ljava/lang/Object;
      //   123: checkcast com/google/android/gms/measurement/internal/zzal$zza
      //   126: astore_2
      //   127: aload_2
      //   128: aload_2
      //   129: getfield zzjb : Lcom/google/android/gms/internal/measurement/zzcw;
      //   132: invokevirtual get : ()Ljava/lang/Object;
      //   135: putfield zzje : Ljava/lang/Object;
      //   138: goto -> 108
      //   141: getstatic com/google/android/gms/measurement/internal/zzal.zzfs : Ljava/util/List;
      //   144: invokeinterface iterator : ()Ljava/util/Iterator;
      //   149: astore_2
      //   150: aload_2
      //   151: invokeinterface hasNext : ()Z
      //   156: ifeq -> 183
      //   159: aload_2
      //   160: invokeinterface next : ()Ljava/lang/Object;
      //   165: checkcast com/google/android/gms/measurement/internal/zzal$zza
      //   168: astore_1
      //   169: aload_1
      //   170: aload_1
      //   171: getfield zzjb : Lcom/google/android/gms/internal/measurement/zzcw;
      //   174: invokevirtual get : ()Ljava/lang/Object;
      //   177: putfield zzje : Ljava/lang/Object;
      //   180: goto -> 150
      //   183: getstatic com/google/android/gms/measurement/internal/zzal.zzfr : Ljava/util/List;
      //   186: invokeinterface iterator : ()Ljava/util/Iterator;
      //   191: astore_1
      //   192: aload_1
      //   193: invokeinterface hasNext : ()Z
      //   198: ifeq -> 225
      //   201: aload_1
      //   202: invokeinterface next : ()Ljava/lang/Object;
      //   207: checkcast com/google/android/gms/measurement/internal/zzal$zza
      //   210: astore_2
      //   211: aload_2
      //   212: aload_2
      //   213: getfield zzjb : Lcom/google/android/gms/internal/measurement/zzcw;
      //   216: invokevirtual get : ()Ljava/lang/Object;
      //   219: putfield zzje : Ljava/lang/Object;
      //   222: goto -> 192
      //   225: getstatic com/google/android/gms/measurement/internal/zzal.zzfv : Ljava/util/List;
      //   228: invokeinterface iterator : ()Ljava/util/Iterator;
      //   233: astore_2
      //   234: aload_2
      //   235: invokeinterface hasNext : ()Z
      //   240: ifeq -> 272
      //   243: aload_2
      //   244: invokeinterface next : ()Ljava/lang/Object;
      //   249: checkcast com/google/android/gms/measurement/internal/zzal$zza
      //   252: astore_1
      //   253: aload_1
      //   254: aload_1
      //   255: getfield zzjb : Lcom/google/android/gms/internal/measurement/zzcw;
      //   258: invokevirtual get : ()Ljava/lang/Object;
      //   261: putfield zzje : Ljava/lang/Object;
      //   264: goto -> 234
      //   267: astore_1
      //   268: aload_1
      //   269: invokestatic zza : (Ljava/lang/Exception;)V
      //   272: ldc com/google/android/gms/measurement/internal/zzal$zza
      //   274: monitorexit
      //   275: aload_0
      //   276: getfield zzjb : Lcom/google/android/gms/internal/measurement/zzcw;
      //   279: invokevirtual get : ()Ljava/lang/Object;
      //   282: astore_1
      //   283: aload_1
      //   284: areturn
      //   285: astore_1
      //   286: aload_1
      //   287: invokestatic zza : (Ljava/lang/Exception;)V
      //   290: aload_0
      //   291: getfield zzjb : Lcom/google/android/gms/internal/measurement/zzcw;
      //   294: invokevirtual getDefaultValue : ()Ljava/lang/Object;
      //   297: areturn
      //   298: new java/lang/IllegalStateException
      //   301: astore_1
      //   302: aload_1
      //   303: ldc 'Tried to refresh flag cache on main thread or on package side.'
      //   305: invokespecial <init> : (Ljava/lang/String;)V
      //   308: aload_1
      //   309: athrow
      //   310: astore_1
      //   311: ldc com/google/android/gms/measurement/internal/zzal$zza
      //   313: monitorexit
      //   314: aload_1
      //   315: athrow
      // Exception table:
      //   from	to	target	type
      //   47	57	310	finally
      //   57	66	267	java/lang/SecurityException
      //   57	66	310	finally
      //   66	96	267	java/lang/SecurityException
      //   66	96	310	finally
      //   99	108	267	java/lang/SecurityException
      //   99	108	310	finally
      //   108	138	267	java/lang/SecurityException
      //   108	138	310	finally
      //   141	150	267	java/lang/SecurityException
      //   141	150	310	finally
      //   150	180	267	java/lang/SecurityException
      //   150	180	310	finally
      //   183	192	267	java/lang/SecurityException
      //   183	192	310	finally
      //   192	222	267	java/lang/SecurityException
      //   192	222	310	finally
      //   225	234	267	java/lang/SecurityException
      //   225	234	310	finally
      //   234	264	267	java/lang/SecurityException
      //   234	264	310	finally
      //   268	272	310	finally
      //   272	275	310	finally
      //   275	283	285	java/lang/SecurityException
      //   298	310	310	finally
      //   311	314	310	finally
    }
    
    public final String getKey() {
      return this.zzjf;
    }
  }
}


/* Location:              Y:\classes-dex2jar.jar!\com\google\android\gms\measurement\internal\zzal.class
 * Java compiler version: 6 (50.0)
 * JD-Core Version:       1.1.3
 */