package com.google.android.gms.measurement.internal;

import android.content.ServiceConnection;
import com.google.android.gms.internal.measurement.zze;

final class zzbn implements Runnable {
  zzbn(zzbm paramzzbm, zze paramzze, ServiceConnection paramServiceConnection) {}
  
  public final void run() {
    // Byte code:
    //   0: aload_0
    //   1: getfield zzmi : Lcom/google/android/gms/measurement/internal/zzbm;
    //   4: getfield zzmf : Lcom/google/android/gms/measurement/internal/zzbl;
    //   7: astore_1
    //   8: aload_0
    //   9: getfield zzmi : Lcom/google/android/gms/measurement/internal/zzbm;
    //   12: invokestatic zza : (Lcom/google/android/gms/measurement/internal/zzbm;)Ljava/lang/String;
    //   15: astore_2
    //   16: aload_0
    //   17: getfield zzmg : Lcom/google/android/gms/internal/measurement/zze;
    //   20: astore_3
    //   21: aload_0
    //   22: getfield zzmh : Landroid/content/ServiceConnection;
    //   25: astore #4
    //   27: aload_1
    //   28: aload_2
    //   29: aload_3
    //   30: invokevirtual zza : (Ljava/lang/String;Lcom/google/android/gms/internal/measurement/zze;)Landroid/os/Bundle;
    //   33: astore_3
    //   34: aload_1
    //   35: getfield zzl : Lcom/google/android/gms/measurement/internal/zzby;
    //   38: invokevirtual zzac : ()Lcom/google/android/gms/measurement/internal/zzbt;
    //   41: invokevirtual zzq : ()V
    //   44: aload_3
    //   45: ifnull -> 415
    //   48: aload_3
    //   49: ldc 'install_begin_timestamp_seconds'
    //   51: lconst_0
    //   52: invokevirtual getLong : (Ljava/lang/String;J)J
    //   55: ldc2_w 1000
    //   58: lmul
    //   59: lstore #5
    //   61: lload #5
    //   63: lconst_0
    //   64: lcmp
    //   65: ifne -> 86
    //   68: aload_1
    //   69: getfield zzl : Lcom/google/android/gms/measurement/internal/zzby;
    //   72: invokevirtual zzad : ()Lcom/google/android/gms/measurement/internal/zzau;
    //   75: invokevirtual zzda : ()Lcom/google/android/gms/measurement/internal/zzaw;
    //   78: ldc 'Service response is missing Install Referrer install timestamp'
    //   80: invokevirtual zzaq : (Ljava/lang/String;)V
    //   83: goto -> 415
    //   86: aload_3
    //   87: ldc 'install_referrer'
    //   89: invokevirtual getString : (Ljava/lang/String;)Ljava/lang/String;
    //   92: astore_2
    //   93: aload_2
    //   94: ifnull -> 400
    //   97: aload_2
    //   98: invokevirtual isEmpty : ()Z
    //   101: ifeq -> 107
    //   104: goto -> 400
    //   107: aload_1
    //   108: getfield zzl : Lcom/google/android/gms/measurement/internal/zzby;
    //   111: invokevirtual zzad : ()Lcom/google/android/gms/measurement/internal/zzau;
    //   114: invokevirtual zzdi : ()Lcom/google/android/gms/measurement/internal/zzaw;
    //   117: ldc 'InstallReferrer API result'
    //   119: aload_2
    //   120: invokevirtual zza : (Ljava/lang/String;Ljava/lang/Object;)V
    //   123: aload_1
    //   124: getfield zzl : Lcom/google/android/gms/measurement/internal/zzby;
    //   127: invokevirtual zzab : ()Lcom/google/android/gms/measurement/internal/zzgd;
    //   130: astore #7
    //   132: aload_2
    //   133: invokestatic valueOf : (Ljava/lang/Object;)Ljava/lang/String;
    //   136: astore_2
    //   137: aload_2
    //   138: invokevirtual length : ()I
    //   141: ifeq -> 154
    //   144: ldc '?'
    //   146: aload_2
    //   147: invokevirtual concat : (Ljava/lang/String;)Ljava/lang/String;
    //   150: astore_2
    //   151: goto -> 164
    //   154: new java/lang/String
    //   157: dup
    //   158: ldc '?'
    //   160: invokespecial <init> : (Ljava/lang/String;)V
    //   163: astore_2
    //   164: aload #7
    //   166: aload_2
    //   167: invokestatic parse : (Ljava/lang/String;)Landroid/net/Uri;
    //   170: invokevirtual zza : (Landroid/net/Uri;)Landroid/os/Bundle;
    //   173: astore_2
    //   174: aload_2
    //   175: ifnonnull -> 196
    //   178: aload_1
    //   179: getfield zzl : Lcom/google/android/gms/measurement/internal/zzby;
    //   182: invokevirtual zzad : ()Lcom/google/android/gms/measurement/internal/zzau;
    //   185: invokevirtual zzda : ()Lcom/google/android/gms/measurement/internal/zzaw;
    //   188: ldc 'No campaign params defined in install referrer result'
    //   190: invokevirtual zzaq : (Ljava/lang/String;)V
    //   193: goto -> 415
    //   196: aload_2
    //   197: ldc 'medium'
    //   199: invokevirtual getString : (Ljava/lang/String;)Ljava/lang/String;
    //   202: astore #7
    //   204: aload #7
    //   206: ifnull -> 235
    //   209: ldc '(not set)'
    //   211: aload #7
    //   213: invokevirtual equalsIgnoreCase : (Ljava/lang/String;)Z
    //   216: ifne -> 235
    //   219: ldc 'organic'
    //   221: aload #7
    //   223: invokevirtual equalsIgnoreCase : (Ljava/lang/String;)Z
    //   226: ifne -> 235
    //   229: iconst_1
    //   230: istore #8
    //   232: goto -> 238
    //   235: iconst_0
    //   236: istore #8
    //   238: iload #8
    //   240: ifeq -> 289
    //   243: aload_3
    //   244: ldc 'referrer_click_timestamp_seconds'
    //   246: lconst_0
    //   247: invokevirtual getLong : (Ljava/lang/String;J)J
    //   250: ldc2_w 1000
    //   253: lmul
    //   254: lstore #9
    //   256: lload #9
    //   258: lconst_0
    //   259: lcmp
    //   260: ifne -> 281
    //   263: aload_1
    //   264: getfield zzl : Lcom/google/android/gms/measurement/internal/zzby;
    //   267: invokevirtual zzad : ()Lcom/google/android/gms/measurement/internal/zzau;
    //   270: invokevirtual zzda : ()Lcom/google/android/gms/measurement/internal/zzaw;
    //   273: ldc 'Install Referrer is missing click timestamp for ad campaign'
    //   275: invokevirtual zzaq : (Ljava/lang/String;)V
    //   278: goto -> 415
    //   281: aload_2
    //   282: ldc 'click_timestamp'
    //   284: lload #9
    //   286: invokevirtual putLong : (Ljava/lang/String;J)V
    //   289: lload #5
    //   291: aload_1
    //   292: getfield zzl : Lcom/google/android/gms/measurement/internal/zzby;
    //   295: invokevirtual zzae : ()Lcom/google/android/gms/measurement/internal/zzbf;
    //   298: getfield zzlh : Lcom/google/android/gms/measurement/internal/zzbi;
    //   301: invokevirtual get : ()J
    //   304: lcmp
    //   305: ifne -> 334
    //   308: aload_1
    //   309: getfield zzl : Lcom/google/android/gms/measurement/internal/zzby;
    //   312: invokevirtual zzag : ()Lcom/google/android/gms/measurement/internal/zzq;
    //   315: pop
    //   316: aload_1
    //   317: getfield zzl : Lcom/google/android/gms/measurement/internal/zzby;
    //   320: invokevirtual zzad : ()Lcom/google/android/gms/measurement/internal/zzau;
    //   323: invokevirtual zzdi : ()Lcom/google/android/gms/measurement/internal/zzaw;
    //   326: ldc 'Campaign has already been logged'
    //   328: invokevirtual zzaq : (Ljava/lang/String;)V
    //   331: goto -> 415
    //   334: aload_1
    //   335: getfield zzl : Lcom/google/android/gms/measurement/internal/zzby;
    //   338: invokevirtual zzae : ()Lcom/google/android/gms/measurement/internal/zzbf;
    //   341: getfield zzlh : Lcom/google/android/gms/measurement/internal/zzbi;
    //   344: lload #5
    //   346: invokevirtual set : (J)V
    //   349: aload_1
    //   350: getfield zzl : Lcom/google/android/gms/measurement/internal/zzby;
    //   353: invokevirtual zzag : ()Lcom/google/android/gms/measurement/internal/zzq;
    //   356: pop
    //   357: aload_1
    //   358: getfield zzl : Lcom/google/android/gms/measurement/internal/zzby;
    //   361: invokevirtual zzad : ()Lcom/google/android/gms/measurement/internal/zzau;
    //   364: invokevirtual zzdi : ()Lcom/google/android/gms/measurement/internal/zzaw;
    //   367: ldc 'Logging Install Referrer campaign from sdk with '
    //   369: ldc 'referrer API'
    //   371: invokevirtual zza : (Ljava/lang/String;Ljava/lang/Object;)V
    //   374: aload_2
    //   375: ldc '_cis'
    //   377: ldc 'referrer API'
    //   379: invokevirtual putString : (Ljava/lang/String;Ljava/lang/String;)V
    //   382: aload_1
    //   383: getfield zzl : Lcom/google/android/gms/measurement/internal/zzby;
    //   386: invokevirtual zzs : ()Lcom/google/android/gms/measurement/internal/zzdd;
    //   389: ldc 'auto'
    //   391: ldc '_cmp'
    //   393: aload_2
    //   394: invokevirtual logEvent : (Ljava/lang/String;Ljava/lang/String;Landroid/os/Bundle;)V
    //   397: goto -> 415
    //   400: aload_1
    //   401: getfield zzl : Lcom/google/android/gms/measurement/internal/zzby;
    //   404: invokevirtual zzad : ()Lcom/google/android/gms/measurement/internal/zzau;
    //   407: invokevirtual zzda : ()Lcom/google/android/gms/measurement/internal/zzaw;
    //   410: ldc 'No referrer defined in install referrer response'
    //   412: invokevirtual zzaq : (Ljava/lang/String;)V
    //   415: aload #4
    //   417: ifnull -> 435
    //   420: invokestatic getInstance : ()Lcom/google/android/gms/common/stats/ConnectionTracker;
    //   423: aload_1
    //   424: getfield zzl : Lcom/google/android/gms/measurement/internal/zzby;
    //   427: invokevirtual getContext : ()Landroid/content/Context;
    //   430: aload #4
    //   432: invokevirtual unbindService : (Landroid/content/Context;Landroid/content/ServiceConnection;)V
    //   435: return
  }
}


/* Location:              Y:\classes-dex2jar.jar!\com\google\android\gms\measurement\internal\zzbn.class
 * Java compiler version: 6 (50.0)
 * JD-Core Version:       1.1.3
 */