package com.google.android.gms.measurement.internal;

import android.content.BroadcastReceiver;
import android.content.Context;
import android.os.Bundle;

final class zzbq implements Runnable {
  zzbq(zzbo paramzzbo, zzby paramzzby, long paramLong, Bundle paramBundle, Context paramContext, zzau paramzzau) {}
  
  public final void run() {
    // Byte code:
    //   0: aload_0
    //   1: getfield zzmk : Lcom/google/android/gms/measurement/internal/zzby;
    //   4: invokevirtual zzae : ()Lcom/google/android/gms/measurement/internal/zzbf;
    //   7: getfield zzlg : Lcom/google/android/gms/measurement/internal/zzbi;
    //   10: invokevirtual get : ()J
    //   13: lstore_1
    //   14: aload_0
    //   15: getfield zzmm : J
    //   18: lstore_3
    //   19: lload_3
    //   20: lstore #5
    //   22: lload_1
    //   23: lconst_0
    //   24: lcmp
    //   25: ifle -> 48
    //   28: lload_3
    //   29: lload_1
    //   30: lcmp
    //   31: ifge -> 43
    //   34: lload_3
    //   35: lstore #5
    //   37: lload_3
    //   38: lconst_0
    //   39: lcmp
    //   40: ifgt -> 48
    //   43: lload_1
    //   44: lconst_1
    //   45: lsub
    //   46: lstore #5
    //   48: lload #5
    //   50: lconst_0
    //   51: lcmp
    //   52: ifle -> 66
    //   55: aload_0
    //   56: getfield zzmn : Landroid/os/Bundle;
    //   59: ldc 'click_timestamp'
    //   61: lload #5
    //   63: invokevirtual putLong : (Ljava/lang/String;J)V
    //   66: aload_0
    //   67: getfield zzmn : Landroid/os/Bundle;
    //   70: ldc '_cis'
    //   72: ldc 'referrer broadcast'
    //   74: invokevirtual putString : (Ljava/lang/String;Ljava/lang/String;)V
    //   77: aload_0
    //   78: getfield val$context : Landroid/content/Context;
    //   81: aconst_null
    //   82: invokestatic zza : (Landroid/content/Context;Lcom/google/android/gms/internal/measurement/zzy;)Lcom/google/android/gms/measurement/internal/zzby;
    //   85: invokevirtual zzs : ()Lcom/google/android/gms/measurement/internal/zzdd;
    //   88: ldc 'auto'
    //   90: ldc '_cmp'
    //   92: aload_0
    //   93: getfield zzmn : Landroid/os/Bundle;
    //   96: invokevirtual logEvent : (Ljava/lang/String;Ljava/lang/String;Landroid/os/Bundle;)V
    //   99: aload_0
    //   100: getfield zzml : Lcom/google/android/gms/measurement/internal/zzau;
    //   103: invokevirtual zzdi : ()Lcom/google/android/gms/measurement/internal/zzaw;
    //   106: ldc 'Install campaign recorded'
    //   108: invokevirtual zzaq : (Ljava/lang/String;)V
    //   111: aload_0
    //   112: getfield zzmo : Landroid/content/BroadcastReceiver$PendingResult;
    //   115: astore #7
    //   117: aload #7
    //   119: ifnull -> 127
    //   122: aload #7
    //   124: invokevirtual finish : ()V
    //   127: return
  }
}


/* Location:              Y:\classes-dex2jar.jar!\com\google\android\gms\measurement\internal\zzbq.class
 * Java compiler version: 6 (50.0)
 * JD-Core Version:       1.1.3
 */