package com.google.android.gms.measurement.internal;

import android.support.annotation.NonNull;
import android.support.annotation.Size;
import android.support.annotation.WorkerThread;

final class zzea extends zzfs {
  public zzea(zzft paramzzft) {
    super(paramzzft);
  }
  
  private static String zzo(String paramString1, String paramString2) {
    throw new SecurityException("This implementation should not be used.");
  }
  
  protected final boolean zzak() {
    return false;
  }
  
  @WorkerThread
  public final byte[] zzb(@NonNull zzaj paramzzaj, @Size(min = 1L) String paramString) {
    // Byte code:
    //   0: aload_0
    //   1: invokevirtual zzq : ()V
    //   4: aload_0
    //   5: getfield zzl : Lcom/google/android/gms/measurement/internal/zzby;
    //   8: invokevirtual zzn : ()V
    //   11: aload_1
    //   12: invokestatic checkNotNull : (Ljava/lang/Object;)Ljava/lang/Object;
    //   15: pop
    //   16: aload_2
    //   17: invokestatic checkNotEmpty : (Ljava/lang/String;)Ljava/lang/String;
    //   20: pop
    //   21: aload_0
    //   22: invokevirtual zzaf : ()Lcom/google/android/gms/measurement/internal/zzt;
    //   25: aload_2
    //   26: getstatic com/google/android/gms/measurement/internal/zzal.zzir : Lcom/google/android/gms/measurement/internal/zzal$zza;
    //   29: invokevirtual zze : (Ljava/lang/String;Lcom/google/android/gms/measurement/internal/zzal$zza;)Z
    //   32: ifne -> 52
    //   35: aload_0
    //   36: invokevirtual zzad : ()Lcom/google/android/gms/measurement/internal/zzau;
    //   39: invokevirtual zzdh : ()Lcom/google/android/gms/measurement/internal/zzaw;
    //   42: ldc 'Generating ScionPayload disabled. packageName'
    //   44: aload_2
    //   45: invokevirtual zza : (Ljava/lang/String;Ljava/lang/Object;)V
    //   48: iconst_0
    //   49: newarray byte
    //   51: areturn
    //   52: ldc '_iap'
    //   54: aload_1
    //   55: getfield name : Ljava/lang/String;
    //   58: invokevirtual equals : (Ljava/lang/Object;)Z
    //   61: ifne -> 95
    //   64: ldc '_iapx'
    //   66: aload_1
    //   67: getfield name : Ljava/lang/String;
    //   70: invokevirtual equals : (Ljava/lang/Object;)Z
    //   73: ifne -> 95
    //   76: aload_0
    //   77: invokevirtual zzad : ()Lcom/google/android/gms/measurement/internal/zzau;
    //   80: invokevirtual zzdh : ()Lcom/google/android/gms/measurement/internal/zzaw;
    //   83: ldc 'Generating a payload for this event is not available. package_name, event_name'
    //   85: aload_2
    //   86: aload_1
    //   87: getfield name : Ljava/lang/String;
    //   90: invokevirtual zza : (Ljava/lang/String;Ljava/lang/Object;Ljava/lang/Object;)V
    //   93: aconst_null
    //   94: areturn
    //   95: new com/google/android/gms/internal/measurement/zzcg
    //   98: dup
    //   99: invokespecial <init> : ()V
    //   102: astore_3
    //   103: aload_0
    //   104: invokevirtual zzdo : ()Lcom/google/android/gms/measurement/internal/zzw;
    //   107: invokevirtual beginTransaction : ()V
    //   110: aload_0
    //   111: invokevirtual zzdo : ()Lcom/google/android/gms/measurement/internal/zzw;
    //   114: aload_2
    //   115: invokevirtual zzae : (Ljava/lang/String;)Lcom/google/android/gms/measurement/internal/zzg;
    //   118: astore #4
    //   120: aload #4
    //   122: ifnonnull -> 149
    //   125: aload_0
    //   126: invokevirtual zzad : ()Lcom/google/android/gms/measurement/internal/zzau;
    //   129: invokevirtual zzdh : ()Lcom/google/android/gms/measurement/internal/zzaw;
    //   132: ldc 'Log and bundle not available. package_name'
    //   134: aload_2
    //   135: invokevirtual zza : (Ljava/lang/String;Ljava/lang/Object;)V
    //   138: aload_0
    //   139: invokevirtual zzdo : ()Lcom/google/android/gms/measurement/internal/zzw;
    //   142: invokevirtual endTransaction : ()V
    //   145: iconst_0
    //   146: newarray byte
    //   148: areturn
    //   149: aload #4
    //   151: invokevirtual isMeasurementEnabled : ()Z
    //   154: ifne -> 181
    //   157: aload_0
    //   158: invokevirtual zzad : ()Lcom/google/android/gms/measurement/internal/zzau;
    //   161: invokevirtual zzdh : ()Lcom/google/android/gms/measurement/internal/zzaw;
    //   164: ldc 'Log and bundle disabled. package_name'
    //   166: aload_2
    //   167: invokevirtual zza : (Ljava/lang/String;Ljava/lang/Object;)V
    //   170: aload_0
    //   171: invokevirtual zzdo : ()Lcom/google/android/gms/measurement/internal/zzw;
    //   174: invokevirtual endTransaction : ()V
    //   177: iconst_0
    //   178: newarray byte
    //   180: areturn
    //   181: new com/google/android/gms/internal/measurement/zzch
    //   184: astore #5
    //   186: aload #5
    //   188: invokespecial <init> : ()V
    //   191: aload_3
    //   192: iconst_1
    //   193: anewarray com/google/android/gms/internal/measurement/zzch
    //   196: dup
    //   197: iconst_0
    //   198: aload #5
    //   200: aastore
    //   201: putfield zzxl : [Lcom/google/android/gms/internal/measurement/zzch;
    //   204: aload #5
    //   206: iconst_1
    //   207: invokestatic valueOf : (I)Ljava/lang/Integer;
    //   210: putfield zzxn : Ljava/lang/Integer;
    //   213: aload #5
    //   215: ldc 'android'
    //   217: putfield zzxv : Ljava/lang/String;
    //   220: aload #5
    //   222: aload #4
    //   224: invokevirtual zzan : ()Ljava/lang/String;
    //   227: putfield zzcf : Ljava/lang/String;
    //   230: aload #5
    //   232: aload #4
    //   234: invokevirtual zzau : ()Ljava/lang/String;
    //   237: putfield zzcp : Ljava/lang/String;
    //   240: aload #5
    //   242: aload #4
    //   244: invokevirtual zzas : ()Ljava/lang/String;
    //   247: putfield zzcn : Ljava/lang/String;
    //   250: aload #4
    //   252: invokevirtual zzat : ()J
    //   255: lstore #6
    //   257: lload #6
    //   259: ldc2_w -2147483648
    //   262: lcmp
    //   263: ifne -> 272
    //   266: aconst_null
    //   267: astore #8
    //   269: goto -> 280
    //   272: lload #6
    //   274: l2i
    //   275: invokestatic valueOf : (I)Ljava/lang/Integer;
    //   278: astore #8
    //   280: aload #5
    //   282: aload #8
    //   284: putfield zzyh : Ljava/lang/Integer;
    //   287: aload #5
    //   289: aload #4
    //   291: invokevirtual zzav : ()J
    //   294: invokestatic valueOf : (J)Ljava/lang/Long;
    //   297: putfield zzxz : Ljava/lang/Long;
    //   300: aload #5
    //   302: aload #4
    //   304: invokevirtual zzax : ()J
    //   307: invokestatic valueOf : (J)Ljava/lang/Long;
    //   310: putfield zzys : Ljava/lang/Long;
    //   313: aload #5
    //   315: aload #4
    //   317: invokevirtual getGmpAppId : ()Ljava/lang/String;
    //   320: putfield zzch : Ljava/lang/String;
    //   323: aload #5
    //   325: getfield zzch : Ljava/lang/String;
    //   328: invokestatic isEmpty : (Ljava/lang/CharSequence;)Z
    //   331: ifeq -> 344
    //   334: aload #5
    //   336: aload #4
    //   338: invokevirtual zzao : ()Ljava/lang/String;
    //   341: putfield zzxf : Ljava/lang/String;
    //   344: aload #5
    //   346: aload #4
    //   348: invokevirtual zzaw : ()J
    //   351: invokestatic valueOf : (J)Ljava/lang/Long;
    //   354: putfield zzyd : Ljava/lang/Long;
    //   357: aload_0
    //   358: getfield zzl : Lcom/google/android/gms/measurement/internal/zzby;
    //   361: invokevirtual isEnabled : ()Z
    //   364: ifeq -> 394
    //   367: invokestatic zzbv : ()Z
    //   370: ifeq -> 394
    //   373: aload_0
    //   374: invokevirtual zzaf : ()Lcom/google/android/gms/measurement/internal/zzt;
    //   377: aload #5
    //   379: getfield zzcf : Ljava/lang/String;
    //   382: invokevirtual zzk : (Ljava/lang/String;)Z
    //   385: ifeq -> 394
    //   388: aload #5
    //   390: aconst_null
    //   391: putfield zzyn : Ljava/lang/String;
    //   394: aload_0
    //   395: invokevirtual zzae : ()Lcom/google/android/gms/measurement/internal/zzbf;
    //   398: aload #4
    //   400: invokevirtual zzan : ()Ljava/lang/String;
    //   403: invokevirtual zzar : (Ljava/lang/String;)Landroid/util/Pair;
    //   406: astore #8
    //   408: aload #4
    //   410: invokevirtual zzbl : ()Z
    //   413: ifeq -> 507
    //   416: aload #8
    //   418: ifnull -> 507
    //   421: aload #8
    //   423: getfield first : Ljava/lang/Object;
    //   426: checkcast java/lang/CharSequence
    //   429: invokestatic isEmpty : (Ljava/lang/CharSequence;)Z
    //   432: istore #9
    //   434: iload #9
    //   436: ifne -> 507
    //   439: aload #5
    //   441: aload #8
    //   443: getfield first : Ljava/lang/Object;
    //   446: checkcast java/lang/String
    //   449: aload_1
    //   450: getfield zzfp : J
    //   453: invokestatic toString : (J)Ljava/lang/String;
    //   456: invokestatic zzo : (Ljava/lang/String;Ljava/lang/String;)Ljava/lang/String;
    //   459: putfield zzyb : Ljava/lang/String;
    //   462: aload #5
    //   464: aload #8
    //   466: getfield second : Ljava/lang/Object;
    //   469: checkcast java/lang/Boolean
    //   472: putfield zzyc : Ljava/lang/Boolean;
    //   475: goto -> 507
    //   478: astore_1
    //   479: aload_0
    //   480: invokevirtual zzad : ()Lcom/google/android/gms/measurement/internal/zzau;
    //   483: invokevirtual zzdh : ()Lcom/google/android/gms/measurement/internal/zzaw;
    //   486: ldc_w 'Resettable device id encryption failed'
    //   489: aload_1
    //   490: invokevirtual getMessage : ()Ljava/lang/String;
    //   493: invokevirtual zza : (Ljava/lang/String;Ljava/lang/Object;)V
    //   496: aload_0
    //   497: invokevirtual zzdo : ()Lcom/google/android/gms/measurement/internal/zzw;
    //   500: invokevirtual endTransaction : ()V
    //   503: iconst_0
    //   504: newarray byte
    //   506: areturn
    //   507: aload_0
    //   508: invokevirtual zzy : ()Lcom/google/android/gms/measurement/internal/zzad;
    //   511: invokevirtual zzah : ()V
    //   514: aload #5
    //   516: getstatic android/os/Build.MODEL : Ljava/lang/String;
    //   519: putfield zzxx : Ljava/lang/String;
    //   522: aload_0
    //   523: invokevirtual zzy : ()Lcom/google/android/gms/measurement/internal/zzad;
    //   526: invokevirtual zzah : ()V
    //   529: aload #5
    //   531: getstatic android/os/Build$VERSION.RELEASE : Ljava/lang/String;
    //   534: putfield zzxw : Ljava/lang/String;
    //   537: aload #5
    //   539: aload_0
    //   540: invokevirtual zzy : ()Lcom/google/android/gms/measurement/internal/zzad;
    //   543: invokevirtual zzco : ()J
    //   546: l2i
    //   547: invokestatic valueOf : (I)Ljava/lang/Integer;
    //   550: putfield zzxy : Ljava/lang/Integer;
    //   553: aload #5
    //   555: aload_0
    //   556: invokevirtual zzy : ()Lcom/google/android/gms/measurement/internal/zzad;
    //   559: invokevirtual zzcp : ()Ljava/lang/String;
    //   562: putfield zzex : Ljava/lang/String;
    //   565: aload #5
    //   567: aload #4
    //   569: invokevirtual getAppInstanceId : ()Ljava/lang/String;
    //   572: aload_1
    //   573: getfield zzfp : J
    //   576: invokestatic toString : (J)Ljava/lang/String;
    //   579: invokestatic zzo : (Ljava/lang/String;Ljava/lang/String;)Ljava/lang/String;
    //   582: putfield zzcg : Ljava/lang/String;
    //   585: aload #5
    //   587: aload #4
    //   589: invokevirtual getFirebaseInstanceId : ()Ljava/lang/String;
    //   592: putfield zzcj : Ljava/lang/String;
    //   595: aload #4
    //   597: invokevirtual zzan : ()Ljava/lang/String;
    //   600: astore #10
    //   602: aload_0
    //   603: invokevirtual zzdo : ()Lcom/google/android/gms/measurement/internal/zzw;
    //   606: aload #10
    //   608: invokevirtual zzad : (Ljava/lang/String;)Ljava/util/List;
    //   611: astore #11
    //   613: aload_0
    //   614: invokevirtual zzaf : ()Lcom/google/android/gms/measurement/internal/zzt;
    //   617: aload #10
    //   619: invokevirtual zzm : (Ljava/lang/String;)Z
    //   622: ifeq -> 740
    //   625: aload #11
    //   627: invokeinterface iterator : ()Ljava/util/Iterator;
    //   632: astore #12
    //   634: aload #12
    //   636: invokeinterface hasNext : ()Z
    //   641: ifeq -> 673
    //   644: aload #12
    //   646: invokeinterface next : ()Ljava/lang/Object;
    //   651: checkcast com/google/android/gms/measurement/internal/zzgc
    //   654: astore #8
    //   656: ldc_w '_lte'
    //   659: aload #8
    //   661: getfield name : Ljava/lang/String;
    //   664: invokevirtual equals : (Ljava/lang/Object;)Z
    //   667: ifeq -> 634
    //   670: goto -> 676
    //   673: aconst_null
    //   674: astore #8
    //   676: aload #8
    //   678: ifnull -> 689
    //   681: aload #8
    //   683: getfield value : Ljava/lang/Object;
    //   686: ifnonnull -> 740
    //   689: new com/google/android/gms/measurement/internal/zzgc
    //   692: astore #8
    //   694: aload #8
    //   696: aload #10
    //   698: ldc_w 'auto'
    //   701: ldc_w '_lte'
    //   704: aload_0
    //   705: invokevirtual zzz : ()Lcom/google/android/gms/common/util/Clock;
    //   708: invokeinterface currentTimeMillis : ()J
    //   713: lconst_0
    //   714: invokestatic valueOf : (J)Ljava/lang/Long;
    //   717: invokespecial <init> : (Ljava/lang/String;Ljava/lang/String;Ljava/lang/String;JLjava/lang/Object;)V
    //   720: aload #11
    //   722: aload #8
    //   724: invokeinterface add : (Ljava/lang/Object;)Z
    //   729: pop
    //   730: aload_0
    //   731: invokevirtual zzdo : ()Lcom/google/android/gms/measurement/internal/zzw;
    //   734: aload #8
    //   736: invokevirtual zza : (Lcom/google/android/gms/measurement/internal/zzgc;)Z
    //   739: pop
    //   740: aload_0
    //   741: invokevirtual zzaf : ()Lcom/google/android/gms/measurement/internal/zzt;
    //   744: aload #10
    //   746: getstatic com/google/android/gms/measurement/internal/zzal.zzin : Lcom/google/android/gms/measurement/internal/zzal$zza;
    //   749: invokevirtual zze : (Ljava/lang/String;Lcom/google/android/gms/measurement/internal/zzal$zza;)Z
    //   752: ifeq -> 924
    //   755: aload_0
    //   756: invokevirtual zzdm : ()Lcom/google/android/gms/measurement/internal/zzfz;
    //   759: astore #8
    //   761: aload #8
    //   763: invokevirtual zzad : ()Lcom/google/android/gms/measurement/internal/zzau;
    //   766: invokevirtual zzdi : ()Lcom/google/android/gms/measurement/internal/zzaw;
    //   769: ldc_w 'Checking account type status for ad personalization signals'
    //   772: invokevirtual zzaq : (Ljava/lang/String;)V
    //   775: aload #8
    //   777: invokevirtual zzy : ()Lcom/google/android/gms/measurement/internal/zzad;
    //   780: invokevirtual zzcs : ()Z
    //   783: ifeq -> 924
    //   786: aload #4
    //   788: invokevirtual zzan : ()Ljava/lang/String;
    //   791: astore #10
    //   793: aload #4
    //   795: invokevirtual zzbl : ()Z
    //   798: ifeq -> 924
    //   801: aload #8
    //   803: invokevirtual zzdp : ()Lcom/google/android/gms/measurement/internal/zzbs;
    //   806: aload #10
    //   808: invokevirtual zzbc : (Ljava/lang/String;)Z
    //   811: ifeq -> 924
    //   814: aload #8
    //   816: invokevirtual zzad : ()Lcom/google/android/gms/measurement/internal/zzau;
    //   819: invokevirtual zzdh : ()Lcom/google/android/gms/measurement/internal/zzaw;
    //   822: ldc_w 'Turning off ad personalization due to account type'
    //   825: invokevirtual zzaq : (Ljava/lang/String;)V
    //   828: aload #11
    //   830: invokeinterface iterator : ()Ljava/util/Iterator;
    //   835: astore #12
    //   837: aload #12
    //   839: invokeinterface hasNext : ()Z
    //   844: ifeq -> 882
    //   847: ldc_w '_npa'
    //   850: aload #12
    //   852: invokeinterface next : ()Ljava/lang/Object;
    //   857: checkcast com/google/android/gms/measurement/internal/zzgc
    //   860: getfield name : Ljava/lang/String;
    //   863: invokevirtual equals : (Ljava/lang/Object;)Z
    //   866: ifeq -> 879
    //   869: aload #12
    //   871: invokeinterface remove : ()V
    //   876: goto -> 882
    //   879: goto -> 837
    //   882: new com/google/android/gms/measurement/internal/zzgc
    //   885: astore #12
    //   887: aload #12
    //   889: aload #10
    //   891: ldc_w 'auto'
    //   894: ldc_w '_npa'
    //   897: aload #8
    //   899: invokevirtual zzz : ()Lcom/google/android/gms/common/util/Clock;
    //   902: invokeinterface currentTimeMillis : ()J
    //   907: lconst_1
    //   908: invokestatic valueOf : (J)Ljava/lang/Long;
    //   911: invokespecial <init> : (Ljava/lang/String;Ljava/lang/String;Ljava/lang/String;JLjava/lang/Object;)V
    //   914: aload #11
    //   916: aload #12
    //   918: invokeinterface add : (Ljava/lang/Object;)Z
    //   923: pop
    //   924: aload #11
    //   926: invokeinterface size : ()I
    //   931: anewarray com/google/android/gms/internal/measurement/zzbt$zzh
    //   934: astore #10
    //   936: iconst_0
    //   937: istore #13
    //   939: iload #13
    //   941: aload #11
    //   943: invokeinterface size : ()I
    //   948: if_icmpge -> 1038
    //   951: invokestatic zziu : ()Lcom/google/android/gms/internal/measurement/zzbt$zzh$zza;
    //   954: aload #11
    //   956: iload #13
    //   958: invokeinterface get : (I)Ljava/lang/Object;
    //   963: checkcast com/google/android/gms/measurement/internal/zzgc
    //   966: getfield name : Ljava/lang/String;
    //   969: invokevirtual zzby : (Ljava/lang/String;)Lcom/google/android/gms/internal/measurement/zzbt$zzh$zza;
    //   972: aload #11
    //   974: iload #13
    //   976: invokeinterface get : (I)Ljava/lang/Object;
    //   981: checkcast com/google/android/gms/measurement/internal/zzgc
    //   984: getfield zzsx : J
    //   987: invokevirtual zzan : (J)Lcom/google/android/gms/internal/measurement/zzbt$zzh$zza;
    //   990: astore #8
    //   992: aload_0
    //   993: invokevirtual zzdm : ()Lcom/google/android/gms/measurement/internal/zzfz;
    //   996: aload #8
    //   998: aload #11
    //   1000: iload #13
    //   1002: invokeinterface get : (I)Ljava/lang/Object;
    //   1007: checkcast com/google/android/gms/measurement/internal/zzgc
    //   1010: getfield value : Ljava/lang/Object;
    //   1013: invokevirtual zza : (Lcom/google/android/gms/internal/measurement/zzbt$zzh$zza;Ljava/lang/Object;)V
    //   1016: aload #10
    //   1018: iload #13
    //   1020: aload #8
    //   1022: invokevirtual zzmr : ()Lcom/google/android/gms/internal/measurement/zzgh;
    //   1025: checkcast com/google/android/gms/internal/measurement/zzez
    //   1028: checkcast com/google/android/gms/internal/measurement/zzbt$zzh
    //   1031: aastore
    //   1032: iinc #13, 1
    //   1035: goto -> 939
    //   1038: aload #5
    //   1040: aload #10
    //   1042: putfield zzxp : [Lcom/google/android/gms/internal/measurement/zzbt$zzh;
    //   1045: aload_1
    //   1046: getfield zzfd : Lcom/google/android/gms/measurement/internal/zzag;
    //   1049: invokevirtual zzct : ()Landroid/os/Bundle;
    //   1052: astore #11
    //   1054: aload #11
    //   1056: ldc_w '_c'
    //   1059: lconst_1
    //   1060: invokevirtual putLong : (Ljava/lang/String;J)V
    //   1063: aload_0
    //   1064: invokevirtual zzad : ()Lcom/google/android/gms/measurement/internal/zzau;
    //   1067: invokevirtual zzdh : ()Lcom/google/android/gms/measurement/internal/zzaw;
    //   1070: ldc_w 'Marking in-app purchase as real-time'
    //   1073: invokevirtual zzaq : (Ljava/lang/String;)V
    //   1076: aload #11
    //   1078: ldc_w '_r'
    //   1081: lconst_1
    //   1082: invokevirtual putLong : (Ljava/lang/String;J)V
    //   1085: aload #11
    //   1087: ldc_w '_o'
    //   1090: aload_1
    //   1091: getfield origin : Ljava/lang/String;
    //   1094: invokevirtual putString : (Ljava/lang/String;Ljava/lang/String;)V
    //   1097: aload_0
    //   1098: invokevirtual zzab : ()Lcom/google/android/gms/measurement/internal/zzgd;
    //   1101: aload #5
    //   1103: getfield zzcf : Ljava/lang/String;
    //   1106: invokevirtual zzbt : (Ljava/lang/String;)Z
    //   1109: ifeq -> 1144
    //   1112: aload_0
    //   1113: invokevirtual zzab : ()Lcom/google/android/gms/measurement/internal/zzgd;
    //   1116: aload #11
    //   1118: ldc_w '_dbg'
    //   1121: lconst_1
    //   1122: invokestatic valueOf : (J)Ljava/lang/Long;
    //   1125: invokevirtual zza : (Landroid/os/Bundle;Ljava/lang/String;Ljava/lang/Object;)V
    //   1128: aload_0
    //   1129: invokevirtual zzab : ()Lcom/google/android/gms/measurement/internal/zzgd;
    //   1132: aload #11
    //   1134: ldc_w '_r'
    //   1137: lconst_1
    //   1138: invokestatic valueOf : (J)Ljava/lang/Long;
    //   1141: invokevirtual zza : (Landroid/os/Bundle;Ljava/lang/String;Ljava/lang/Object;)V
    //   1144: aload_0
    //   1145: invokevirtual zzdo : ()Lcom/google/android/gms/measurement/internal/zzw;
    //   1148: aload_2
    //   1149: aload_1
    //   1150: getfield name : Ljava/lang/String;
    //   1153: invokevirtual zzc : (Ljava/lang/String;Ljava/lang/String;)Lcom/google/android/gms/measurement/internal/zzaf;
    //   1156: astore #8
    //   1158: aload #8
    //   1160: ifnonnull -> 1195
    //   1163: new com/google/android/gms/measurement/internal/zzaf
    //   1166: astore #8
    //   1168: aload #8
    //   1170: aload_2
    //   1171: aload_1
    //   1172: getfield name : Ljava/lang/String;
    //   1175: lconst_0
    //   1176: lconst_0
    //   1177: aload_1
    //   1178: getfield zzfp : J
    //   1181: lconst_0
    //   1182: aconst_null
    //   1183: aconst_null
    //   1184: aconst_null
    //   1185: aconst_null
    //   1186: invokespecial <init> : (Ljava/lang/String;Ljava/lang/String;JJJJLjava/lang/Long;Ljava/lang/Long;Ljava/lang/Long;Ljava/lang/Boolean;)V
    //   1189: lconst_0
    //   1190: lstore #6
    //   1192: goto -> 1213
    //   1195: aload #8
    //   1197: getfield zzfg : J
    //   1200: lstore #6
    //   1202: aload #8
    //   1204: aload_1
    //   1205: getfield zzfp : J
    //   1208: invokevirtual zzw : (J)Lcom/google/android/gms/measurement/internal/zzaf;
    //   1211: astore #8
    //   1213: aload_0
    //   1214: invokevirtual zzdo : ()Lcom/google/android/gms/measurement/internal/zzw;
    //   1217: aload #8
    //   1219: invokevirtual zza : (Lcom/google/android/gms/measurement/internal/zzaf;)V
    //   1222: new com/google/android/gms/measurement/internal/zzae
    //   1225: astore #10
    //   1227: aload #10
    //   1229: aload_0
    //   1230: getfield zzl : Lcom/google/android/gms/measurement/internal/zzby;
    //   1233: aload_1
    //   1234: getfield origin : Ljava/lang/String;
    //   1237: aload_2
    //   1238: aload_1
    //   1239: getfield name : Ljava/lang/String;
    //   1242: aload_1
    //   1243: getfield zzfp : J
    //   1246: lload #6
    //   1248: aload #11
    //   1250: invokespecial <init> : (Lcom/google/android/gms/measurement/internal/zzby;Ljava/lang/String;Ljava/lang/String;Ljava/lang/String;JJLandroid/os/Bundle;)V
    //   1253: new com/google/android/gms/internal/measurement/zzcf
    //   1256: astore #12
    //   1258: aload #12
    //   1260: invokespecial <init> : ()V
    //   1263: aload #5
    //   1265: iconst_1
    //   1266: anewarray com/google/android/gms/internal/measurement/zzcf
    //   1269: dup
    //   1270: iconst_0
    //   1271: aload #12
    //   1273: aastore
    //   1274: putfield zzxo : [Lcom/google/android/gms/internal/measurement/zzcf;
    //   1277: aload #12
    //   1279: aload #10
    //   1281: getfield timestamp : J
    //   1284: invokestatic valueOf : (J)Ljava/lang/Long;
    //   1287: putfield zzxj : Ljava/lang/Long;
    //   1290: aload #12
    //   1292: aload #10
    //   1294: getfield name : Ljava/lang/String;
    //   1297: putfield name : Ljava/lang/String;
    //   1300: aload #12
    //   1302: aload #10
    //   1304: getfield zzfc : J
    //   1307: invokestatic valueOf : (J)Ljava/lang/Long;
    //   1310: putfield zzxk : Ljava/lang/Long;
    //   1313: aload #12
    //   1315: aload #10
    //   1317: getfield zzfd : Lcom/google/android/gms/measurement/internal/zzag;
    //   1320: invokevirtual size : ()I
    //   1323: anewarray com/google/android/gms/internal/measurement/zzbt$zzd
    //   1326: putfield zzxi : [Lcom/google/android/gms/internal/measurement/zzbt$zzd;
    //   1329: aload #10
    //   1331: getfield zzfd : Lcom/google/android/gms/measurement/internal/zzag;
    //   1334: invokevirtual iterator : ()Ljava/util/Iterator;
    //   1337: astore #14
    //   1339: iconst_0
    //   1340: istore #13
    //   1342: aload #14
    //   1344: invokeinterface hasNext : ()Z
    //   1349: ifeq -> 1422
    //   1352: aload #14
    //   1354: invokeinterface next : ()Ljava/lang/Object;
    //   1359: checkcast java/lang/String
    //   1362: astore #15
    //   1364: invokestatic zzht : ()Lcom/google/android/gms/internal/measurement/zzbt$zzd$zza;
    //   1367: aload #15
    //   1369: invokevirtual zzbw : (Ljava/lang/String;)Lcom/google/android/gms/internal/measurement/zzbt$zzd$zza;
    //   1372: astore #11
    //   1374: aload #10
    //   1376: getfield zzfd : Lcom/google/android/gms/measurement/internal/zzag;
    //   1379: aload #15
    //   1381: invokevirtual get : (Ljava/lang/String;)Ljava/lang/Object;
    //   1384: astore #15
    //   1386: aload_0
    //   1387: invokevirtual zzdm : ()Lcom/google/android/gms/measurement/internal/zzfz;
    //   1390: aload #11
    //   1392: aload #15
    //   1394: invokevirtual zza : (Lcom/google/android/gms/internal/measurement/zzbt$zzd$zza;Ljava/lang/Object;)V
    //   1397: aload #12
    //   1399: getfield zzxi : [Lcom/google/android/gms/internal/measurement/zzbt$zzd;
    //   1402: iload #13
    //   1404: aload #11
    //   1406: invokevirtual zzmr : ()Lcom/google/android/gms/internal/measurement/zzgh;
    //   1409: checkcast com/google/android/gms/internal/measurement/zzez
    //   1412: checkcast com/google/android/gms/internal/measurement/zzbt$zzd
    //   1415: aastore
    //   1416: iinc #13, 1
    //   1419: goto -> 1342
    //   1422: aload #5
    //   1424: invokestatic zzhy : ()Lcom/google/android/gms/internal/measurement/zzbt$zze$zza;
    //   1427: invokestatic zzhi : ()Lcom/google/android/gms/internal/measurement/zzbt$zzc$zza;
    //   1430: aload #8
    //   1432: getfield zzfe : J
    //   1435: invokevirtual zzai : (J)Lcom/google/android/gms/internal/measurement/zzbt$zzc$zza;
    //   1438: aload_1
    //   1439: getfield name : Ljava/lang/String;
    //   1442: invokevirtual zzbu : (Ljava/lang/String;)Lcom/google/android/gms/internal/measurement/zzbt$zzc$zza;
    //   1445: invokevirtual zzb : (Lcom/google/android/gms/internal/measurement/zzbt$zzc$zza;)Lcom/google/android/gms/internal/measurement/zzbt$zze$zza;
    //   1448: invokevirtual zzmr : ()Lcom/google/android/gms/internal/measurement/zzgh;
    //   1451: checkcast com/google/android/gms/internal/measurement/zzez
    //   1454: checkcast com/google/android/gms/internal/measurement/zzbt$zze
    //   1457: putfield zzyq : Lcom/google/android/gms/internal/measurement/zzbt$zze;
    //   1460: aload #5
    //   1462: aload_0
    //   1463: invokevirtual zzdn : ()Lcom/google/android/gms/measurement/internal/zzo;
    //   1466: aload #4
    //   1468: invokevirtual zzan : ()Ljava/lang/String;
    //   1471: aconst_null
    //   1472: aload #5
    //   1474: getfield zzxp : [Lcom/google/android/gms/internal/measurement/zzbt$zzh;
    //   1477: invokevirtual zza : (Ljava/lang/String;[Lcom/google/android/gms/internal/measurement/zzcf;[Lcom/google/android/gms/internal/measurement/zzbt$zzh;)[Lcom/google/android/gms/internal/measurement/zzbt$zza;
    //   1480: putfield zzyg : [Lcom/google/android/gms/internal/measurement/zzbt$zza;
    //   1483: aload #5
    //   1485: aload #12
    //   1487: getfield zzxj : Ljava/lang/Long;
    //   1490: putfield zzxr : Ljava/lang/Long;
    //   1493: aload #5
    //   1495: aload #12
    //   1497: getfield zzxj : Ljava/lang/Long;
    //   1500: putfield zzxs : Ljava/lang/Long;
    //   1503: aload #4
    //   1505: invokevirtual zzar : ()J
    //   1508: lstore #6
    //   1510: lload #6
    //   1512: lconst_0
    //   1513: lcmp
    //   1514: ifeq -> 1526
    //   1517: lload #6
    //   1519: invokestatic valueOf : (J)Ljava/lang/Long;
    //   1522: astore_1
    //   1523: goto -> 1528
    //   1526: aconst_null
    //   1527: astore_1
    //   1528: aload #5
    //   1530: aload_1
    //   1531: putfield zzxu : Ljava/lang/Long;
    //   1534: aload #4
    //   1536: invokevirtual zzaq : ()J
    //   1539: lstore #16
    //   1541: lload #16
    //   1543: lconst_0
    //   1544: lcmp
    //   1545: ifne -> 1551
    //   1548: goto -> 1555
    //   1551: lload #16
    //   1553: lstore #6
    //   1555: lload #6
    //   1557: lconst_0
    //   1558: lcmp
    //   1559: ifeq -> 1571
    //   1562: lload #6
    //   1564: invokestatic valueOf : (J)Ljava/lang/Long;
    //   1567: astore_1
    //   1568: goto -> 1573
    //   1571: aconst_null
    //   1572: astore_1
    //   1573: aload #5
    //   1575: aload_1
    //   1576: putfield zzxt : Ljava/lang/Long;
    //   1579: aload #4
    //   1581: invokevirtual zzbb : ()V
    //   1584: aload #5
    //   1586: aload #4
    //   1588: invokevirtual zzay : ()J
    //   1591: l2i
    //   1592: invokestatic valueOf : (I)Ljava/lang/Integer;
    //   1595: putfield zzye : Ljava/lang/Integer;
    //   1598: aload #5
    //   1600: aload_0
    //   1601: invokevirtual zzaf : ()Lcom/google/android/gms/measurement/internal/zzt;
    //   1604: invokevirtual zzav : ()J
    //   1607: invokestatic valueOf : (J)Ljava/lang/Long;
    //   1610: putfield zzya : Ljava/lang/Long;
    //   1613: aload #5
    //   1615: aload_0
    //   1616: invokevirtual zzz : ()Lcom/google/android/gms/common/util/Clock;
    //   1619: invokeinterface currentTimeMillis : ()J
    //   1624: invokestatic valueOf : (J)Ljava/lang/Long;
    //   1627: putfield zzxq : Ljava/lang/Long;
    //   1630: aload #5
    //   1632: getstatic java/lang/Boolean.TRUE : Ljava/lang/Boolean;
    //   1635: putfield zzyf : Ljava/lang/Boolean;
    //   1638: aload #4
    //   1640: aload #5
    //   1642: getfield zzxr : Ljava/lang/Long;
    //   1645: invokevirtual longValue : ()J
    //   1648: invokevirtual zze : (J)V
    //   1651: aload #4
    //   1653: aload #5
    //   1655: getfield zzxs : Ljava/lang/Long;
    //   1658: invokevirtual longValue : ()J
    //   1661: invokevirtual zzf : (J)V
    //   1664: aload_0
    //   1665: invokevirtual zzdo : ()Lcom/google/android/gms/measurement/internal/zzw;
    //   1668: aload #4
    //   1670: invokevirtual zza : (Lcom/google/android/gms/measurement/internal/zzg;)V
    //   1673: aload_0
    //   1674: invokevirtual zzdo : ()Lcom/google/android/gms/measurement/internal/zzw;
    //   1677: invokevirtual setTransactionSuccessful : ()V
    //   1680: aload_0
    //   1681: invokevirtual zzdo : ()Lcom/google/android/gms/measurement/internal/zzw;
    //   1684: invokevirtual endTransaction : ()V
    //   1687: aload_3
    //   1688: invokevirtual zzly : ()I
    //   1691: newarray byte
    //   1693: astore #8
    //   1695: aload #8
    //   1697: iconst_0
    //   1698: aload #8
    //   1700: arraylength
    //   1701: invokestatic zzk : ([BII)Lcom/google/android/gms/internal/measurement/zzin;
    //   1704: astore_1
    //   1705: aload_3
    //   1706: aload_1
    //   1707: invokevirtual zza : (Lcom/google/android/gms/internal/measurement/zzin;)V
    //   1710: aload_1
    //   1711: invokevirtual zzlk : ()V
    //   1714: aload_0
    //   1715: invokevirtual zzdm : ()Lcom/google/android/gms/measurement/internal/zzfz;
    //   1718: aload #8
    //   1720: invokevirtual zzc : ([B)[B
    //   1723: astore_1
    //   1724: aload_1
    //   1725: areturn
    //   1726: astore_1
    //   1727: aload_0
    //   1728: invokevirtual zzad : ()Lcom/google/android/gms/measurement/internal/zzau;
    //   1731: invokevirtual zzda : ()Lcom/google/android/gms/measurement/internal/zzaw;
    //   1734: ldc_w 'Data loss. Failed to bundle and serialize. appId'
    //   1737: aload_2
    //   1738: invokestatic zzao : (Ljava/lang/String;)Ljava/lang/Object;
    //   1741: aload_1
    //   1742: invokevirtual zza : (Ljava/lang/String;Ljava/lang/Object;Ljava/lang/Object;)V
    //   1745: aconst_null
    //   1746: areturn
    //   1747: astore_1
    //   1748: aload_0
    //   1749: invokevirtual zzad : ()Lcom/google/android/gms/measurement/internal/zzau;
    //   1752: invokevirtual zzdh : ()Lcom/google/android/gms/measurement/internal/zzaw;
    //   1755: ldc_w 'app instance id encryption failed'
    //   1758: aload_1
    //   1759: invokevirtual getMessage : ()Ljava/lang/String;
    //   1762: invokevirtual zza : (Ljava/lang/String;Ljava/lang/Object;)V
    //   1765: aload_0
    //   1766: invokevirtual zzdo : ()Lcom/google/android/gms/measurement/internal/zzw;
    //   1769: invokevirtual endTransaction : ()V
    //   1772: iconst_0
    //   1773: newarray byte
    //   1775: areturn
    //   1776: astore_1
    //   1777: aload_0
    //   1778: invokevirtual zzdo : ()Lcom/google/android/gms/measurement/internal/zzw;
    //   1781: invokevirtual endTransaction : ()V
    //   1784: aload_1
    //   1785: athrow
    // Exception table:
    //   from	to	target	type
    //   110	120	1776	finally
    //   125	138	1776	finally
    //   149	170	1776	finally
    //   181	257	1776	finally
    //   272	280	1776	finally
    //   280	344	1776	finally
    //   344	394	1776	finally
    //   394	416	1776	finally
    //   421	434	1776	finally
    //   439	462	478	java/lang/SecurityException
    //   439	462	1776	finally
    //   462	475	1776	finally
    //   479	496	1776	finally
    //   507	565	1776	finally
    //   565	585	1747	java/lang/SecurityException
    //   565	585	1776	finally
    //   585	634	1776	finally
    //   634	670	1776	finally
    //   681	689	1776	finally
    //   689	740	1776	finally
    //   740	837	1776	finally
    //   837	876	1776	finally
    //   882	924	1776	finally
    //   924	936	1776	finally
    //   939	1032	1776	finally
    //   1038	1144	1776	finally
    //   1144	1158	1776	finally
    //   1163	1189	1776	finally
    //   1195	1213	1776	finally
    //   1213	1339	1776	finally
    //   1342	1416	1776	finally
    //   1422	1510	1776	finally
    //   1517	1523	1776	finally
    //   1528	1541	1776	finally
    //   1562	1568	1776	finally
    //   1573	1680	1776	finally
    //   1687	1724	1726	java/io/IOException
    //   1748	1765	1776	finally
  }
}


/* Location:              Y:\classes-dex2jar.jar!\com\google\android\gms\measurement\internal\zzea.class
 * Java compiler version: 6 (50.0)
 * JD-Core Version:       1.1.3
 */