package com.google.android.gms.measurement.internal;

final class zzee implements Runnable {
  zzee(zzed paramzzed, boolean paramBoolean, zzec paramzzec1, zzec paramzzec2) {}
  
  public final void run() {
    // Byte code:
    //   0: aload_0
    //   1: getfield zzqh : Lcom/google/android/gms/measurement/internal/zzed;
    //   4: invokevirtual zzaf : ()Lcom/google/android/gms/measurement/internal/zzt;
    //   7: aload_0
    //   8: getfield zzqh : Lcom/google/android/gms/measurement/internal/zzed;
    //   11: invokevirtual zzt : ()Lcom/google/android/gms/measurement/internal/zzap;
    //   14: invokevirtual zzan : ()Ljava/lang/String;
    //   17: invokevirtual zzac : (Ljava/lang/String;)Z
    //   20: istore_1
    //   21: iconst_0
    //   22: istore_2
    //   23: iload_1
    //   24: ifeq -> 81
    //   27: aload_0
    //   28: getfield zzqe : Z
    //   31: ifeq -> 49
    //   34: aload_0
    //   35: getfield zzqh : Lcom/google/android/gms/measurement/internal/zzed;
    //   38: getfield zzpy : Lcom/google/android/gms/measurement/internal/zzec;
    //   41: ifnull -> 49
    //   44: iconst_1
    //   45: istore_3
    //   46: goto -> 51
    //   49: iconst_0
    //   50: istore_3
    //   51: iload_3
    //   52: istore #4
    //   54: iload_3
    //   55: ifeq -> 118
    //   58: aload_0
    //   59: getfield zzqh : Lcom/google/android/gms/measurement/internal/zzed;
    //   62: astore #5
    //   64: aload #5
    //   66: aload #5
    //   68: getfield zzpy : Lcom/google/android/gms/measurement/internal/zzec;
    //   71: iconst_1
    //   72: invokestatic zza : (Lcom/google/android/gms/measurement/internal/zzed;Lcom/google/android/gms/measurement/internal/zzec;Z)V
    //   75: iload_3
    //   76: istore #4
    //   78: goto -> 118
    //   81: aload_0
    //   82: getfield zzqe : Z
    //   85: ifeq -> 115
    //   88: aload_0
    //   89: getfield zzqh : Lcom/google/android/gms/measurement/internal/zzed;
    //   92: getfield zzpy : Lcom/google/android/gms/measurement/internal/zzec;
    //   95: ifnull -> 115
    //   98: aload_0
    //   99: getfield zzqh : Lcom/google/android/gms/measurement/internal/zzed;
    //   102: astore #5
    //   104: aload #5
    //   106: aload #5
    //   108: getfield zzpy : Lcom/google/android/gms/measurement/internal/zzec;
    //   111: iconst_1
    //   112: invokestatic zza : (Lcom/google/android/gms/measurement/internal/zzed;Lcom/google/android/gms/measurement/internal/zzec;Z)V
    //   115: iconst_0
    //   116: istore #4
    //   118: aload_0
    //   119: getfield zzqf : Lcom/google/android/gms/measurement/internal/zzec;
    //   122: astore #5
    //   124: aload #5
    //   126: ifnull -> 187
    //   129: aload #5
    //   131: getfield zzpw : J
    //   134: aload_0
    //   135: getfield zzqg : Lcom/google/android/gms/measurement/internal/zzec;
    //   138: getfield zzpw : J
    //   141: lcmp
    //   142: ifne -> 187
    //   145: aload_0
    //   146: getfield zzqf : Lcom/google/android/gms/measurement/internal/zzec;
    //   149: getfield zzpv : Ljava/lang/String;
    //   152: aload_0
    //   153: getfield zzqg : Lcom/google/android/gms/measurement/internal/zzec;
    //   156: getfield zzpv : Ljava/lang/String;
    //   159: invokestatic zzs : (Ljava/lang/String;Ljava/lang/String;)Z
    //   162: ifeq -> 187
    //   165: iload_2
    //   166: istore_3
    //   167: aload_0
    //   168: getfield zzqf : Lcom/google/android/gms/measurement/internal/zzec;
    //   171: getfield zzpu : Ljava/lang/String;
    //   174: aload_0
    //   175: getfield zzqg : Lcom/google/android/gms/measurement/internal/zzec;
    //   178: getfield zzpu : Ljava/lang/String;
    //   181: invokestatic zzs : (Ljava/lang/String;Ljava/lang/String;)Z
    //   184: ifne -> 189
    //   187: iconst_1
    //   188: istore_3
    //   189: iload_3
    //   190: ifeq -> 350
    //   193: new android/os/Bundle
    //   196: dup
    //   197: invokespecial <init> : ()V
    //   200: astore #6
    //   202: aload_0
    //   203: getfield zzqg : Lcom/google/android/gms/measurement/internal/zzec;
    //   206: aload #6
    //   208: iconst_1
    //   209: invokestatic zza : (Lcom/google/android/gms/measurement/internal/zzec;Landroid/os/Bundle;Z)V
    //   212: aload_0
    //   213: getfield zzqf : Lcom/google/android/gms/measurement/internal/zzec;
    //   216: astore #5
    //   218: aload #5
    //   220: ifnull -> 273
    //   223: aload #5
    //   225: getfield zzpu : Ljava/lang/String;
    //   228: ifnull -> 245
    //   231: aload #6
    //   233: ldc '_pn'
    //   235: aload_0
    //   236: getfield zzqf : Lcom/google/android/gms/measurement/internal/zzec;
    //   239: getfield zzpu : Ljava/lang/String;
    //   242: invokevirtual putString : (Ljava/lang/String;Ljava/lang/String;)V
    //   245: aload #6
    //   247: ldc '_pc'
    //   249: aload_0
    //   250: getfield zzqf : Lcom/google/android/gms/measurement/internal/zzec;
    //   253: getfield zzpv : Ljava/lang/String;
    //   256: invokevirtual putString : (Ljava/lang/String;Ljava/lang/String;)V
    //   259: aload #6
    //   261: ldc '_pi'
    //   263: aload_0
    //   264: getfield zzqf : Lcom/google/android/gms/measurement/internal/zzec;
    //   267: getfield zzpw : J
    //   270: invokevirtual putLong : (Ljava/lang/String;J)V
    //   273: aload_0
    //   274: getfield zzqh : Lcom/google/android/gms/measurement/internal/zzed;
    //   277: invokevirtual zzaf : ()Lcom/google/android/gms/measurement/internal/zzt;
    //   280: aload_0
    //   281: getfield zzqh : Lcom/google/android/gms/measurement/internal/zzed;
    //   284: invokevirtual zzt : ()Lcom/google/android/gms/measurement/internal/zzap;
    //   287: invokevirtual zzan : ()Ljava/lang/String;
    //   290: invokevirtual zzac : (Ljava/lang/String;)Z
    //   293: ifeq -> 334
    //   296: iload #4
    //   298: ifeq -> 334
    //   301: aload_0
    //   302: getfield zzqh : Lcom/google/android/gms/measurement/internal/zzed;
    //   305: invokevirtual zzx : ()Lcom/google/android/gms/measurement/internal/zzfj;
    //   308: invokevirtual zzfq : ()J
    //   311: lstore #7
    //   313: lload #7
    //   315: lconst_0
    //   316: lcmp
    //   317: ifle -> 334
    //   320: aload_0
    //   321: getfield zzqh : Lcom/google/android/gms/measurement/internal/zzed;
    //   324: invokevirtual zzab : ()Lcom/google/android/gms/measurement/internal/zzgd;
    //   327: aload #6
    //   329: lload #7
    //   331: invokevirtual zzb : (Landroid/os/Bundle;J)V
    //   334: aload_0
    //   335: getfield zzqh : Lcom/google/android/gms/measurement/internal/zzed;
    //   338: invokevirtual zzs : ()Lcom/google/android/gms/measurement/internal/zzdd;
    //   341: ldc 'auto'
    //   343: ldc '_vs'
    //   345: aload #6
    //   347: invokevirtual zza : (Ljava/lang/String;Ljava/lang/String;Landroid/os/Bundle;)V
    //   350: aload_0
    //   351: getfield zzqh : Lcom/google/android/gms/measurement/internal/zzed;
    //   354: astore #5
    //   356: aload #5
    //   358: aload_0
    //   359: getfield zzqg : Lcom/google/android/gms/measurement/internal/zzec;
    //   362: putfield zzpy : Lcom/google/android/gms/measurement/internal/zzec;
    //   365: aload #5
    //   367: invokevirtual zzu : ()Lcom/google/android/gms/measurement/internal/zzeg;
    //   370: aload_0
    //   371: getfield zzqg : Lcom/google/android/gms/measurement/internal/zzec;
    //   374: invokevirtual zza : (Lcom/google/android/gms/measurement/internal/zzec;)V
    //   377: return
  }
}


/* Location:              Y:\classes-dex2jar.jar!\com\google\android\gms\measurement\internal\zzee.class
 * Java compiler version: 6 (50.0)
 * JD-Core Version:       1.1.3
 */