package com.google.android.gms.measurement.internal;

import java.util.concurrent.atomic.AtomicReference;

final class zzew implements Runnable {
  zzew(zzeg paramzzeg, AtomicReference paramAtomicReference, String paramString1, String paramString2, String paramString3, boolean paramBoolean, zzm paramzzm) {}
  
  public final void run() {
    // Byte code:
    //   0: aload_0
    //   1: getfield zzqs : Ljava/util/concurrent/atomic/AtomicReference;
    //   4: astore_1
    //   5: aload_1
    //   6: monitorenter
    //   7: aload_0
    //   8: getfield zzqq : Lcom/google/android/gms/measurement/internal/zzeg;
    //   11: invokestatic zzd : (Lcom/google/android/gms/measurement/internal/zzeg;)Lcom/google/android/gms/measurement/internal/zzam;
    //   14: astore_2
    //   15: aload_2
    //   16: ifnonnull -> 69
    //   19: aload_0
    //   20: getfield zzqq : Lcom/google/android/gms/measurement/internal/zzeg;
    //   23: invokevirtual zzad : ()Lcom/google/android/gms/measurement/internal/zzau;
    //   26: invokevirtual zzda : ()Lcom/google/android/gms/measurement/internal/zzaw;
    //   29: ldc 'Failed to get user properties'
    //   31: aload_0
    //   32: getfield zzdk : Ljava/lang/String;
    //   35: invokestatic zzao : (Ljava/lang/String;)Ljava/lang/Object;
    //   38: aload_0
    //   39: getfield zzao : Ljava/lang/String;
    //   42: aload_0
    //   43: getfield zzav : Ljava/lang/String;
    //   46: invokevirtual zza : (Ljava/lang/String;Ljava/lang/Object;Ljava/lang/Object;Ljava/lang/Object;)V
    //   49: aload_0
    //   50: getfield zzqs : Ljava/util/concurrent/atomic/AtomicReference;
    //   53: invokestatic emptyList : ()Ljava/util/List;
    //   56: invokevirtual set : (Ljava/lang/Object;)V
    //   59: aload_0
    //   60: getfield zzqs : Ljava/util/concurrent/atomic/AtomicReference;
    //   63: invokevirtual notify : ()V
    //   66: aload_1
    //   67: monitorexit
    //   68: return
    //   69: aload_0
    //   70: getfield zzdk : Ljava/lang/String;
    //   73: invokestatic isEmpty : (Ljava/lang/CharSequence;)Z
    //   76: ifeq -> 111
    //   79: aload_0
    //   80: getfield zzqs : Ljava/util/concurrent/atomic/AtomicReference;
    //   83: aload_2
    //   84: aload_0
    //   85: getfield zzao : Ljava/lang/String;
    //   88: aload_0
    //   89: getfield zzav : Ljava/lang/String;
    //   92: aload_0
    //   93: getfield zzbd : Z
    //   96: aload_0
    //   97: getfield zzos : Lcom/google/android/gms/measurement/internal/zzm;
    //   100: invokeinterface zza : (Ljava/lang/String;Ljava/lang/String;ZLcom/google/android/gms/measurement/internal/zzm;)Ljava/util/List;
    //   105: invokevirtual set : (Ljava/lang/Object;)V
    //   108: goto -> 140
    //   111: aload_0
    //   112: getfield zzqs : Ljava/util/concurrent/atomic/AtomicReference;
    //   115: aload_2
    //   116: aload_0
    //   117: getfield zzdk : Ljava/lang/String;
    //   120: aload_0
    //   121: getfield zzao : Ljava/lang/String;
    //   124: aload_0
    //   125: getfield zzav : Ljava/lang/String;
    //   128: aload_0
    //   129: getfield zzbd : Z
    //   132: invokeinterface zza : (Ljava/lang/String;Ljava/lang/String;Ljava/lang/String;Z)Ljava/util/List;
    //   137: invokevirtual set : (Ljava/lang/Object;)V
    //   140: aload_0
    //   141: getfield zzqq : Lcom/google/android/gms/measurement/internal/zzeg;
    //   144: invokestatic zze : (Lcom/google/android/gms/measurement/internal/zzeg;)V
    //   147: aload_0
    //   148: getfield zzqs : Ljava/util/concurrent/atomic/AtomicReference;
    //   151: invokevirtual notify : ()V
    //   154: goto -> 206
    //   157: astore_2
    //   158: goto -> 209
    //   161: astore_2
    //   162: aload_0
    //   163: getfield zzqq : Lcom/google/android/gms/measurement/internal/zzeg;
    //   166: invokevirtual zzad : ()Lcom/google/android/gms/measurement/internal/zzau;
    //   169: invokevirtual zzda : ()Lcom/google/android/gms/measurement/internal/zzaw;
    //   172: ldc 'Failed to get user properties'
    //   174: aload_0
    //   175: getfield zzdk : Ljava/lang/String;
    //   178: invokestatic zzao : (Ljava/lang/String;)Ljava/lang/Object;
    //   181: aload_0
    //   182: getfield zzao : Ljava/lang/String;
    //   185: aload_2
    //   186: invokevirtual zza : (Ljava/lang/String;Ljava/lang/Object;Ljava/lang/Object;Ljava/lang/Object;)V
    //   189: aload_0
    //   190: getfield zzqs : Ljava/util/concurrent/atomic/AtomicReference;
    //   193: invokestatic emptyList : ()Ljava/util/List;
    //   196: invokevirtual set : (Ljava/lang/Object;)V
    //   199: aload_0
    //   200: getfield zzqs : Ljava/util/concurrent/atomic/AtomicReference;
    //   203: invokevirtual notify : ()V
    //   206: aload_1
    //   207: monitorexit
    //   208: return
    //   209: aload_0
    //   210: getfield zzqs : Ljava/util/concurrent/atomic/AtomicReference;
    //   213: invokevirtual notify : ()V
    //   216: aload_2
    //   217: athrow
    //   218: astore_2
    //   219: aload_1
    //   220: monitorexit
    //   221: aload_2
    //   222: athrow
    // Exception table:
    //   from	to	target	type
    //   7	15	161	android/os/RemoteException
    //   7	15	157	finally
    //   19	59	161	android/os/RemoteException
    //   19	59	157	finally
    //   59	68	218	finally
    //   69	108	161	android/os/RemoteException
    //   69	108	157	finally
    //   111	140	161	android/os/RemoteException
    //   111	140	157	finally
    //   140	147	161	android/os/RemoteException
    //   140	147	157	finally
    //   147	154	218	finally
    //   162	199	157	finally
    //   199	206	218	finally
    //   206	208	218	finally
    //   209	218	218	finally
    //   219	221	218	finally
  }
}


/* Location:              Y:\classes-dex2jar.jar!\com\google\android\gms\measurement\internal\zzew.class
 * Java compiler version: 6 (50.0)
 * JD-Core Version:       1.1.3
 */