package com.google.android.gms.measurement.internal;

import android.support.annotation.WorkerThread;
import android.support.v4.util.ArrayMap;
import android.text.TextUtils;
import com.google.android.gms.common.internal.Preconditions;
import com.google.android.gms.common.util.VisibleForTesting;
import com.google.android.gms.internal.measurement.zzbl;
import com.google.android.gms.internal.measurement.zzbt;
import com.google.android.gms.internal.measurement.zzby;
import com.google.android.gms.internal.measurement.zzbz;
import com.google.android.gms.internal.measurement.zzca;
import com.google.android.gms.internal.measurement.zzcb;
import com.google.android.gms.internal.measurement.zzcc;
import com.google.android.gms.internal.measurement.zzcf;
import java.math.BigDecimal;
import java.util.ArrayList;
import java.util.Arrays;
import java.util.HashSet;
import java.util.Iterator;
import java.util.List;
import java.util.Locale;
import java.util.Map;
import java.util.regex.Pattern;
import java.util.regex.PatternSyntaxException;

final class zzo extends zzfs {
  zzo(zzft paramzzft) {
    super(paramzzft);
  }
  
  private final Boolean zza(double paramDouble, zzca paramzzca) {
    try {
      BigDecimal bigDecimal = new BigDecimal();
      this(paramDouble);
      return zza(bigDecimal, paramzzca, Math.ulp(paramDouble));
    } catch (NumberFormatException numberFormatException) {
      return null;
    } 
  }
  
  private final Boolean zza(long paramLong, zzca paramzzca) {
    try {
      BigDecimal bigDecimal = new BigDecimal();
      this(paramLong);
      return zza(bigDecimal, paramzzca, 0.0D);
    } catch (NumberFormatException numberFormatException) {
      return null;
    } 
  }
  
  private final Boolean zza(zzby paramzzby, String paramString, List<zzbt.zzd> paramList, long paramLong) {
    if (paramzzby.zzwe != null) {
      Boolean bool = zza(paramLong, paramzzby.zzwe);
      if (bool == null)
        return null; 
      if (!bool.booleanValue())
        return Boolean.valueOf(false); 
    } 
    HashSet<String> hashSet = new HashSet();
    for (zzbz zzbz : paramzzby.zzwc) {
      if (TextUtils.isEmpty(zzbz.zzwj)) {
        zzad().zzdd().zza("null or empty param name in filter. event", zzaa().zzal(paramString));
        return null;
      } 
      hashSet.add(zzbz.zzwj);
    } 
    ArrayMap<String, zzbt.zzd> arrayMap = new ArrayMap();
    for (zzbt.zzd zzd : paramList) {
      if (hashSet.contains(zzd.getName())) {
        if (zzd.zzhn()) {
          String str = zzd.getName();
          if (zzd.zzhn()) {
            Long long_ = Long.valueOf(zzd.zzho());
          } else {
            zzd = null;
          } 
          arrayMap.put(str, zzd);
          continue;
        } 
        if (zzd.zzhq()) {
          String str = zzd.getName();
          if (zzd.zzhq()) {
            Double double_ = Double.valueOf(zzd.zzhr());
          } else {
            zzd = null;
          } 
          arrayMap.put(str, zzd);
          continue;
        } 
        if (zzd.zzhk()) {
          arrayMap.put(zzd.getName(), zzd.zzhl());
          continue;
        } 
        zzad().zzdd().zza("Unknown value for param. event, param", zzaa().zzal(paramString), zzaa().zzam(zzd.getName()));
        return null;
      } 
    } 
    for (zzbz zzbz : paramzzby.zzwc) {
      Boolean bool;
      boolean bool1 = Boolean.TRUE.equals(zzbz.zzwi);
      String str = zzbz.zzwj;
      if (TextUtils.isEmpty(str)) {
        zzad().zzdd().zza("Event has empty param name. event", zzaa().zzal(paramString));
        return null;
      } 
      Long long_ = (Long)arrayMap.get(str);
      if (long_ instanceof Long) {
        if (zzbz.zzwh == null) {
          zzad().zzdd().zza("No number filter for long param. event, param", zzaa().zzal(paramString), zzaa().zzam(str));
          return null;
        } 
        bool = zza(((Long)long_).longValue(), zzbz.zzwh);
        if (bool == null)
          return null; 
        if ((true ^ bool.booleanValue() ^ bool1) != 0)
          return Boolean.valueOf(false); 
      } else if (long_ instanceof Double) {
        if (((zzbz)bool).zzwh == null) {
          zzad().zzdd().zza("No number filter for double param. event, param", zzaa().zzal(paramString), zzaa().zzam(str));
          return null;
        } 
        bool = zza(((Double)long_).doubleValue(), ((zzbz)bool).zzwh);
        if (bool == null)
          return null; 
        if ((true ^ bool.booleanValue() ^ bool1) != 0)
          return Boolean.valueOf(false); 
      } else {
        String str1;
        if (long_ instanceof String) {
          if (((zzbz)bool).zzwg != null) {
            bool = zza((String)long_, ((zzbz)bool).zzwg);
          } else if (((zzbz)bool).zzwh != null) {
            str1 = (String)long_;
            if (zzfz.zzbl(str1)) {
              bool = zza(str1, ((zzbz)bool).zzwh);
            } else {
              zzad().zzdd().zza("Invalid param value for number filter. event, param", zzaa().zzal(paramString), zzaa().zzam(str));
              return null;
            } 
          } else {
            zzad().zzdd().zza("No filter for String param. event, param", zzaa().zzal(paramString), zzaa().zzam(str));
            return null;
          } 
          if (bool == null)
            return null; 
          if ((true ^ bool.booleanValue() ^ bool1) != 0)
            return Boolean.valueOf(false); 
        } else {
          if (str1 == null) {
            zzad().zzdi().zza("Missing param for filter. event, param", zzaa().zzal(paramString), zzaa().zzam(str));
            return Boolean.valueOf(false);
          } 
          zzad().zzdd().zza("Unknown param type. event, param", zzaa().zzal(paramString), zzaa().zzam(str));
          return null;
        } 
      } 
    } 
    return Boolean.valueOf(true);
  }
  
  private final Boolean zza(zzcb paramzzcb, zzbt.zzh paramzzh) {
    zzbz zzbz = paramzzcb.zzwr;
    if (zzbz == null) {
      zzad().zzdd().zza("Missing property filter. property", zzaa().zzan(paramzzh.getName()));
      return null;
    } 
    boolean bool = Boolean.TRUE.equals(zzbz.zzwi);
    if (paramzzh.zzhn()) {
      if (zzbz.zzwh == null) {
        zzad().zzdd().zza("No number filter for long property. property", zzaa().zzan(paramzzh.getName()));
        return null;
      } 
      return zza(zza(paramzzh.zzho(), zzbz.zzwh), bool);
    } 
    if (paramzzh.zzhq()) {
      if (zzbz.zzwh == null) {
        zzad().zzdd().zza("No number filter for double property. property", zzaa().zzan(paramzzh.getName()));
        return null;
      } 
      return zza(zza(paramzzh.zzhr(), zzbz.zzwh), bool);
    } 
    if (paramzzh.zzhk()) {
      if (zzbz.zzwg == null) {
        if (zzbz.zzwh == null) {
          zzad().zzdd().zza("No string or number filter defined. property", zzaa().zzan(paramzzh.getName()));
        } else {
          if (zzfz.zzbl(paramzzh.zzhl()))
            return zza(zza(paramzzh.zzhl(), zzbz.zzwh), bool); 
          zzad().zzdd().zza("Invalid user property value for Numeric number filter. property, value", zzaa().zzan(paramzzh.getName()), paramzzh.zzhl());
        } 
        return null;
      } 
      return zza(zza(paramzzh.zzhl(), zzbz.zzwg), bool);
    } 
    zzad().zzdd().zza("User property has no value, property", zzaa().zzan(paramzzh.getName()));
    return null;
  }
  
  @VisibleForTesting
  private static Boolean zza(Boolean paramBoolean, boolean paramBoolean1) {
    return (paramBoolean == null) ? null : Boolean.valueOf(paramBoolean.booleanValue() ^ paramBoolean1);
  }
  
  private final Boolean zza(String paramString1, zzbl.zzb.zzb paramzzb, boolean paramBoolean, String paramString2, List<String> paramList, String paramString3) {
    byte b;
    if (paramString1 == null)
      return null; 
    if (paramzzb == zzbl.zzb.zzb.zzuk) {
      if (paramList == null || paramList.size() == 0)
        return null; 
    } else if (paramString2 == null) {
      return null;
    } 
    String str = paramString1;
    if (!paramBoolean)
      if (paramzzb == zzbl.zzb.zzb.zzuf) {
        str = paramString1;
      } else {
        str = paramString1.toUpperCase(Locale.ENGLISH);
      }  
    switch (zzp.zzds[paramzzb.ordinal()]) {
      default:
        return null;
      case 6:
        return Boolean.valueOf(paramList.contains(str));
      case 5:
        return Boolean.valueOf(str.equals(paramString2));
      case 4:
        return Boolean.valueOf(str.contains(paramString2));
      case 3:
        return Boolean.valueOf(str.endsWith(paramString2));
      case 2:
        return Boolean.valueOf(str.startsWith(paramString2));
      case 1:
        break;
    } 
    if (paramBoolean) {
      b = 0;
    } else {
      b = 66;
    } 
    try {
      paramBoolean = Pattern.compile(paramString3, b).matcher(str).matches();
      return Boolean.valueOf(paramBoolean);
    } catch (PatternSyntaxException patternSyntaxException) {
      zzad().zzdd().zza("Invalid regular expression in REGEXP audience filter. expression", paramString3);
      return null;
    } 
  }
  
  private final Boolean zza(String paramString, zzca paramzzca) {
    if (!zzfz.zzbl(paramString))
      return null; 
    try {
      BigDecimal bigDecimal = new BigDecimal();
      this(paramString);
      return zza(bigDecimal, paramzzca, 0.0D);
    } catch (NumberFormatException numberFormatException) {
      return null;
    } 
  }
  
  @VisibleForTesting
  private final Boolean zza(String paramString, zzcc paramzzcc) {
    List<String> list;
    String str1;
    boolean bool1;
    String str2;
    Preconditions.checkNotNull(paramzzcc);
    if (paramString == null)
      return null; 
    if (paramzzcc.zzws == null || paramzzcc.zzws == zzbl.zzb.zzb.zzue)
      return null; 
    if (paramzzcc.zzws == zzbl.zzb.zzb.zzuk) {
      if (paramzzcc.zzwv == null || paramzzcc.zzwv.length == 0)
        return null; 
    } else if (paramzzcc.zzwt == null) {
      return null;
    } 
    zzbl.zzb.zzb zzb = paramzzcc.zzws;
    Boolean bool = paramzzcc.zzwu;
    byte b = 0;
    if (bool != null && paramzzcc.zzwu.booleanValue()) {
      bool1 = true;
    } else {
      bool1 = false;
    } 
    if (bool1 || zzb == zzbl.zzb.zzb.zzuf || zzb == zzbl.zzb.zzb.zzuk) {
      str1 = paramzzcc.zzwt;
    } else {
      str1 = paramzzcc.zzwt.toUpperCase(Locale.ENGLISH);
    } 
    if (paramzzcc.zzwv == null) {
      paramzzcc = null;
    } else {
      str2 = (String)paramzzcc.zzwv;
      if (bool1) {
        list = Arrays.asList((String[])str2);
      } else {
        list = new ArrayList();
        int i = str2.length;
        while (b < i) {
          list.add(str2[b].toUpperCase(Locale.ENGLISH));
          b++;
        } 
      } 
    } 
    if (zzb == zzbl.zzb.zzb.zzuf) {
      str2 = str1;
    } else {
      str2 = null;
    } 
    return zza(paramString, zzb, bool1, str1, list, str2);
  }
  
  @VisibleForTesting
  private static Boolean zza(BigDecimal paramBigDecimal, zzca paramzzca, double paramDouble) {
    // Byte code:
    //   0: aload_1
    //   1: invokestatic checkNotNull : (Ljava/lang/Object;)Ljava/lang/Object;
    //   4: pop
    //   5: aload_1
    //   6: getfield zzwk : Lcom/google/android/gms/internal/measurement/zzbl$zza$zzb;
    //   9: ifnull -> 439
    //   12: aload_1
    //   13: getfield zzwk : Lcom/google/android/gms/internal/measurement/zzbl$zza$zzb;
    //   16: getstatic com/google/android/gms/internal/measurement/zzbl$zza$zzb.zztr : Lcom/google/android/gms/internal/measurement/zzbl$zza$zzb;
    //   19: if_acmpne -> 25
    //   22: goto -> 439
    //   25: aload_1
    //   26: getfield zzwk : Lcom/google/android/gms/internal/measurement/zzbl$zza$zzb;
    //   29: getstatic com/google/android/gms/internal/measurement/zzbl$zza$zzb.zztv : Lcom/google/android/gms/internal/measurement/zzbl$zza$zzb;
    //   32: if_acmpne -> 51
    //   35: aload_1
    //   36: getfield zzwn : Ljava/lang/String;
    //   39: ifnull -> 49
    //   42: aload_1
    //   43: getfield zzwo : Ljava/lang/String;
    //   46: ifnonnull -> 60
    //   49: aconst_null
    //   50: areturn
    //   51: aload_1
    //   52: getfield zzwm : Ljava/lang/String;
    //   55: ifnonnull -> 60
    //   58: aconst_null
    //   59: areturn
    //   60: aload_1
    //   61: getfield zzwk : Lcom/google/android/gms/internal/measurement/zzbl$zza$zzb;
    //   64: astore #4
    //   66: aload_1
    //   67: getfield zzwk : Lcom/google/android/gms/internal/measurement/zzbl$zza$zzb;
    //   70: getstatic com/google/android/gms/internal/measurement/zzbl$zza$zzb.zztv : Lcom/google/android/gms/internal/measurement/zzbl$zza$zzb;
    //   73: if_acmpne -> 136
    //   76: aload_1
    //   77: getfield zzwn : Ljava/lang/String;
    //   80: invokestatic zzbl : (Ljava/lang/String;)Z
    //   83: ifeq -> 134
    //   86: aload_1
    //   87: getfield zzwo : Ljava/lang/String;
    //   90: invokestatic zzbl : (Ljava/lang/String;)Z
    //   93: ifne -> 99
    //   96: goto -> 134
    //   99: new java/math/BigDecimal
    //   102: astore #5
    //   104: aload #5
    //   106: aload_1
    //   107: getfield zzwn : Ljava/lang/String;
    //   110: invokespecial <init> : (Ljava/lang/String;)V
    //   113: new java/math/BigDecimal
    //   116: dup
    //   117: aload_1
    //   118: getfield zzwo : Ljava/lang/String;
    //   121: invokespecial <init> : (Ljava/lang/String;)V
    //   124: astore #6
    //   126: aconst_null
    //   127: astore_1
    //   128: goto -> 167
    //   131: astore_0
    //   132: aconst_null
    //   133: areturn
    //   134: aconst_null
    //   135: areturn
    //   136: aload_1
    //   137: getfield zzwm : Ljava/lang/String;
    //   140: invokestatic zzbl : (Ljava/lang/String;)Z
    //   143: ifne -> 148
    //   146: aconst_null
    //   147: areturn
    //   148: new java/math/BigDecimal
    //   151: dup
    //   152: aload_1
    //   153: getfield zzwm : Ljava/lang/String;
    //   156: invokespecial <init> : (Ljava/lang/String;)V
    //   159: astore_1
    //   160: aconst_null
    //   161: astore #5
    //   163: aload #5
    //   165: astore #6
    //   167: aload #4
    //   169: getstatic com/google/android/gms/internal/measurement/zzbl$zza$zzb.zztv : Lcom/google/android/gms/internal/measurement/zzbl$zza$zzb;
    //   172: if_acmpne -> 185
    //   175: aload #5
    //   177: ifnull -> 183
    //   180: goto -> 189
    //   183: aconst_null
    //   184: areturn
    //   185: aload_1
    //   186: ifnull -> 434
    //   189: getstatic com/google/android/gms/measurement/internal/zzp.zzdt : [I
    //   192: aload #4
    //   194: invokevirtual ordinal : ()I
    //   197: iaload
    //   198: istore #7
    //   200: iconst_0
    //   201: istore #8
    //   203: iconst_0
    //   204: istore #9
    //   206: iconst_0
    //   207: istore #10
    //   209: iconst_0
    //   210: istore #11
    //   212: iconst_0
    //   213: istore #12
    //   215: iload #7
    //   217: tableswitch default -> 248, 1 -> 412, 2 -> 390, 3 -> 288, 4 -> 251
    //   248: goto -> 434
    //   251: iload #12
    //   253: istore #9
    //   255: aload_0
    //   256: aload #5
    //   258: invokevirtual compareTo : (Ljava/math/BigDecimal;)I
    //   261: iconst_m1
    //   262: if_icmpeq -> 282
    //   265: iload #12
    //   267: istore #9
    //   269: aload_0
    //   270: aload #6
    //   272: invokevirtual compareTo : (Ljava/math/BigDecimal;)I
    //   275: iconst_1
    //   276: if_icmpeq -> 282
    //   279: iconst_1
    //   280: istore #9
    //   282: iload #9
    //   284: invokestatic valueOf : (Z)Ljava/lang/Boolean;
    //   287: areturn
    //   288: dload_2
    //   289: dconst_0
    //   290: dcmpl
    //   291: ifeq -> 373
    //   294: iload #8
    //   296: istore #9
    //   298: aload_0
    //   299: aload_1
    //   300: new java/math/BigDecimal
    //   303: dup
    //   304: dload_2
    //   305: invokespecial <init> : (D)V
    //   308: new java/math/BigDecimal
    //   311: dup
    //   312: iconst_2
    //   313: invokespecial <init> : (I)V
    //   316: invokevirtual multiply : (Ljava/math/BigDecimal;)Ljava/math/BigDecimal;
    //   319: invokevirtual subtract : (Ljava/math/BigDecimal;)Ljava/math/BigDecimal;
    //   322: invokevirtual compareTo : (Ljava/math/BigDecimal;)I
    //   325: iconst_1
    //   326: if_icmpne -> 367
    //   329: iload #8
    //   331: istore #9
    //   333: aload_0
    //   334: aload_1
    //   335: new java/math/BigDecimal
    //   338: dup
    //   339: dload_2
    //   340: invokespecial <init> : (D)V
    //   343: new java/math/BigDecimal
    //   346: dup
    //   347: iconst_2
    //   348: invokespecial <init> : (I)V
    //   351: invokevirtual multiply : (Ljava/math/BigDecimal;)Ljava/math/BigDecimal;
    //   354: invokevirtual add : (Ljava/math/BigDecimal;)Ljava/math/BigDecimal;
    //   357: invokevirtual compareTo : (Ljava/math/BigDecimal;)I
    //   360: iconst_m1
    //   361: if_icmpne -> 367
    //   364: iconst_1
    //   365: istore #9
    //   367: iload #9
    //   369: invokestatic valueOf : (Z)Ljava/lang/Boolean;
    //   372: areturn
    //   373: aload_0
    //   374: aload_1
    //   375: invokevirtual compareTo : (Ljava/math/BigDecimal;)I
    //   378: ifne -> 384
    //   381: iconst_1
    //   382: istore #9
    //   384: iload #9
    //   386: invokestatic valueOf : (Z)Ljava/lang/Boolean;
    //   389: areturn
    //   390: iload #10
    //   392: istore #9
    //   394: aload_0
    //   395: aload_1
    //   396: invokevirtual compareTo : (Ljava/math/BigDecimal;)I
    //   399: iconst_1
    //   400: if_icmpne -> 406
    //   403: iconst_1
    //   404: istore #9
    //   406: iload #9
    //   408: invokestatic valueOf : (Z)Ljava/lang/Boolean;
    //   411: areturn
    //   412: iload #11
    //   414: istore #9
    //   416: aload_0
    //   417: aload_1
    //   418: invokevirtual compareTo : (Ljava/math/BigDecimal;)I
    //   421: iconst_m1
    //   422: if_icmpne -> 428
    //   425: iconst_1
    //   426: istore #9
    //   428: iload #9
    //   430: invokestatic valueOf : (Z)Ljava/lang/Boolean;
    //   433: areturn
    //   434: aconst_null
    //   435: areturn
    //   436: astore_0
    //   437: aconst_null
    //   438: areturn
    //   439: aconst_null
    //   440: areturn
    // Exception table:
    //   from	to	target	type
    //   99	126	131	java/lang/NumberFormatException
    //   148	160	436	java/lang/NumberFormatException
  }
  
  private static List<zzbt.zzb> zza(Map<Integer, Long> paramMap) {
    if (paramMap == null)
      return null; 
    ArrayList<zzbt.zzb> arrayList = new ArrayList(paramMap.size());
    Iterator<Integer> iterator = paramMap.keySet().iterator();
    while (iterator.hasNext()) {
      int i = ((Integer)iterator.next()).intValue();
      arrayList.add((zzbt.zzb)zzbt.zzb.zzhg().zzj(i).zzag(((Long)paramMap.get(Integer.valueOf(i))).longValue()).zzmr());
    } 
    return arrayList;
  }
  
  private static void zza(Map<Integer, Long> paramMap, int paramInt, long paramLong) {
    Long long_ = paramMap.get(Integer.valueOf(paramInt));
    paramLong /= 1000L;
    if (long_ == null || paramLong > long_.longValue())
      paramMap.put(Integer.valueOf(paramInt), Long.valueOf(paramLong)); 
  }
  
  private static boolean zza(zzcb paramzzcb) {
    return (paramzzcb != null && paramzzcb.zzvx != null && paramzzcb.zzvx.booleanValue());
  }
  
  private static void zzb(Map<Integer, List<Long>> paramMap, int paramInt, long paramLong) {
    List<Long> list1 = paramMap.get(Integer.valueOf(paramInt));
    List<Long> list2 = list1;
    if (list1 == null) {
      list2 = new ArrayList();
      paramMap.put(Integer.valueOf(paramInt), list2);
    } 
    list2.add(Long.valueOf(paramLong / 1000L));
  }
  
  @WorkerThread
  final zzbt.zza[] zza(String paramString, zzcf[] paramArrayOfzzcf, zzbt.zzh[] paramArrayOfzzh) {
    // Byte code:
    //   0: aload_1
    //   1: astore #4
    //   3: aload_2
    //   4: astore #5
    //   6: aload_1
    //   7: invokestatic checkNotEmpty : (Ljava/lang/String;)Ljava/lang/String;
    //   10: pop
    //   11: new java/util/HashSet
    //   14: dup
    //   15: invokespecial <init> : ()V
    //   18: astore #6
    //   20: new android/support/v4/util/ArrayMap
    //   23: dup
    //   24: invokespecial <init> : ()V
    //   27: astore #7
    //   29: new android/support/v4/util/ArrayMap
    //   32: dup
    //   33: invokespecial <init> : ()V
    //   36: astore #8
    //   38: new android/support/v4/util/ArrayMap
    //   41: dup
    //   42: invokespecial <init> : ()V
    //   45: astore #9
    //   47: new android/support/v4/util/ArrayMap
    //   50: dup
    //   51: invokespecial <init> : ()V
    //   54: astore #10
    //   56: new android/support/v4/util/ArrayMap
    //   59: dup
    //   60: invokespecial <init> : ()V
    //   63: astore #11
    //   65: aload_0
    //   66: invokevirtual zzaf : ()Lcom/google/android/gms/measurement/internal/zzt;
    //   69: aload #4
    //   71: invokevirtual zzt : (Ljava/lang/String;)Z
    //   74: istore #12
    //   76: aload_0
    //   77: invokevirtual zzaf : ()Lcom/google/android/gms/measurement/internal/zzt;
    //   80: aload #4
    //   82: getstatic com/google/android/gms/measurement/internal/zzal.zzit : Lcom/google/android/gms/measurement/internal/zzal$zza;
    //   85: invokevirtual zzd : (Ljava/lang/String;Lcom/google/android/gms/measurement/internal/zzal$zza;)Z
    //   88: istore #13
    //   90: aload_0
    //   91: invokevirtual zzdo : ()Lcom/google/android/gms/measurement/internal/zzw;
    //   94: aload #4
    //   96: invokevirtual zzah : (Ljava/lang/String;)Ljava/util/Map;
    //   99: astore #14
    //   101: aload #14
    //   103: ifnull -> 658
    //   106: aload #14
    //   108: invokeinterface keySet : ()Ljava/util/Set;
    //   113: invokeinterface iterator : ()Ljava/util/Iterator;
    //   118: astore #4
    //   120: aload #4
    //   122: invokeinterface hasNext : ()Z
    //   127: ifeq -> 635
    //   130: aload #4
    //   132: invokeinterface next : ()Ljava/lang/Object;
    //   137: checkcast java/lang/Integer
    //   140: invokevirtual intValue : ()I
    //   143: istore #15
    //   145: aload #14
    //   147: iload #15
    //   149: invokestatic valueOf : (I)Ljava/lang/Integer;
    //   152: invokeinterface get : (Ljava/lang/Object;)Ljava/lang/Object;
    //   157: checkcast com/google/android/gms/internal/measurement/zzbt$zzf
    //   160: astore #16
    //   162: aload #8
    //   164: iload #15
    //   166: invokestatic valueOf : (I)Ljava/lang/Integer;
    //   169: invokeinterface get : (Ljava/lang/Object;)Ljava/lang/Object;
    //   174: checkcast java/util/BitSet
    //   177: astore #17
    //   179: aload #9
    //   181: iload #15
    //   183: invokestatic valueOf : (I)Ljava/lang/Integer;
    //   186: invokeinterface get : (Ljava/lang/Object;)Ljava/lang/Object;
    //   191: checkcast java/util/BitSet
    //   194: astore #18
    //   196: iload #12
    //   198: ifeq -> 345
    //   201: new android/support/v4/util/ArrayMap
    //   204: dup
    //   205: invokespecial <init> : ()V
    //   208: astore #19
    //   210: aload #16
    //   212: ifnull -> 323
    //   215: aload #16
    //   217: invokevirtual zzif : ()I
    //   220: ifne -> 226
    //   223: goto -> 323
    //   226: aload #16
    //   228: invokevirtual zzie : ()Ljava/util/List;
    //   231: invokeinterface iterator : ()Ljava/util/Iterator;
    //   236: astore #20
    //   238: aload #20
    //   240: invokeinterface hasNext : ()Z
    //   245: ifeq -> 320
    //   248: aload #20
    //   250: invokeinterface next : ()Ljava/lang/Object;
    //   255: checkcast com/google/android/gms/internal/measurement/zzbt$zzb
    //   258: astore #21
    //   260: aload #21
    //   262: invokevirtual zzhd : ()Z
    //   265: ifeq -> 317
    //   268: aload #21
    //   270: invokevirtual getIndex : ()I
    //   273: istore #22
    //   275: aload #21
    //   277: invokevirtual zzhe : ()Z
    //   280: ifeq -> 296
    //   283: aload #21
    //   285: invokevirtual zzhf : ()J
    //   288: invokestatic valueOf : (J)Ljava/lang/Long;
    //   291: astore #21
    //   293: goto -> 299
    //   296: aconst_null
    //   297: astore #21
    //   299: aload #19
    //   301: iload #22
    //   303: invokestatic valueOf : (I)Ljava/lang/Integer;
    //   306: aload #21
    //   308: invokeinterface put : (Ljava/lang/Object;Ljava/lang/Object;)Ljava/lang/Object;
    //   313: pop
    //   314: goto -> 317
    //   317: goto -> 238
    //   320: goto -> 323
    //   323: aload #10
    //   325: iload #15
    //   327: invokestatic valueOf : (I)Ljava/lang/Integer;
    //   330: aload #19
    //   332: invokeinterface put : (Ljava/lang/Object;Ljava/lang/Object;)Ljava/lang/Object;
    //   337: pop
    //   338: aload #19
    //   340: astore #21
    //   342: goto -> 348
    //   345: aconst_null
    //   346: astore #21
    //   348: aload #17
    //   350: ifnonnull -> 404
    //   353: new java/util/BitSet
    //   356: dup
    //   357: invokespecial <init> : ()V
    //   360: astore #18
    //   362: aload #8
    //   364: iload #15
    //   366: invokestatic valueOf : (I)Ljava/lang/Integer;
    //   369: aload #18
    //   371: invokeinterface put : (Ljava/lang/Object;Ljava/lang/Object;)Ljava/lang/Object;
    //   376: pop
    //   377: new java/util/BitSet
    //   380: dup
    //   381: invokespecial <init> : ()V
    //   384: astore #19
    //   386: aload #9
    //   388: iload #15
    //   390: invokestatic valueOf : (I)Ljava/lang/Integer;
    //   393: aload #19
    //   395: invokeinterface put : (Ljava/lang/Object;Ljava/lang/Object;)Ljava/lang/Object;
    //   400: pop
    //   401: goto -> 412
    //   404: aload #18
    //   406: astore #19
    //   408: aload #17
    //   410: astore #18
    //   412: iconst_0
    //   413: istore #22
    //   415: iload #22
    //   417: aload #16
    //   419: invokevirtual zzib : ()I
    //   422: bipush #6
    //   424: ishl
    //   425: if_icmpge -> 529
    //   428: aload #16
    //   430: invokevirtual zzia : ()Ljava/util/List;
    //   433: iload #22
    //   435: invokestatic zza : (Ljava/util/List;I)Z
    //   438: ifeq -> 497
    //   441: aload_0
    //   442: invokevirtual zzad : ()Lcom/google/android/gms/measurement/internal/zzau;
    //   445: invokevirtual zzdi : ()Lcom/google/android/gms/measurement/internal/zzaw;
    //   448: ldc_w 'Filter already evaluated. audience ID, filter ID'
    //   451: iload #15
    //   453: invokestatic valueOf : (I)Ljava/lang/Integer;
    //   456: iload #22
    //   458: invokestatic valueOf : (I)Ljava/lang/Integer;
    //   461: invokevirtual zza : (Ljava/lang/String;Ljava/lang/Object;Ljava/lang/Object;)V
    //   464: aload #19
    //   466: iload #22
    //   468: invokevirtual set : (I)V
    //   471: aload #16
    //   473: invokevirtual zzic : ()Ljava/util/List;
    //   476: iload #22
    //   478: invokestatic zza : (Ljava/util/List;I)Z
    //   481: ifeq -> 497
    //   484: aload #18
    //   486: iload #22
    //   488: invokevirtual set : (I)V
    //   491: iconst_1
    //   492: istore #23
    //   494: goto -> 500
    //   497: iconst_0
    //   498: istore #23
    //   500: aload #21
    //   502: ifnull -> 523
    //   505: iload #23
    //   507: ifne -> 523
    //   510: aload #21
    //   512: iload #22
    //   514: invokestatic valueOf : (I)Ljava/lang/Integer;
    //   517: invokeinterface remove : (Ljava/lang/Object;)Ljava/lang/Object;
    //   522: pop
    //   523: iinc #22, 1
    //   526: goto -> 415
    //   529: invokestatic zzhb : ()Lcom/google/android/gms/internal/measurement/zzbt$zza$zza;
    //   532: iconst_0
    //   533: invokevirtual zzl : (Z)Lcom/google/android/gms/internal/measurement/zzbt$zza$zza;
    //   536: aload #16
    //   538: invokevirtual zzb : (Lcom/google/android/gms/internal/measurement/zzbt$zzf;)Lcom/google/android/gms/internal/measurement/zzbt$zza$zza;
    //   541: astore #17
    //   543: invokestatic zzii : ()Lcom/google/android/gms/internal/measurement/zzbt$zzf$zza;
    //   546: aload #18
    //   548: invokestatic zza : (Ljava/util/BitSet;)Ljava/util/List;
    //   551: invokevirtual zzf : (Ljava/lang/Iterable;)Lcom/google/android/gms/internal/measurement/zzbt$zzf$zza;
    //   554: aload #19
    //   556: invokestatic zza : (Ljava/util/BitSet;)Ljava/util/List;
    //   559: invokevirtual zze : (Ljava/lang/Iterable;)Lcom/google/android/gms/internal/measurement/zzbt$zzf$zza;
    //   562: astore #18
    //   564: iload #12
    //   566: ifeq -> 600
    //   569: aload #18
    //   571: aload #21
    //   573: invokestatic zza : (Ljava/util/Map;)Ljava/util/List;
    //   576: invokevirtual zzg : (Ljava/lang/Iterable;)Lcom/google/android/gms/internal/measurement/zzbt$zzf$zza;
    //   579: pop
    //   580: aload #11
    //   582: iload #15
    //   584: invokestatic valueOf : (I)Ljava/lang/Integer;
    //   587: new android/support/v4/util/ArrayMap
    //   590: dup
    //   591: invokespecial <init> : ()V
    //   594: invokeinterface put : (Ljava/lang/Object;Ljava/lang/Object;)Ljava/lang/Object;
    //   599: pop
    //   600: aload #17
    //   602: aload #18
    //   604: invokevirtual zzb : (Lcom/google/android/gms/internal/measurement/zzbt$zzf$zza;)Lcom/google/android/gms/internal/measurement/zzbt$zza$zza;
    //   607: pop
    //   608: aload #7
    //   610: iload #15
    //   612: invokestatic valueOf : (I)Ljava/lang/Integer;
    //   615: aload #17
    //   617: invokevirtual zzmr : ()Lcom/google/android/gms/internal/measurement/zzgh;
    //   620: checkcast com/google/android/gms/internal/measurement/zzez
    //   623: checkcast com/google/android/gms/internal/measurement/zzbt$zza
    //   626: invokeinterface put : (Ljava/lang/Object;Ljava/lang/Object;)Ljava/lang/Object;
    //   631: pop
    //   632: goto -> 120
    //   635: aload #9
    //   637: astore #18
    //   639: aload #8
    //   641: astore #9
    //   643: aload #6
    //   645: astore #4
    //   647: aload #18
    //   649: astore #8
    //   651: aload #9
    //   653: astore #6
    //   655: goto -> 670
    //   658: aload #6
    //   660: astore #4
    //   662: aload #8
    //   664: astore #6
    //   666: aload #9
    //   668: astore #8
    //   670: aload #5
    //   672: ifnull -> 2874
    //   675: new android/support/v4/util/ArrayMap
    //   678: dup
    //   679: invokespecial <init> : ()V
    //   682: astore #18
    //   684: aload #5
    //   686: arraylength
    //   687: istore #22
    //   689: lconst_0
    //   690: lstore #24
    //   692: aconst_null
    //   693: astore #14
    //   695: aconst_null
    //   696: astore #21
    //   698: iconst_0
    //   699: istore #23
    //   701: aload #7
    //   703: astore #9
    //   705: aload #18
    //   707: astore #7
    //   709: aload #11
    //   711: astore #18
    //   713: aload #21
    //   715: astore #11
    //   717: aload_1
    //   718: astore #26
    //   720: iload #23
    //   722: iload #22
    //   724: if_icmpge -> 2856
    //   727: aload_2
    //   728: iload #23
    //   730: aaload
    //   731: astore #17
    //   733: aload #17
    //   735: getfield name : Ljava/lang/String;
    //   738: astore #19
    //   740: aload #17
    //   742: getfield zzxi : [Lcom/google/android/gms/internal/measurement/zzbt$zzd;
    //   745: invokestatic asList : ([Ljava/lang/Object;)Ljava/util/List;
    //   748: astore #21
    //   750: aload_0
    //   751: invokevirtual zzaf : ()Lcom/google/android/gms/measurement/internal/zzt;
    //   754: aload #26
    //   756: getstatic com/google/android/gms/measurement/internal/zzal.zzhr : Lcom/google/android/gms/measurement/internal/zzal$zza;
    //   759: invokevirtual zzd : (Ljava/lang/String;Lcom/google/android/gms/measurement/internal/zzal$zza;)Z
    //   762: ifeq -> 1442
    //   765: aload_0
    //   766: invokevirtual zzdm : ()Lcom/google/android/gms/measurement/internal/zzfz;
    //   769: pop
    //   770: aload #17
    //   772: ldc_w '_eid'
    //   775: invokestatic zzb : (Lcom/google/android/gms/internal/measurement/zzcf;Ljava/lang/String;)Ljava/lang/Object;
    //   778: checkcast java/lang/Long
    //   781: astore #16
    //   783: aload #16
    //   785: ifnull -> 794
    //   788: iconst_1
    //   789: istore #15
    //   791: goto -> 797
    //   794: iconst_0
    //   795: istore #15
    //   797: iload #15
    //   799: ifeq -> 819
    //   802: aload #19
    //   804: ldc_w '_ep'
    //   807: invokevirtual equals : (Ljava/lang/Object;)Z
    //   810: ifeq -> 819
    //   813: iconst_1
    //   814: istore #27
    //   816: goto -> 822
    //   819: iconst_0
    //   820: istore #27
    //   822: iload #27
    //   824: ifeq -> 1326
    //   827: aload_0
    //   828: invokevirtual zzdm : ()Lcom/google/android/gms/measurement/internal/zzfz;
    //   831: pop
    //   832: aload #17
    //   834: ldc_w '_en'
    //   837: invokestatic zzb : (Lcom/google/android/gms/internal/measurement/zzcf;Ljava/lang/String;)Ljava/lang/Object;
    //   840: checkcast java/lang/String
    //   843: astore #19
    //   845: aload #19
    //   847: invokestatic isEmpty : (Ljava/lang/CharSequence;)Z
    //   850: ifeq -> 871
    //   853: aload_0
    //   854: invokevirtual zzad : ()Lcom/google/android/gms/measurement/internal/zzau;
    //   857: invokevirtual zzda : ()Lcom/google/android/gms/measurement/internal/zzaw;
    //   860: ldc_w 'Extra parameter without an event name. eventId'
    //   863: aload #16
    //   865: invokevirtual zza : (Ljava/lang/String;Ljava/lang/Object;)V
    //   868: goto -> 1279
    //   871: aload #14
    //   873: ifnull -> 901
    //   876: aload #11
    //   878: ifnull -> 901
    //   881: aload #16
    //   883: invokevirtual longValue : ()J
    //   886: aload #11
    //   888: invokevirtual longValue : ()J
    //   891: lcmp
    //   892: ifeq -> 898
    //   895: goto -> 901
    //   898: goto -> 971
    //   901: aload_0
    //   902: invokevirtual zzdo : ()Lcom/google/android/gms/measurement/internal/zzw;
    //   905: aload #26
    //   907: aload #16
    //   909: invokevirtual zza : (Ljava/lang/String;Ljava/lang/Long;)Landroid/util/Pair;
    //   912: astore #5
    //   914: aload #5
    //   916: ifnull -> 1262
    //   919: aload #5
    //   921: getfield first : Ljava/lang/Object;
    //   924: ifnonnull -> 930
    //   927: goto -> 1262
    //   930: aload #5
    //   932: getfield first : Ljava/lang/Object;
    //   935: checkcast com/google/android/gms/internal/measurement/zzcf
    //   938: astore #14
    //   940: aload #5
    //   942: getfield second : Ljava/lang/Object;
    //   945: checkcast java/lang/Long
    //   948: invokevirtual longValue : ()J
    //   951: lstore #24
    //   953: aload_0
    //   954: invokevirtual zzdm : ()Lcom/google/android/gms/measurement/internal/zzfz;
    //   957: pop
    //   958: aload #14
    //   960: ldc_w '_eid'
    //   963: invokestatic zzb : (Lcom/google/android/gms/internal/measurement/zzcf;Ljava/lang/String;)Ljava/lang/Object;
    //   966: checkcast java/lang/Long
    //   969: astore #11
    //   971: lload #24
    //   973: lconst_1
    //   974: lsub
    //   975: lstore #24
    //   977: lload #24
    //   979: lconst_0
    //   980: lcmp
    //   981: ifgt -> 1068
    //   984: aload_0
    //   985: invokevirtual zzdo : ()Lcom/google/android/gms/measurement/internal/zzw;
    //   988: astore #16
    //   990: aload #16
    //   992: invokevirtual zzq : ()V
    //   995: aload #16
    //   997: invokevirtual zzad : ()Lcom/google/android/gms/measurement/internal/zzau;
    //   1000: invokevirtual zzdi : ()Lcom/google/android/gms/measurement/internal/zzaw;
    //   1003: ldc_w 'Clearing complex main event info. appId'
    //   1006: aload #26
    //   1008: invokevirtual zza : (Ljava/lang/String;Ljava/lang/Object;)V
    //   1011: aload #16
    //   1013: invokevirtual getWritableDatabase : ()Landroid/database/sqlite/SQLiteDatabase;
    //   1016: astore #5
    //   1018: aload #5
    //   1020: ldc_w 'delete from main_event_params where app_id=?'
    //   1023: iconst_1
    //   1024: anewarray java/lang/String
    //   1027: dup
    //   1028: iconst_0
    //   1029: aload #26
    //   1031: aastore
    //   1032: invokevirtual execSQL : (Ljava/lang/String;[Ljava/lang/Object;)V
    //   1035: goto -> 1083
    //   1038: astore #5
    //   1040: goto -> 1049
    //   1043: astore_1
    //   1044: goto -> 1049
    //   1047: astore #5
    //   1049: aload #16
    //   1051: invokevirtual zzad : ()Lcom/google/android/gms/measurement/internal/zzau;
    //   1054: invokevirtual zzda : ()Lcom/google/android/gms/measurement/internal/zzaw;
    //   1057: ldc_w 'Error clearing complex main event'
    //   1060: aload #5
    //   1062: invokevirtual zza : (Ljava/lang/String;Ljava/lang/Object;)V
    //   1065: goto -> 1083
    //   1068: aload_0
    //   1069: invokevirtual zzdo : ()Lcom/google/android/gms/measurement/internal/zzw;
    //   1072: aload_1
    //   1073: aload #16
    //   1075: lload #24
    //   1077: aload #14
    //   1079: invokevirtual zza : (Ljava/lang/String;Ljava/lang/Long;JLcom/google/android/gms/internal/measurement/zzcf;)Z
    //   1082: pop
    //   1083: new java/util/ArrayList
    //   1086: dup
    //   1087: invokespecial <init> : ()V
    //   1090: astore #5
    //   1092: aload #14
    //   1094: getfield zzxi : [Lcom/google/android/gms/internal/measurement/zzbt$zzd;
    //   1097: astore #20
    //   1099: aload #20
    //   1101: arraylength
    //   1102: istore #27
    //   1104: iconst_0
    //   1105: istore #15
    //   1107: iload #15
    //   1109: iload #27
    //   1111: if_icmpge -> 1155
    //   1114: aload #20
    //   1116: iload #15
    //   1118: aaload
    //   1119: astore #16
    //   1121: aload_0
    //   1122: invokevirtual zzdm : ()Lcom/google/android/gms/measurement/internal/zzfz;
    //   1125: pop
    //   1126: aload #17
    //   1128: aload #16
    //   1130: invokevirtual getName : ()Ljava/lang/String;
    //   1133: invokestatic zza : (Lcom/google/android/gms/internal/measurement/zzcf;Ljava/lang/String;)Lcom/google/android/gms/internal/measurement/zzbt$zzd;
    //   1136: ifnonnull -> 1149
    //   1139: aload #5
    //   1141: aload #16
    //   1143: invokeinterface add : (Ljava/lang/Object;)Z
    //   1148: pop
    //   1149: iinc #15, 1
    //   1152: goto -> 1107
    //   1155: aload #5
    //   1157: invokeinterface isEmpty : ()Z
    //   1162: ifne -> 1224
    //   1165: aload #21
    //   1167: invokeinterface iterator : ()Ljava/util/Iterator;
    //   1172: astore #21
    //   1174: aload #21
    //   1176: invokeinterface hasNext : ()Z
    //   1181: ifeq -> 1205
    //   1184: aload #5
    //   1186: aload #21
    //   1188: invokeinterface next : ()Ljava/lang/Object;
    //   1193: checkcast com/google/android/gms/internal/measurement/zzbt$zzd
    //   1196: invokeinterface add : (Ljava/lang/Object;)Z
    //   1201: pop
    //   1202: goto -> 1174
    //   1205: aload #11
    //   1207: astore #16
    //   1209: aload #19
    //   1211: astore #11
    //   1213: aload #14
    //   1215: astore #21
    //   1217: aload #16
    //   1219: astore #19
    //   1221: goto -> 1462
    //   1224: aload_0
    //   1225: invokevirtual zzad : ()Lcom/google/android/gms/measurement/internal/zzau;
    //   1228: invokevirtual zzdd : ()Lcom/google/android/gms/measurement/internal/zzaw;
    //   1231: ldc_w 'No unique parameters in main event. eventName'
    //   1234: aload #19
    //   1236: invokevirtual zza : (Ljava/lang/String;Ljava/lang/Object;)V
    //   1239: aload #21
    //   1241: astore #5
    //   1243: aload #14
    //   1245: astore #21
    //   1247: aload #11
    //   1249: astore #14
    //   1251: aload #19
    //   1253: astore #11
    //   1255: aload #14
    //   1257: astore #19
    //   1259: goto -> 1462
    //   1262: aload_0
    //   1263: invokevirtual zzad : ()Lcom/google/android/gms/measurement/internal/zzau;
    //   1266: invokevirtual zzda : ()Lcom/google/android/gms/measurement/internal/zzaw;
    //   1269: ldc_w 'Extra parameter without existing main event. eventName, eventId'
    //   1272: aload #19
    //   1274: aload #16
    //   1276: invokevirtual zza : (Ljava/lang/String;Ljava/lang/Object;Ljava/lang/Object;)V
    //   1279: aload #18
    //   1281: astore #19
    //   1283: aload #7
    //   1285: astore #5
    //   1287: aload #9
    //   1289: astore #18
    //   1291: aload #8
    //   1293: astore #21
    //   1295: aload #11
    //   1297: astore #7
    //   1299: aload #4
    //   1301: astore #11
    //   1303: aload #19
    //   1305: astore #4
    //   1307: aload #5
    //   1309: astore #9
    //   1311: aload #6
    //   1313: astore #8
    //   1315: aload #10
    //   1317: astore #6
    //   1319: aload #21
    //   1321: astore #10
    //   1323: goto -> 2802
    //   1326: aload #17
    //   1328: astore #5
    //   1330: iload #15
    //   1332: ifeq -> 1442
    //   1335: aload_0
    //   1336: invokevirtual zzdm : ()Lcom/google/android/gms/measurement/internal/zzfz;
    //   1339: pop
    //   1340: aload #5
    //   1342: ldc_w '_epc'
    //   1345: invokestatic zzb : (Lcom/google/android/gms/internal/measurement/zzcf;Ljava/lang/String;)Ljava/lang/Object;
    //   1348: astore #14
    //   1350: aload #14
    //   1352: astore #11
    //   1354: aload #14
    //   1356: ifnonnull -> 1365
    //   1359: lconst_0
    //   1360: invokestatic valueOf : (J)Ljava/lang/Long;
    //   1363: astore #11
    //   1365: aload #11
    //   1367: checkcast java/lang/Long
    //   1370: invokevirtual longValue : ()J
    //   1373: lstore #24
    //   1375: lload #24
    //   1377: lconst_0
    //   1378: lcmp
    //   1379: ifgt -> 1400
    //   1382: aload_0
    //   1383: invokevirtual zzad : ()Lcom/google/android/gms/measurement/internal/zzau;
    //   1386: invokevirtual zzdd : ()Lcom/google/android/gms/measurement/internal/zzaw;
    //   1389: ldc_w 'Complex event with zero extra param count. eventName'
    //   1392: aload #19
    //   1394: invokevirtual zza : (Ljava/lang/String;Ljava/lang/Object;)V
    //   1397: goto -> 1415
    //   1400: aload_0
    //   1401: invokevirtual zzdo : ()Lcom/google/android/gms/measurement/internal/zzw;
    //   1404: aload_1
    //   1405: aload #16
    //   1407: lload #24
    //   1409: aload #5
    //   1411: invokevirtual zza : (Ljava/lang/String;Ljava/lang/Long;JLcom/google/android/gms/internal/measurement/zzcf;)Z
    //   1414: pop
    //   1415: aload #16
    //   1417: astore #14
    //   1419: aload #19
    //   1421: astore #11
    //   1423: aload #21
    //   1425: astore #16
    //   1427: aload #5
    //   1429: astore #21
    //   1431: aload #14
    //   1433: astore #19
    //   1435: aload #16
    //   1437: astore #5
    //   1439: goto -> 1462
    //   1442: aload #11
    //   1444: astore #16
    //   1446: aload #19
    //   1448: astore #11
    //   1450: aload #21
    //   1452: astore #5
    //   1454: aload #16
    //   1456: astore #19
    //   1458: aload #14
    //   1460: astore #21
    //   1462: aload #18
    //   1464: astore #14
    //   1466: aload #17
    //   1468: astore #28
    //   1470: aload_0
    //   1471: invokevirtual zzdo : ()Lcom/google/android/gms/measurement/internal/zzw;
    //   1474: aload #26
    //   1476: aload #28
    //   1478: getfield name : Ljava/lang/String;
    //   1481: invokevirtual zzc : (Ljava/lang/String;Ljava/lang/String;)Lcom/google/android/gms/measurement/internal/zzaf;
    //   1484: astore #18
    //   1486: aload #18
    //   1488: ifnonnull -> 1550
    //   1491: aload_0
    //   1492: invokevirtual zzad : ()Lcom/google/android/gms/measurement/internal/zzau;
    //   1495: invokevirtual zzdd : ()Lcom/google/android/gms/measurement/internal/zzaw;
    //   1498: ldc_w 'Event aggregate wasn't created during raw event logging. appId, event'
    //   1501: aload_1
    //   1502: invokestatic zzao : (Ljava/lang/String;)Ljava/lang/Object;
    //   1505: aload_0
    //   1506: invokevirtual zzaa : ()Lcom/google/android/gms/measurement/internal/zzas;
    //   1509: aload #11
    //   1511: invokevirtual zzal : (Ljava/lang/String;)Ljava/lang/String;
    //   1514: invokevirtual zza : (Ljava/lang/String;Ljava/lang/Object;Ljava/lang/Object;)V
    //   1517: new com/google/android/gms/measurement/internal/zzaf
    //   1520: dup
    //   1521: aload_1
    //   1522: aload #28
    //   1524: getfield name : Ljava/lang/String;
    //   1527: lconst_1
    //   1528: lconst_1
    //   1529: aload #28
    //   1531: getfield zzxj : Ljava/lang/Long;
    //   1534: invokevirtual longValue : ()J
    //   1537: lconst_0
    //   1538: aconst_null
    //   1539: aconst_null
    //   1540: aconst_null
    //   1541: aconst_null
    //   1542: invokespecial <init> : (Ljava/lang/String;Ljava/lang/String;JJJJLjava/lang/Long;Ljava/lang/Long;Ljava/lang/Long;Ljava/lang/Boolean;)V
    //   1545: astore #29
    //   1547: goto -> 1613
    //   1550: new com/google/android/gms/measurement/internal/zzaf
    //   1553: dup
    //   1554: aload #18
    //   1556: getfield zzcf : Ljava/lang/String;
    //   1559: aload #18
    //   1561: getfield name : Ljava/lang/String;
    //   1564: aload #18
    //   1566: getfield zzfe : J
    //   1569: lconst_1
    //   1570: ladd
    //   1571: aload #18
    //   1573: getfield zzff : J
    //   1576: lconst_1
    //   1577: ladd
    //   1578: aload #18
    //   1580: getfield zzfg : J
    //   1583: aload #18
    //   1585: getfield zzfh : J
    //   1588: aload #18
    //   1590: getfield zzfi : Ljava/lang/Long;
    //   1593: aload #18
    //   1595: getfield zzfj : Ljava/lang/Long;
    //   1598: aload #18
    //   1600: getfield zzfk : Ljava/lang/Long;
    //   1603: aload #18
    //   1605: getfield zzfl : Ljava/lang/Boolean;
    //   1608: invokespecial <init> : (Ljava/lang/String;Ljava/lang/String;JJJJLjava/lang/Long;Ljava/lang/Long;Ljava/lang/Long;Ljava/lang/Boolean;)V
    //   1611: astore #29
    //   1613: aload #10
    //   1615: astore #17
    //   1617: aload #9
    //   1619: astore #18
    //   1621: aload #4
    //   1623: astore #20
    //   1625: aload #6
    //   1627: astore #16
    //   1629: aload #8
    //   1631: astore #10
    //   1633: aload_0
    //   1634: invokevirtual zzdo : ()Lcom/google/android/gms/measurement/internal/zzw;
    //   1637: aload #29
    //   1639: invokevirtual zza : (Lcom/google/android/gms/measurement/internal/zzaf;)V
    //   1642: aload #29
    //   1644: getfield zzfe : J
    //   1647: lstore #30
    //   1649: aload #7
    //   1651: aload #11
    //   1653: invokeinterface get : (Ljava/lang/Object;)Ljava/lang/Object;
    //   1658: checkcast java/util/Map
    //   1661: astore #9
    //   1663: aload #9
    //   1665: ifnonnull -> 1718
    //   1668: aload_0
    //   1669: invokevirtual zzdo : ()Lcom/google/android/gms/measurement/internal/zzw;
    //   1672: aload #26
    //   1674: aload #11
    //   1676: invokevirtual zzh : (Ljava/lang/String;Ljava/lang/String;)Ljava/util/Map;
    //   1679: astore #6
    //   1681: aload #6
    //   1683: astore #4
    //   1685: aload #6
    //   1687: ifnonnull -> 1699
    //   1690: new android/support/v4/util/ArrayMap
    //   1693: dup
    //   1694: invokespecial <init> : ()V
    //   1697: astore #4
    //   1699: aload #7
    //   1701: aload #11
    //   1703: aload #4
    //   1705: invokeinterface put : (Ljava/lang/Object;Ljava/lang/Object;)Ljava/lang/Object;
    //   1710: pop
    //   1711: aload #4
    //   1713: astore #9
    //   1715: goto -> 1718
    //   1718: aload #9
    //   1720: invokeinterface keySet : ()Ljava/util/Set;
    //   1725: invokeinterface iterator : ()Ljava/util/Iterator;
    //   1730: astore #29
    //   1732: aload #17
    //   1734: astore #6
    //   1736: aload #20
    //   1738: astore #17
    //   1740: aload #16
    //   1742: astore #8
    //   1744: aload #14
    //   1746: astore #4
    //   1748: aload #9
    //   1750: astore #32
    //   1752: aload #7
    //   1754: astore #16
    //   1756: aload #29
    //   1758: invokeinterface hasNext : ()Z
    //   1763: ifeq -> 2786
    //   1766: aload #29
    //   1768: invokeinterface next : ()Ljava/lang/Object;
    //   1773: checkcast java/lang/Integer
    //   1776: invokevirtual intValue : ()I
    //   1779: istore #33
    //   1781: aload #17
    //   1783: iload #33
    //   1785: invokestatic valueOf : (I)Ljava/lang/Integer;
    //   1788: invokeinterface contains : (Ljava/lang/Object;)Z
    //   1793: ifeq -> 1817
    //   1796: aload_0
    //   1797: invokevirtual zzad : ()Lcom/google/android/gms/measurement/internal/zzau;
    //   1800: invokevirtual zzdi : ()Lcom/google/android/gms/measurement/internal/zzaw;
    //   1803: ldc_w 'Skipping failed audience ID'
    //   1806: iload #33
    //   1808: invokestatic valueOf : (I)Ljava/lang/Integer;
    //   1811: invokevirtual zza : (Ljava/lang/String;Ljava/lang/Object;)V
    //   1814: goto -> 1756
    //   1817: aload #8
    //   1819: astore #34
    //   1821: aload #34
    //   1823: iload #33
    //   1825: invokestatic valueOf : (I)Ljava/lang/Integer;
    //   1828: invokeinterface get : (Ljava/lang/Object;)Ljava/lang/Object;
    //   1833: checkcast java/util/BitSet
    //   1836: astore #14
    //   1838: aload #10
    //   1840: astore #35
    //   1842: aload #35
    //   1844: iload #33
    //   1846: invokestatic valueOf : (I)Ljava/lang/Integer;
    //   1849: invokeinterface get : (Ljava/lang/Object;)Ljava/lang/Object;
    //   1854: checkcast java/util/BitSet
    //   1857: astore #9
    //   1859: iload #12
    //   1861: ifeq -> 1901
    //   1864: aload #6
    //   1866: iload #33
    //   1868: invokestatic valueOf : (I)Ljava/lang/Integer;
    //   1871: invokeinterface get : (Ljava/lang/Object;)Ljava/lang/Object;
    //   1876: checkcast java/util/Map
    //   1879: astore #10
    //   1881: aload #4
    //   1883: iload #33
    //   1885: invokestatic valueOf : (I)Ljava/lang/Integer;
    //   1888: invokeinterface get : (Ljava/lang/Object;)Ljava/lang/Object;
    //   1893: checkcast java/util/Map
    //   1896: astore #8
    //   1898: goto -> 1907
    //   1901: aconst_null
    //   1902: astore #10
    //   1904: aconst_null
    //   1905: astore #8
    //   1907: aload #18
    //   1909: iload #33
    //   1911: invokestatic valueOf : (I)Ljava/lang/Integer;
    //   1914: invokeinterface get : (Ljava/lang/Object;)Ljava/lang/Object;
    //   1919: checkcast com/google/android/gms/internal/measurement/zzbt$zza
    //   1922: ifnonnull -> 2100
    //   1925: invokestatic zzhb : ()Lcom/google/android/gms/internal/measurement/zzbt$zza$zza;
    //   1928: astore #9
    //   1930: aload #9
    //   1932: iconst_1
    //   1933: invokevirtual zzl : (Z)Lcom/google/android/gms/internal/measurement/zzbt$zza$zza;
    //   1936: pop
    //   1937: aload #18
    //   1939: iload #33
    //   1941: invokestatic valueOf : (I)Ljava/lang/Integer;
    //   1944: aload #9
    //   1946: invokevirtual zzmr : ()Lcom/google/android/gms/internal/measurement/zzgh;
    //   1949: checkcast com/google/android/gms/internal/measurement/zzez
    //   1952: checkcast com/google/android/gms/internal/measurement/zzbt$zza
    //   1955: invokeinterface put : (Ljava/lang/Object;Ljava/lang/Object;)Ljava/lang/Object;
    //   1960: pop
    //   1961: new java/util/BitSet
    //   1964: dup
    //   1965: invokespecial <init> : ()V
    //   1968: astore #9
    //   1970: aload #34
    //   1972: iload #33
    //   1974: invokestatic valueOf : (I)Ljava/lang/Integer;
    //   1977: aload #9
    //   1979: invokeinterface put : (Ljava/lang/Object;Ljava/lang/Object;)Ljava/lang/Object;
    //   1984: pop
    //   1985: new java/util/BitSet
    //   1988: dup
    //   1989: invokespecial <init> : ()V
    //   1992: astore #7
    //   1994: aload #35
    //   1996: iload #33
    //   1998: invokestatic valueOf : (I)Ljava/lang/Integer;
    //   2001: aload #7
    //   2003: invokeinterface put : (Ljava/lang/Object;Ljava/lang/Object;)Ljava/lang/Object;
    //   2008: pop
    //   2009: iload #12
    //   2011: ifeq -> 2081
    //   2014: new android/support/v4/util/ArrayMap
    //   2017: dup
    //   2018: invokespecial <init> : ()V
    //   2021: astore #10
    //   2023: aload #6
    //   2025: iload #33
    //   2027: invokestatic valueOf : (I)Ljava/lang/Integer;
    //   2030: aload #10
    //   2032: invokeinterface put : (Ljava/lang/Object;Ljava/lang/Object;)Ljava/lang/Object;
    //   2037: pop
    //   2038: new android/support/v4/util/ArrayMap
    //   2041: dup
    //   2042: invokespecial <init> : ()V
    //   2045: astore #20
    //   2047: aload #4
    //   2049: iload #33
    //   2051: invokestatic valueOf : (I)Ljava/lang/Integer;
    //   2054: aload #20
    //   2056: invokeinterface put : (Ljava/lang/Object;Ljava/lang/Object;)Ljava/lang/Object;
    //   2061: pop
    //   2062: aload #7
    //   2064: astore #8
    //   2066: aload #9
    //   2068: astore #14
    //   2070: aload #10
    //   2072: astore #7
    //   2074: aload #8
    //   2076: astore #9
    //   2078: goto -> 2108
    //   2081: aload #9
    //   2083: astore #14
    //   2085: aload #7
    //   2087: astore #9
    //   2089: aload #10
    //   2091: astore #7
    //   2093: aload #8
    //   2095: astore #20
    //   2097: goto -> 2108
    //   2100: aload #8
    //   2102: astore #20
    //   2104: aload #10
    //   2106: astore #7
    //   2108: aload #18
    //   2110: astore #36
    //   2112: aload #4
    //   2114: astore #26
    //   2116: aload #28
    //   2118: astore #10
    //   2120: aload #32
    //   2122: iload #33
    //   2124: invokestatic valueOf : (I)Ljava/lang/Integer;
    //   2127: invokeinterface get : (Ljava/lang/Object;)Ljava/lang/Object;
    //   2132: checkcast java/util/List
    //   2135: invokeinterface iterator : ()Ljava/util/Iterator;
    //   2140: astore #37
    //   2142: aload #34
    //   2144: astore #18
    //   2146: aload #32
    //   2148: astore #8
    //   2150: aload #35
    //   2152: astore #4
    //   2154: aload #37
    //   2156: invokeinterface hasNext : ()Z
    //   2161: ifeq -> 2755
    //   2164: aload #37
    //   2166: invokeinterface next : ()Ljava/lang/Object;
    //   2171: checkcast com/google/android/gms/internal/measurement/zzby
    //   2174: astore #35
    //   2176: aload_0
    //   2177: invokevirtual zzad : ()Lcom/google/android/gms/measurement/internal/zzau;
    //   2180: iconst_2
    //   2181: invokevirtual isLoggable : (I)Z
    //   2184: ifeq -> 2247
    //   2187: aload_0
    //   2188: invokevirtual zzad : ()Lcom/google/android/gms/measurement/internal/zzau;
    //   2191: invokevirtual zzdi : ()Lcom/google/android/gms/measurement/internal/zzaw;
    //   2194: ldc_w 'Evaluating filter. audience, filter, event'
    //   2197: iload #33
    //   2199: invokestatic valueOf : (I)Ljava/lang/Integer;
    //   2202: aload #35
    //   2204: getfield zzwa : Ljava/lang/Integer;
    //   2207: aload_0
    //   2208: invokevirtual zzaa : ()Lcom/google/android/gms/measurement/internal/zzas;
    //   2211: aload #35
    //   2213: getfield zzwb : Ljava/lang/String;
    //   2216: invokevirtual zzal : (Ljava/lang/String;)Ljava/lang/String;
    //   2219: invokevirtual zza : (Ljava/lang/String;Ljava/lang/Object;Ljava/lang/Object;Ljava/lang/Object;)V
    //   2222: aload_0
    //   2223: invokevirtual zzad : ()Lcom/google/android/gms/measurement/internal/zzau;
    //   2226: invokevirtual zzdi : ()Lcom/google/android/gms/measurement/internal/zzaw;
    //   2229: ldc_w 'Filter definition'
    //   2232: aload_0
    //   2233: invokevirtual zzdm : ()Lcom/google/android/gms/measurement/internal/zzfz;
    //   2236: aload #35
    //   2238: invokevirtual zza : (Lcom/google/android/gms/internal/measurement/zzby;)Ljava/lang/String;
    //   2241: invokevirtual zza : (Ljava/lang/String;Ljava/lang/Object;)V
    //   2244: goto -> 2247
    //   2247: aload #35
    //   2249: getfield zzwa : Ljava/lang/Integer;
    //   2252: ifnull -> 2727
    //   2255: aload #35
    //   2257: getfield zzwa : Ljava/lang/Integer;
    //   2260: invokevirtual intValue : ()I
    //   2263: sipush #256
    //   2266: if_icmple -> 2272
    //   2269: goto -> 2727
    //   2272: iload #12
    //   2274: ifeq -> 2577
    //   2277: aload #35
    //   2279: ifnull -> 2307
    //   2282: aload #35
    //   2284: getfield zzvx : Ljava/lang/Boolean;
    //   2287: ifnull -> 2307
    //   2290: aload #35
    //   2292: getfield zzvx : Ljava/lang/Boolean;
    //   2295: invokevirtual booleanValue : ()Z
    //   2298: ifeq -> 2307
    //   2301: iconst_1
    //   2302: istore #15
    //   2304: goto -> 2310
    //   2307: iconst_0
    //   2308: istore #15
    //   2310: aload #35
    //   2312: ifnull -> 2340
    //   2315: aload #35
    //   2317: getfield zzvy : Ljava/lang/Boolean;
    //   2320: ifnull -> 2340
    //   2323: aload #35
    //   2325: getfield zzvy : Ljava/lang/Boolean;
    //   2328: invokevirtual booleanValue : ()Z
    //   2331: ifeq -> 2340
    //   2334: iconst_1
    //   2335: istore #27
    //   2337: goto -> 2343
    //   2340: iconst_0
    //   2341: istore #27
    //   2343: aload #14
    //   2345: aload #35
    //   2347: getfield zzwa : Ljava/lang/Integer;
    //   2350: invokevirtual intValue : ()I
    //   2353: invokevirtual get : (I)Z
    //   2356: ifeq -> 2395
    //   2359: iload #15
    //   2361: ifne -> 2395
    //   2364: iload #27
    //   2366: ifne -> 2395
    //   2369: aload_0
    //   2370: invokevirtual zzad : ()Lcom/google/android/gms/measurement/internal/zzau;
    //   2373: invokevirtual zzdi : ()Lcom/google/android/gms/measurement/internal/zzaw;
    //   2376: ldc_w 'Event filter already evaluated true and it is not associated with a dynamic audience. audience ID, filter ID'
    //   2379: iload #33
    //   2381: invokestatic valueOf : (I)Ljava/lang/Integer;
    //   2384: aload #35
    //   2386: getfield zzwa : Ljava/lang/Integer;
    //   2389: invokevirtual zza : (Ljava/lang/String;Ljava/lang/Object;Ljava/lang/Object;)V
    //   2392: goto -> 2154
    //   2395: aload_0
    //   2396: aload #35
    //   2398: aload #11
    //   2400: aload #5
    //   2402: lload #30
    //   2404: invokespecial zza : (Lcom/google/android/gms/internal/measurement/zzby;Ljava/lang/String;Ljava/util/List;J)Ljava/lang/Boolean;
    //   2407: astore #32
    //   2409: aload_0
    //   2410: invokevirtual zzad : ()Lcom/google/android/gms/measurement/internal/zzau;
    //   2413: invokevirtual zzdi : ()Lcom/google/android/gms/measurement/internal/zzaw;
    //   2416: astore #34
    //   2418: aload #32
    //   2420: ifnonnull -> 2431
    //   2423: ldc_w 'null'
    //   2426: astore #28
    //   2428: goto -> 2435
    //   2431: aload #32
    //   2433: astore #28
    //   2435: aload #34
    //   2437: ldc_w 'Event filter result'
    //   2440: aload #28
    //   2442: invokevirtual zza : (Ljava/lang/String;Ljava/lang/Object;)V
    //   2445: aload #32
    //   2447: ifnonnull -> 2466
    //   2450: aload #17
    //   2452: iload #33
    //   2454: invokestatic valueOf : (I)Ljava/lang/Integer;
    //   2457: invokeinterface add : (Ljava/lang/Object;)Z
    //   2462: pop
    //   2463: goto -> 2154
    //   2466: aload #9
    //   2468: aload #35
    //   2470: getfield zzwa : Ljava/lang/Integer;
    //   2473: invokevirtual intValue : ()I
    //   2476: invokevirtual set : (I)V
    //   2479: aload #32
    //   2481: invokevirtual booleanValue : ()Z
    //   2484: ifeq -> 2574
    //   2487: aload #14
    //   2489: aload #35
    //   2491: getfield zzwa : Ljava/lang/Integer;
    //   2494: invokevirtual intValue : ()I
    //   2497: invokevirtual set : (I)V
    //   2500: iload #15
    //   2502: ifne -> 2510
    //   2505: iload #27
    //   2507: ifeq -> 2571
    //   2510: aload #10
    //   2512: getfield zzxj : Ljava/lang/Long;
    //   2515: ifnull -> 2571
    //   2518: iload #27
    //   2520: ifeq -> 2547
    //   2523: aload #20
    //   2525: aload #35
    //   2527: getfield zzwa : Ljava/lang/Integer;
    //   2530: invokevirtual intValue : ()I
    //   2533: aload #10
    //   2535: getfield zzxj : Ljava/lang/Long;
    //   2538: invokevirtual longValue : ()J
    //   2541: invokestatic zzb : (Ljava/util/Map;IJ)V
    //   2544: goto -> 2154
    //   2547: aload #7
    //   2549: aload #35
    //   2551: getfield zzwa : Ljava/lang/Integer;
    //   2554: invokevirtual intValue : ()I
    //   2557: aload #10
    //   2559: getfield zzxj : Ljava/lang/Long;
    //   2562: invokevirtual longValue : ()J
    //   2565: invokestatic zza : (Ljava/util/Map;IJ)V
    //   2568: goto -> 2154
    //   2571: goto -> 2154
    //   2574: goto -> 2154
    //   2577: aload #14
    //   2579: aload #35
    //   2581: getfield zzwa : Ljava/lang/Integer;
    //   2584: invokevirtual intValue : ()I
    //   2587: invokevirtual get : (I)Z
    //   2590: ifeq -> 2619
    //   2593: aload_0
    //   2594: invokevirtual zzad : ()Lcom/google/android/gms/measurement/internal/zzau;
    //   2597: invokevirtual zzdi : ()Lcom/google/android/gms/measurement/internal/zzaw;
    //   2600: ldc_w 'Event filter already evaluated true. audience ID, filter ID'
    //   2603: iload #33
    //   2605: invokestatic valueOf : (I)Ljava/lang/Integer;
    //   2608: aload #35
    //   2610: getfield zzwa : Ljava/lang/Integer;
    //   2613: invokevirtual zza : (Ljava/lang/String;Ljava/lang/Object;Ljava/lang/Object;)V
    //   2616: goto -> 2154
    //   2619: aload_0
    //   2620: aload #35
    //   2622: aload #11
    //   2624: aload #5
    //   2626: lload #30
    //   2628: invokespecial zza : (Lcom/google/android/gms/internal/measurement/zzby;Ljava/lang/String;Ljava/util/List;J)Ljava/lang/Boolean;
    //   2631: astore #32
    //   2633: aload_0
    //   2634: invokevirtual zzad : ()Lcom/google/android/gms/measurement/internal/zzau;
    //   2637: invokevirtual zzdi : ()Lcom/google/android/gms/measurement/internal/zzaw;
    //   2640: astore #34
    //   2642: aload #32
    //   2644: ifnonnull -> 2655
    //   2647: ldc_w 'null'
    //   2650: astore #28
    //   2652: goto -> 2659
    //   2655: aload #32
    //   2657: astore #28
    //   2659: aload #34
    //   2661: ldc_w 'Event filter result'
    //   2664: aload #28
    //   2666: invokevirtual zza : (Ljava/lang/String;Ljava/lang/Object;)V
    //   2669: aload #32
    //   2671: ifnonnull -> 2690
    //   2674: aload #17
    //   2676: iload #33
    //   2678: invokestatic valueOf : (I)Ljava/lang/Integer;
    //   2681: invokeinterface add : (Ljava/lang/Object;)Z
    //   2686: pop
    //   2687: goto -> 2154
    //   2690: aload #9
    //   2692: aload #35
    //   2694: getfield zzwa : Ljava/lang/Integer;
    //   2697: invokevirtual intValue : ()I
    //   2700: invokevirtual set : (I)V
    //   2703: aload #32
    //   2705: invokevirtual booleanValue : ()Z
    //   2708: ifeq -> 2724
    //   2711: aload #14
    //   2713: aload #35
    //   2715: getfield zzwa : Ljava/lang/Integer;
    //   2718: invokevirtual intValue : ()I
    //   2721: invokevirtual set : (I)V
    //   2724: goto -> 2154
    //   2727: aload_0
    //   2728: invokevirtual zzad : ()Lcom/google/android/gms/measurement/internal/zzau;
    //   2731: invokevirtual zzdd : ()Lcom/google/android/gms/measurement/internal/zzaw;
    //   2734: ldc_w 'Invalid event filter ID. appId, id'
    //   2737: aload_1
    //   2738: invokestatic zzao : (Ljava/lang/String;)Ljava/lang/Object;
    //   2741: aload #35
    //   2743: getfield zzwa : Ljava/lang/Integer;
    //   2746: invokestatic valueOf : (Ljava/lang/Object;)Ljava/lang/String;
    //   2749: invokevirtual zza : (Ljava/lang/String;Ljava/lang/Object;Ljava/lang/Object;)V
    //   2752: goto -> 2154
    //   2755: aload #4
    //   2757: astore #9
    //   2759: aload #10
    //   2761: astore #28
    //   2763: aload #8
    //   2765: astore #32
    //   2767: aload #26
    //   2769: astore #4
    //   2771: aload #9
    //   2773: astore #10
    //   2775: aload #18
    //   2777: astore #8
    //   2779: aload #36
    //   2781: astore #18
    //   2783: goto -> 1756
    //   2786: aload #16
    //   2788: astore #9
    //   2790: aload #17
    //   2792: astore #11
    //   2794: aload #21
    //   2796: astore #14
    //   2798: aload #19
    //   2800: astore #7
    //   2802: iinc #23, 1
    //   2805: aload #11
    //   2807: astore #21
    //   2809: aload #4
    //   2811: astore #19
    //   2813: aload #8
    //   2815: astore #4
    //   2817: aload #18
    //   2819: astore #8
    //   2821: aload #7
    //   2823: astore #11
    //   2825: aload #19
    //   2827: astore #18
    //   2829: aload #9
    //   2831: astore #7
    //   2833: aload #8
    //   2835: astore #9
    //   2837: aload #10
    //   2839: astore #8
    //   2841: aload #6
    //   2843: astore #10
    //   2845: aload #4
    //   2847: astore #6
    //   2849: aload #21
    //   2851: astore #4
    //   2853: goto -> 717
    //   2856: aload #18
    //   2858: astore_2
    //   2859: aload #4
    //   2861: astore #21
    //   2863: aload #6
    //   2865: astore #4
    //   2867: aload #9
    //   2869: astore #6
    //   2871: goto -> 2893
    //   2874: aload #11
    //   2876: astore_2
    //   2877: aload #6
    //   2879: astore #9
    //   2881: aload #4
    //   2883: astore #21
    //   2885: aload #7
    //   2887: astore #6
    //   2889: aload #9
    //   2891: astore #4
    //   2893: aload_3
    //   2894: astore #9
    //   2896: aload #9
    //   2898: ifnull -> 4157
    //   2901: new android/support/v4/util/ArrayMap
    //   2904: dup
    //   2905: invokespecial <init> : ()V
    //   2908: astore #11
    //   2910: aload #9
    //   2912: arraylength
    //   2913: istore #22
    //   2915: iconst_0
    //   2916: istore #23
    //   2918: aload #6
    //   2920: astore #14
    //   2922: iload #23
    //   2924: iload #22
    //   2926: if_icmpge -> 4140
    //   2929: aload_3
    //   2930: iload #23
    //   2932: aaload
    //   2933: astore #29
    //   2935: aload #11
    //   2937: aload #29
    //   2939: invokevirtual getName : ()Ljava/lang/String;
    //   2942: invokeinterface get : (Ljava/lang/Object;)Ljava/lang/Object;
    //   2947: checkcast java/util/Map
    //   2950: astore #9
    //   2952: aload #9
    //   2954: ifnonnull -> 3008
    //   2957: aload_0
    //   2958: invokevirtual zzdo : ()Lcom/google/android/gms/measurement/internal/zzw;
    //   2961: aload_1
    //   2962: aload #29
    //   2964: invokevirtual getName : ()Ljava/lang/String;
    //   2967: invokevirtual zzi : (Ljava/lang/String;Ljava/lang/String;)Ljava/util/Map;
    //   2970: astore #6
    //   2972: aload #6
    //   2974: astore #9
    //   2976: aload #6
    //   2978: ifnonnull -> 2990
    //   2981: new android/support/v4/util/ArrayMap
    //   2984: dup
    //   2985: invokespecial <init> : ()V
    //   2988: astore #9
    //   2990: aload #11
    //   2992: aload #29
    //   2994: invokevirtual getName : ()Ljava/lang/String;
    //   2997: aload #9
    //   2999: invokeinterface put : (Ljava/lang/Object;Ljava/lang/Object;)Ljava/lang/Object;
    //   3004: pop
    //   3005: goto -> 3008
    //   3008: aload #9
    //   3010: invokeinterface keySet : ()Ljava/util/Set;
    //   3015: invokeinterface iterator : ()Ljava/util/Iterator;
    //   3020: astore #18
    //   3022: aload #10
    //   3024: astore #6
    //   3026: aload #4
    //   3028: astore #10
    //   3030: aload #11
    //   3032: astore #4
    //   3034: aload #18
    //   3036: invokeinterface hasNext : ()Z
    //   3041: ifeq -> 4122
    //   3044: aload #18
    //   3046: invokeinterface next : ()Ljava/lang/Object;
    //   3051: checkcast java/lang/Integer
    //   3054: invokevirtual intValue : ()I
    //   3057: istore #27
    //   3059: aload #21
    //   3061: iload #27
    //   3063: invokestatic valueOf : (I)Ljava/lang/Integer;
    //   3066: invokeinterface contains : (Ljava/lang/Object;)Z
    //   3071: ifeq -> 3095
    //   3074: aload_0
    //   3075: invokevirtual zzad : ()Lcom/google/android/gms/measurement/internal/zzau;
    //   3078: invokevirtual zzdi : ()Lcom/google/android/gms/measurement/internal/zzaw;
    //   3081: ldc_w 'Skipping failed audience ID'
    //   3084: iload #27
    //   3086: invokestatic valueOf : (I)Ljava/lang/Integer;
    //   3089: invokevirtual zza : (Ljava/lang/String;Ljava/lang/Object;)V
    //   3092: goto -> 3034
    //   3095: aload #10
    //   3097: astore #16
    //   3099: aload #16
    //   3101: iload #27
    //   3103: invokestatic valueOf : (I)Ljava/lang/Integer;
    //   3106: invokeinterface get : (Ljava/lang/Object;)Ljava/lang/Object;
    //   3111: checkcast java/util/BitSet
    //   3114: astore #5
    //   3116: aload #8
    //   3118: astore #20
    //   3120: aload #20
    //   3122: iload #27
    //   3124: invokestatic valueOf : (I)Ljava/lang/Integer;
    //   3127: invokeinterface get : (Ljava/lang/Object;)Ljava/lang/Object;
    //   3132: checkcast java/util/BitSet
    //   3135: astore #19
    //   3137: iload #12
    //   3139: ifeq -> 3178
    //   3142: aload #6
    //   3144: iload #27
    //   3146: invokestatic valueOf : (I)Ljava/lang/Integer;
    //   3149: invokeinterface get : (Ljava/lang/Object;)Ljava/lang/Object;
    //   3154: checkcast java/util/Map
    //   3157: astore #10
    //   3159: aload_2
    //   3160: iload #27
    //   3162: invokestatic valueOf : (I)Ljava/lang/Integer;
    //   3165: invokeinterface get : (Ljava/lang/Object;)Ljava/lang/Object;
    //   3170: checkcast java/util/Map
    //   3173: astore #8
    //   3175: goto -> 3184
    //   3178: aconst_null
    //   3179: astore #10
    //   3181: aconst_null
    //   3182: astore #8
    //   3184: aload #4
    //   3186: astore #11
    //   3188: aload #14
    //   3190: iload #27
    //   3192: invokestatic valueOf : (I)Ljava/lang/Integer;
    //   3195: invokeinterface get : (Ljava/lang/Object;)Ljava/lang/Object;
    //   3200: checkcast com/google/android/gms/internal/measurement/zzbt$zza
    //   3203: ifnonnull -> 3356
    //   3206: invokestatic zzhb : ()Lcom/google/android/gms/internal/measurement/zzbt$zza$zza;
    //   3209: astore #4
    //   3211: aload #4
    //   3213: iconst_1
    //   3214: invokevirtual zzl : (Z)Lcom/google/android/gms/internal/measurement/zzbt$zza$zza;
    //   3217: pop
    //   3218: aload #14
    //   3220: iload #27
    //   3222: invokestatic valueOf : (I)Ljava/lang/Integer;
    //   3225: aload #4
    //   3227: invokevirtual zzmr : ()Lcom/google/android/gms/internal/measurement/zzgh;
    //   3230: checkcast com/google/android/gms/internal/measurement/zzez
    //   3233: checkcast com/google/android/gms/internal/measurement/zzbt$zza
    //   3236: invokeinterface put : (Ljava/lang/Object;Ljava/lang/Object;)Ljava/lang/Object;
    //   3241: pop
    //   3242: new java/util/BitSet
    //   3245: dup
    //   3246: invokespecial <init> : ()V
    //   3249: astore #5
    //   3251: aload #16
    //   3253: iload #27
    //   3255: invokestatic valueOf : (I)Ljava/lang/Integer;
    //   3258: aload #5
    //   3260: invokeinterface put : (Ljava/lang/Object;Ljava/lang/Object;)Ljava/lang/Object;
    //   3265: pop
    //   3266: new java/util/BitSet
    //   3269: dup
    //   3270: invokespecial <init> : ()V
    //   3273: astore #19
    //   3275: aload #20
    //   3277: iload #27
    //   3279: invokestatic valueOf : (I)Ljava/lang/Integer;
    //   3282: aload #19
    //   3284: invokeinterface put : (Ljava/lang/Object;Ljava/lang/Object;)Ljava/lang/Object;
    //   3289: pop
    //   3290: iload #12
    //   3292: ifeq -> 3345
    //   3295: new android/support/v4/util/ArrayMap
    //   3298: dup
    //   3299: invokespecial <init> : ()V
    //   3302: astore #17
    //   3304: aload #6
    //   3306: iload #27
    //   3308: invokestatic valueOf : (I)Ljava/lang/Integer;
    //   3311: aload #17
    //   3313: invokeinterface put : (Ljava/lang/Object;Ljava/lang/Object;)Ljava/lang/Object;
    //   3318: pop
    //   3319: new android/support/v4/util/ArrayMap
    //   3322: dup
    //   3323: invokespecial <init> : ()V
    //   3326: astore #7
    //   3328: aload_2
    //   3329: iload #27
    //   3331: invokestatic valueOf : (I)Ljava/lang/Integer;
    //   3334: aload #7
    //   3336: invokeinterface put : (Ljava/lang/Object;Ljava/lang/Object;)Ljava/lang/Object;
    //   3341: pop
    //   3342: goto -> 3364
    //   3345: aload #8
    //   3347: astore #7
    //   3349: aload #10
    //   3351: astore #17
    //   3353: goto -> 3364
    //   3356: aload #10
    //   3358: astore #17
    //   3360: aload #8
    //   3362: astore #7
    //   3364: aload #9
    //   3366: iload #27
    //   3368: invokestatic valueOf : (I)Ljava/lang/Integer;
    //   3371: invokeinterface get : (Ljava/lang/Object;)Ljava/lang/Object;
    //   3376: checkcast java/util/List
    //   3379: invokeinterface iterator : ()Ljava/util/Iterator;
    //   3384: astore #28
    //   3386: aload #6
    //   3388: astore #8
    //   3390: aload #20
    //   3392: astore #6
    //   3394: aload #16
    //   3396: astore #4
    //   3398: aload #18
    //   3400: astore #10
    //   3402: aload #28
    //   3404: astore #18
    //   3406: aload #18
    //   3408: invokeinterface hasNext : ()Z
    //   3413: ifeq -> 4087
    //   3416: aload #18
    //   3418: invokeinterface next : ()Ljava/lang/Object;
    //   3423: checkcast com/google/android/gms/internal/measurement/zzcb
    //   3426: astore #28
    //   3428: aload_0
    //   3429: invokevirtual zzad : ()Lcom/google/android/gms/measurement/internal/zzau;
    //   3432: iconst_2
    //   3433: invokevirtual isLoggable : (I)Z
    //   3436: ifeq -> 3499
    //   3439: aload_0
    //   3440: invokevirtual zzad : ()Lcom/google/android/gms/measurement/internal/zzau;
    //   3443: invokevirtual zzdi : ()Lcom/google/android/gms/measurement/internal/zzaw;
    //   3446: ldc_w 'Evaluating filter. audience, filter, property'
    //   3449: iload #27
    //   3451: invokestatic valueOf : (I)Ljava/lang/Integer;
    //   3454: aload #28
    //   3456: getfield zzwa : Ljava/lang/Integer;
    //   3459: aload_0
    //   3460: invokevirtual zzaa : ()Lcom/google/android/gms/measurement/internal/zzas;
    //   3463: aload #28
    //   3465: getfield zzwq : Ljava/lang/String;
    //   3468: invokevirtual zzan : (Ljava/lang/String;)Ljava/lang/String;
    //   3471: invokevirtual zza : (Ljava/lang/String;Ljava/lang/Object;Ljava/lang/Object;Ljava/lang/Object;)V
    //   3474: aload_0
    //   3475: invokevirtual zzad : ()Lcom/google/android/gms/measurement/internal/zzau;
    //   3478: invokevirtual zzdi : ()Lcom/google/android/gms/measurement/internal/zzaw;
    //   3481: ldc_w 'Filter definition'
    //   3484: aload_0
    //   3485: invokevirtual zzdm : ()Lcom/google/android/gms/measurement/internal/zzfz;
    //   3488: aload #28
    //   3490: invokevirtual zzb : (Lcom/google/android/gms/internal/measurement/zzcb;)Ljava/lang/String;
    //   3493: invokevirtual zza : (Ljava/lang/String;Ljava/lang/Object;)V
    //   3496: goto -> 3499
    //   3499: aload #28
    //   3501: getfield zzwa : Ljava/lang/Integer;
    //   3504: ifnull -> 4018
    //   3507: aload #28
    //   3509: getfield zzwa : Ljava/lang/Integer;
    //   3512: invokevirtual intValue : ()I
    //   3515: sipush #256
    //   3518: if_icmple -> 3524
    //   3521: goto -> 4018
    //   3524: iload #12
    //   3526: ifeq -> 3872
    //   3529: aload #28
    //   3531: invokestatic zza : (Lcom/google/android/gms/internal/measurement/zzcb;)Z
    //   3534: istore #38
    //   3536: aload #28
    //   3538: ifnull -> 3566
    //   3541: aload #28
    //   3543: getfield zzvy : Ljava/lang/Boolean;
    //   3546: ifnull -> 3566
    //   3549: aload #28
    //   3551: getfield zzvy : Ljava/lang/Boolean;
    //   3554: invokevirtual booleanValue : ()Z
    //   3557: ifeq -> 3566
    //   3560: iconst_1
    //   3561: istore #15
    //   3563: goto -> 3569
    //   3566: iconst_0
    //   3567: istore #15
    //   3569: aload #5
    //   3571: aload #28
    //   3573: getfield zzwa : Ljava/lang/Integer;
    //   3576: invokevirtual intValue : ()I
    //   3579: invokevirtual get : (I)Z
    //   3582: ifeq -> 3621
    //   3585: iload #38
    //   3587: ifne -> 3621
    //   3590: iload #15
    //   3592: ifne -> 3621
    //   3595: aload_0
    //   3596: invokevirtual zzad : ()Lcom/google/android/gms/measurement/internal/zzau;
    //   3599: invokevirtual zzdi : ()Lcom/google/android/gms/measurement/internal/zzaw;
    //   3602: ldc_w 'Property filter already evaluated true and it is not associated with a dynamic audience. audience ID, filter ID'
    //   3605: iload #27
    //   3607: invokestatic valueOf : (I)Ljava/lang/Integer;
    //   3610: aload #28
    //   3612: getfield zzwa : Ljava/lang/Integer;
    //   3615: invokevirtual zza : (Ljava/lang/String;Ljava/lang/Object;Ljava/lang/Object;)V
    //   3618: goto -> 3406
    //   3621: aload_0
    //   3622: aload #28
    //   3624: aload #29
    //   3626: invokespecial zza : (Lcom/google/android/gms/internal/measurement/zzcb;Lcom/google/android/gms/internal/measurement/zzbt$zzh;)Ljava/lang/Boolean;
    //   3629: astore #20
    //   3631: aload_0
    //   3632: invokevirtual zzad : ()Lcom/google/android/gms/measurement/internal/zzau;
    //   3635: invokevirtual zzdi : ()Lcom/google/android/gms/measurement/internal/zzaw;
    //   3638: astore #26
    //   3640: aload #14
    //   3642: astore #16
    //   3644: aload #20
    //   3646: ifnonnull -> 3657
    //   3649: ldc_w 'null'
    //   3652: astore #14
    //   3654: goto -> 3661
    //   3657: aload #20
    //   3659: astore #14
    //   3661: aload #26
    //   3663: ldc_w 'Property filter result'
    //   3666: aload #14
    //   3668: invokevirtual zza : (Ljava/lang/String;Ljava/lang/Object;)V
    //   3671: aload #20
    //   3673: ifnonnull -> 3696
    //   3676: aload #21
    //   3678: iload #27
    //   3680: invokestatic valueOf : (I)Ljava/lang/Integer;
    //   3683: invokeinterface add : (Ljava/lang/Object;)Z
    //   3688: pop
    //   3689: aload #16
    //   3691: astore #14
    //   3693: goto -> 3406
    //   3696: aload #19
    //   3698: aload #28
    //   3700: getfield zzwa : Ljava/lang/Integer;
    //   3703: invokevirtual intValue : ()I
    //   3706: invokevirtual set : (I)V
    //   3709: iload #13
    //   3711: ifeq -> 3759
    //   3714: aload #5
    //   3716: aload #28
    //   3718: getfield zzwa : Ljava/lang/Integer;
    //   3721: invokevirtual intValue : ()I
    //   3724: invokevirtual get : (I)Z
    //   3727: ifeq -> 3738
    //   3730: aload #28
    //   3732: invokestatic zza : (Lcom/google/android/gms/internal/measurement/zzcb;)Z
    //   3735: ifeq -> 3777
    //   3738: aload #5
    //   3740: aload #28
    //   3742: getfield zzwa : Ljava/lang/Integer;
    //   3745: invokevirtual intValue : ()I
    //   3748: aload #20
    //   3750: invokevirtual booleanValue : ()Z
    //   3753: invokevirtual set : (IZ)V
    //   3756: goto -> 3777
    //   3759: aload #5
    //   3761: aload #28
    //   3763: getfield zzwa : Ljava/lang/Integer;
    //   3766: invokevirtual intValue : ()I
    //   3769: aload #20
    //   3771: invokevirtual booleanValue : ()Z
    //   3774: invokevirtual set : (IZ)V
    //   3777: aload #20
    //   3779: invokevirtual booleanValue : ()Z
    //   3782: ifeq -> 3865
    //   3785: iload #38
    //   3787: ifne -> 3795
    //   3790: iload #15
    //   3792: ifeq -> 3865
    //   3795: aload #29
    //   3797: invokevirtual zzis : ()Z
    //   3800: ifeq -> 3858
    //   3803: iload #15
    //   3805: ifeq -> 3833
    //   3808: aload #7
    //   3810: aload #28
    //   3812: getfield zzwa : Ljava/lang/Integer;
    //   3815: invokevirtual intValue : ()I
    //   3818: aload #29
    //   3820: invokevirtual zzit : ()J
    //   3823: invokestatic zzb : (Ljava/util/Map;IJ)V
    //   3826: aload #16
    //   3828: astore #14
    //   3830: goto -> 3406
    //   3833: aload #17
    //   3835: aload #28
    //   3837: getfield zzwa : Ljava/lang/Integer;
    //   3840: invokevirtual intValue : ()I
    //   3843: aload #29
    //   3845: invokevirtual zzit : ()J
    //   3848: invokestatic zza : (Ljava/util/Map;IJ)V
    //   3851: aload #16
    //   3853: astore #14
    //   3855: goto -> 3406
    //   3858: aload #16
    //   3860: astore #14
    //   3862: goto -> 3406
    //   3865: aload #16
    //   3867: astore #14
    //   3869: goto -> 3406
    //   3872: aload #5
    //   3874: aload #28
    //   3876: getfield zzwa : Ljava/lang/Integer;
    //   3879: invokevirtual intValue : ()I
    //   3882: invokevirtual get : (I)Z
    //   3885: ifeq -> 3914
    //   3888: aload_0
    //   3889: invokevirtual zzad : ()Lcom/google/android/gms/measurement/internal/zzau;
    //   3892: invokevirtual zzdi : ()Lcom/google/android/gms/measurement/internal/zzaw;
    //   3895: ldc_w 'Property filter already evaluated true. audience ID, filter ID'
    //   3898: iload #27
    //   3900: invokestatic valueOf : (I)Ljava/lang/Integer;
    //   3903: aload #28
    //   3905: getfield zzwa : Ljava/lang/Integer;
    //   3908: invokevirtual zza : (Ljava/lang/String;Ljava/lang/Object;Ljava/lang/Object;)V
    //   3911: goto -> 3406
    //   3914: aload_0
    //   3915: aload #28
    //   3917: aload #29
    //   3919: invokespecial zza : (Lcom/google/android/gms/internal/measurement/zzcb;Lcom/google/android/gms/internal/measurement/zzbt$zzh;)Ljava/lang/Boolean;
    //   3922: astore #20
    //   3924: aload_0
    //   3925: invokevirtual zzad : ()Lcom/google/android/gms/measurement/internal/zzau;
    //   3928: invokevirtual zzdi : ()Lcom/google/android/gms/measurement/internal/zzaw;
    //   3931: astore #26
    //   3933: aload #20
    //   3935: ifnonnull -> 3946
    //   3938: ldc_w 'null'
    //   3941: astore #16
    //   3943: goto -> 3950
    //   3946: aload #20
    //   3948: astore #16
    //   3950: aload #26
    //   3952: ldc_w 'Property filter result'
    //   3955: aload #16
    //   3957: invokevirtual zza : (Ljava/lang/String;Ljava/lang/Object;)V
    //   3960: aload #20
    //   3962: ifnonnull -> 3981
    //   3965: aload #21
    //   3967: iload #27
    //   3969: invokestatic valueOf : (I)Ljava/lang/Integer;
    //   3972: invokeinterface add : (Ljava/lang/Object;)Z
    //   3977: pop
    //   3978: goto -> 3406
    //   3981: aload #19
    //   3983: aload #28
    //   3985: getfield zzwa : Ljava/lang/Integer;
    //   3988: invokevirtual intValue : ()I
    //   3991: invokevirtual set : (I)V
    //   3994: aload #20
    //   3996: invokevirtual booleanValue : ()Z
    //   3999: ifeq -> 4015
    //   4002: aload #5
    //   4004: aload #28
    //   4006: getfield zzwa : Ljava/lang/Integer;
    //   4009: invokevirtual intValue : ()I
    //   4012: invokevirtual set : (I)V
    //   4015: goto -> 3406
    //   4018: aload #4
    //   4020: astore #7
    //   4022: aload_0
    //   4023: invokevirtual zzad : ()Lcom/google/android/gms/measurement/internal/zzau;
    //   4026: invokevirtual zzdd : ()Lcom/google/android/gms/measurement/internal/zzaw;
    //   4029: ldc_w 'Invalid property filter ID. appId, id'
    //   4032: aload_1
    //   4033: invokestatic zzao : (Ljava/lang/String;)Ljava/lang/Object;
    //   4036: aload #28
    //   4038: getfield zzwa : Ljava/lang/Integer;
    //   4041: invokestatic valueOf : (Ljava/lang/Object;)Ljava/lang/String;
    //   4044: invokevirtual zza : (Ljava/lang/String;Ljava/lang/Object;Ljava/lang/Object;)V
    //   4047: aload #21
    //   4049: iload #27
    //   4051: invokestatic valueOf : (I)Ljava/lang/Integer;
    //   4054: invokeinterface add : (Ljava/lang/Object;)Z
    //   4059: pop
    //   4060: aload #11
    //   4062: astore #4
    //   4064: aload #6
    //   4066: astore #11
    //   4068: aload #10
    //   4070: astore #18
    //   4072: aload #7
    //   4074: astore #10
    //   4076: aload #8
    //   4078: astore #6
    //   4080: aload #11
    //   4082: astore #8
    //   4084: goto -> 3034
    //   4087: aload #11
    //   4089: astore #18
    //   4091: aload #4
    //   4093: astore #7
    //   4095: aload #6
    //   4097: astore #11
    //   4099: aload #8
    //   4101: astore #6
    //   4103: aload #18
    //   4105: astore #4
    //   4107: aload #10
    //   4109: astore #18
    //   4111: aload #7
    //   4113: astore #10
    //   4115: aload #11
    //   4117: astore #8
    //   4119: goto -> 3034
    //   4122: iinc #23, 1
    //   4125: aload #4
    //   4127: astore #11
    //   4129: aload #10
    //   4131: astore #4
    //   4133: aload #6
    //   4135: astore #10
    //   4137: goto -> 2922
    //   4140: aload #10
    //   4142: astore_3
    //   4143: aload #8
    //   4145: astore #10
    //   4147: aload_2
    //   4148: astore #8
    //   4150: aload #14
    //   4152: astore #6
    //   4154: goto -> 4167
    //   4157: aload #10
    //   4159: astore_3
    //   4160: aload #8
    //   4162: astore #10
    //   4164: aload_2
    //   4165: astore #8
    //   4167: aload #4
    //   4169: invokeinterface size : ()I
    //   4174: anewarray com/google/android/gms/internal/measurement/zzbt$zza
    //   4177: astore #14
    //   4179: aload #4
    //   4181: invokeinterface keySet : ()Ljava/util/Set;
    //   4186: invokeinterface iterator : ()Ljava/util/Iterator;
    //   4191: astore #11
    //   4193: iconst_0
    //   4194: istore #22
    //   4196: aload #6
    //   4198: astore #9
    //   4200: aload #4
    //   4202: astore #6
    //   4204: aload #10
    //   4206: astore_2
    //   4207: aload #8
    //   4209: astore #18
    //   4211: aload_3
    //   4212: astore #4
    //   4214: aload #11
    //   4216: astore_3
    //   4217: aload_3
    //   4218: invokeinterface hasNext : ()Z
    //   4223: ifeq -> 5207
    //   4226: aload_3
    //   4227: invokeinterface next : ()Ljava/lang/Object;
    //   4232: checkcast java/lang/Integer
    //   4235: invokevirtual intValue : ()I
    //   4238: istore #15
    //   4240: aload #21
    //   4242: iload #15
    //   4244: invokestatic valueOf : (I)Ljava/lang/Integer;
    //   4247: invokeinterface contains : (Ljava/lang/Object;)Z
    //   4252: ifne -> 5204
    //   4255: aload #9
    //   4257: iload #15
    //   4259: invokestatic valueOf : (I)Ljava/lang/Integer;
    //   4262: invokeinterface get : (Ljava/lang/Object;)Ljava/lang/Object;
    //   4267: checkcast com/google/android/gms/internal/measurement/zzbt$zza
    //   4270: astore #8
    //   4272: aload #8
    //   4274: ifnonnull -> 4285
    //   4277: invokestatic zzhb : ()Lcom/google/android/gms/internal/measurement/zzbt$zza$zza;
    //   4280: astore #11
    //   4282: goto -> 4298
    //   4285: aload #8
    //   4287: invokevirtual zzmh : ()Lcom/google/android/gms/internal/measurement/zzez$zza;
    //   4290: checkcast com/google/android/gms/internal/measurement/zzez$zza
    //   4293: checkcast com/google/android/gms/internal/measurement/zzbt$zza$zza
    //   4296: astore #11
    //   4298: aload #11
    //   4300: iload #15
    //   4302: invokevirtual zzi : (I)Lcom/google/android/gms/internal/measurement/zzbt$zza$zza;
    //   4305: pop
    //   4306: invokestatic zzii : ()Lcom/google/android/gms/internal/measurement/zzbt$zzf$zza;
    //   4309: astore #8
    //   4311: aload #8
    //   4313: aload #6
    //   4315: iload #15
    //   4317: invokestatic valueOf : (I)Ljava/lang/Integer;
    //   4320: invokeinterface get : (Ljava/lang/Object;)Ljava/lang/Object;
    //   4325: checkcast java/util/BitSet
    //   4328: invokestatic zza : (Ljava/util/BitSet;)Ljava/util/List;
    //   4331: invokevirtual zzf : (Ljava/lang/Iterable;)Lcom/google/android/gms/internal/measurement/zzbt$zzf$zza;
    //   4334: astore #8
    //   4336: aload #8
    //   4338: aload_2
    //   4339: iload #15
    //   4341: invokestatic valueOf : (I)Ljava/lang/Integer;
    //   4344: invokeinterface get : (Ljava/lang/Object;)Ljava/lang/Object;
    //   4349: checkcast java/util/BitSet
    //   4352: invokestatic zza : (Ljava/util/BitSet;)Ljava/util/List;
    //   4355: invokevirtual zze : (Ljava/lang/Iterable;)Lcom/google/android/gms/internal/measurement/zzbt$zzf$zza;
    //   4358: astore #19
    //   4360: iload #12
    //   4362: ifeq -> 4991
    //   4365: aload #19
    //   4367: aload #4
    //   4369: iload #15
    //   4371: invokestatic valueOf : (I)Ljava/lang/Integer;
    //   4374: invokeinterface get : (Ljava/lang/Object;)Ljava/lang/Object;
    //   4379: checkcast java/util/Map
    //   4382: invokestatic zza : (Ljava/util/Map;)Ljava/util/List;
    //   4385: invokevirtual zzg : (Ljava/lang/Iterable;)Lcom/google/android/gms/internal/measurement/zzbt$zzf$zza;
    //   4388: pop
    //   4389: aload #18
    //   4391: iload #15
    //   4393: invokestatic valueOf : (I)Ljava/lang/Integer;
    //   4396: invokeinterface get : (Ljava/lang/Object;)Ljava/lang/Object;
    //   4401: checkcast java/util/Map
    //   4404: astore #7
    //   4406: aload #7
    //   4408: ifnonnull -> 4426
    //   4411: invokestatic emptyList : ()Ljava/util/List;
    //   4414: astore #10
    //   4416: aload #6
    //   4418: astore #8
    //   4420: aload_3
    //   4421: astore #6
    //   4423: goto -> 4590
    //   4426: new java/util/ArrayList
    //   4429: dup
    //   4430: aload #7
    //   4432: invokeinterface size : ()I
    //   4437: invokespecial <init> : (I)V
    //   4440: astore #10
    //   4442: aload #7
    //   4444: invokeinterface keySet : ()Ljava/util/Set;
    //   4449: invokeinterface iterator : ()Ljava/util/Iterator;
    //   4454: astore #5
    //   4456: aload #6
    //   4458: astore #8
    //   4460: aload #7
    //   4462: astore #6
    //   4464: aload #5
    //   4466: invokeinterface hasNext : ()Z
    //   4471: ifeq -> 4587
    //   4474: aload #5
    //   4476: invokeinterface next : ()Ljava/lang/Object;
    //   4481: checkcast java/lang/Integer
    //   4484: astore #17
    //   4486: invokestatic zzip : ()Lcom/google/android/gms/internal/measurement/zzbt$zzg$zza;
    //   4489: aload #17
    //   4491: invokevirtual intValue : ()I
    //   4494: invokevirtual zzm : (I)Lcom/google/android/gms/internal/measurement/zzbt$zzg$zza;
    //   4497: astore #7
    //   4499: aload #6
    //   4501: aload #17
    //   4503: invokeinterface get : (Ljava/lang/Object;)Ljava/lang/Object;
    //   4508: checkcast java/util/List
    //   4511: astore #17
    //   4513: aload #17
    //   4515: ifnull -> 4567
    //   4518: aload #17
    //   4520: invokestatic sort : (Ljava/util/List;)V
    //   4523: aload #17
    //   4525: invokeinterface iterator : ()Ljava/util/Iterator;
    //   4530: astore #17
    //   4532: aload #17
    //   4534: invokeinterface hasNext : ()Z
    //   4539: ifeq -> 4564
    //   4542: aload #7
    //   4544: aload #17
    //   4546: invokeinterface next : ()Ljava/lang/Object;
    //   4551: checkcast java/lang/Long
    //   4554: invokevirtual longValue : ()J
    //   4557: invokevirtual zzal : (J)Lcom/google/android/gms/internal/measurement/zzbt$zzg$zza;
    //   4560: pop
    //   4561: goto -> 4532
    //   4564: goto -> 4567
    //   4567: aload #10
    //   4569: aload #7
    //   4571: invokevirtual zzmr : ()Lcom/google/android/gms/internal/measurement/zzgh;
    //   4574: checkcast com/google/android/gms/internal/measurement/zzez
    //   4577: checkcast com/google/android/gms/internal/measurement/zzbt$zzg
    //   4580: invokevirtual add : (Ljava/lang/Object;)Z
    //   4583: pop
    //   4584: goto -> 4464
    //   4587: aload_3
    //   4588: astore #6
    //   4590: iload #13
    //   4592: ifeq -> 4974
    //   4595: aload #11
    //   4597: invokevirtual zzgx : ()Z
    //   4600: ifeq -> 4974
    //   4603: aload #11
    //   4605: invokevirtual zzgy : ()Lcom/google/android/gms/internal/measurement/zzbt$zzf;
    //   4608: invokevirtual zzig : ()Ljava/util/List;
    //   4611: astore_3
    //   4612: aload_3
    //   4613: invokeinterface isEmpty : ()Z
    //   4618: ifeq -> 4627
    //   4621: aload #4
    //   4623: astore_3
    //   4624: goto -> 4977
    //   4627: new java/util/ArrayList
    //   4630: dup
    //   4631: aload #10
    //   4633: invokespecial <init> : (Ljava/util/Collection;)V
    //   4636: astore #10
    //   4638: new android/support/v4/util/ArrayMap
    //   4641: dup
    //   4642: invokespecial <init> : ()V
    //   4645: astore #7
    //   4647: aload_3
    //   4648: invokeinterface iterator : ()Ljava/util/Iterator;
    //   4653: astore #5
    //   4655: aload #5
    //   4657: invokeinterface hasNext : ()Z
    //   4662: ifeq -> 4727
    //   4665: aload #5
    //   4667: invokeinterface next : ()Ljava/lang/Object;
    //   4672: checkcast com/google/android/gms/internal/measurement/zzbt$zzg
    //   4675: astore_3
    //   4676: aload_3
    //   4677: invokevirtual zzhd : ()Z
    //   4680: ifeq -> 4724
    //   4683: aload_3
    //   4684: invokevirtual zzim : ()I
    //   4687: ifle -> 4721
    //   4690: aload #7
    //   4692: aload_3
    //   4693: invokevirtual getIndex : ()I
    //   4696: invokestatic valueOf : (I)Ljava/lang/Integer;
    //   4699: aload_3
    //   4700: aload_3
    //   4701: invokevirtual zzim : ()I
    //   4704: iconst_1
    //   4705: isub
    //   4706: invokevirtual zzl : (I)J
    //   4709: invokestatic valueOf : (J)Ljava/lang/Long;
    //   4712: invokeinterface put : (Ljava/lang/Object;Ljava/lang/Object;)Ljava/lang/Object;
    //   4717: pop
    //   4718: goto -> 4655
    //   4721: goto -> 4655
    //   4724: goto -> 4655
    //   4727: iconst_0
    //   4728: istore #23
    //   4730: iload #23
    //   4732: aload #10
    //   4734: invokeinterface size : ()I
    //   4739: if_icmpge -> 4886
    //   4742: aload #10
    //   4744: iload #23
    //   4746: invokeinterface get : (I)Ljava/lang/Object;
    //   4751: checkcast com/google/android/gms/internal/measurement/zzbt$zzg
    //   4754: astore #5
    //   4756: aload #5
    //   4758: invokevirtual zzhd : ()Z
    //   4761: ifeq -> 4776
    //   4764: aload #5
    //   4766: invokevirtual getIndex : ()I
    //   4769: invokestatic valueOf : (I)Ljava/lang/Integer;
    //   4772: astore_3
    //   4773: goto -> 4778
    //   4776: aconst_null
    //   4777: astore_3
    //   4778: aload #7
    //   4780: aload_3
    //   4781: invokeinterface remove : (Ljava/lang/Object;)Ljava/lang/Object;
    //   4786: checkcast java/lang/Long
    //   4789: astore_3
    //   4790: aload_3
    //   4791: ifnull -> 4880
    //   4794: new java/util/ArrayList
    //   4797: dup
    //   4798: invokespecial <init> : ()V
    //   4801: astore #17
    //   4803: aload_3
    //   4804: invokevirtual longValue : ()J
    //   4807: aload #5
    //   4809: iconst_0
    //   4810: invokevirtual zzl : (I)J
    //   4813: lcmp
    //   4814: ifge -> 4826
    //   4817: aload #17
    //   4819: aload_3
    //   4820: invokeinterface add : (Ljava/lang/Object;)Z
    //   4825: pop
    //   4826: aload #17
    //   4828: aload #5
    //   4830: invokevirtual zzil : ()Ljava/util/List;
    //   4833: invokeinterface addAll : (Ljava/util/Collection;)Z
    //   4838: pop
    //   4839: aload #10
    //   4841: iload #23
    //   4843: aload #5
    //   4845: invokevirtual zzmh : ()Lcom/google/android/gms/internal/measurement/zzez$zza;
    //   4848: checkcast com/google/android/gms/internal/measurement/zzez$zza
    //   4851: checkcast com/google/android/gms/internal/measurement/zzbt$zzg$zza
    //   4854: invokevirtual zzir : ()Lcom/google/android/gms/internal/measurement/zzbt$zzg$zza;
    //   4857: aload #17
    //   4859: invokevirtual zzj : (Ljava/lang/Iterable;)Lcom/google/android/gms/internal/measurement/zzbt$zzg$zza;
    //   4862: invokevirtual zzmr : ()Lcom/google/android/gms/internal/measurement/zzgh;
    //   4865: checkcast com/google/android/gms/internal/measurement/zzez
    //   4868: checkcast com/google/android/gms/internal/measurement/zzbt$zzg
    //   4871: invokeinterface set : (ILjava/lang/Object;)Ljava/lang/Object;
    //   4876: pop
    //   4877: goto -> 4880
    //   4880: iinc #23, 1
    //   4883: goto -> 4730
    //   4886: aload #7
    //   4888: invokeinterface keySet : ()Ljava/util/Set;
    //   4893: invokeinterface iterator : ()Ljava/util/Iterator;
    //   4898: astore_3
    //   4899: aload_3
    //   4900: invokeinterface hasNext : ()Z
    //   4905: ifeq -> 4968
    //   4908: aload_3
    //   4909: invokeinterface next : ()Ljava/lang/Object;
    //   4914: checkcast java/lang/Integer
    //   4917: astore #5
    //   4919: aload #10
    //   4921: invokestatic zzip : ()Lcom/google/android/gms/internal/measurement/zzbt$zzg$zza;
    //   4924: aload #5
    //   4926: invokevirtual intValue : ()I
    //   4929: invokevirtual zzm : (I)Lcom/google/android/gms/internal/measurement/zzbt$zzg$zza;
    //   4932: aload #7
    //   4934: aload #5
    //   4936: invokeinterface get : (Ljava/lang/Object;)Ljava/lang/Object;
    //   4941: checkcast java/lang/Long
    //   4944: invokevirtual longValue : ()J
    //   4947: invokevirtual zzal : (J)Lcom/google/android/gms/internal/measurement/zzbt$zzg$zza;
    //   4950: invokevirtual zzmr : ()Lcom/google/android/gms/internal/measurement/zzgh;
    //   4953: checkcast com/google/android/gms/internal/measurement/zzez
    //   4956: checkcast com/google/android/gms/internal/measurement/zzbt$zzg
    //   4959: invokeinterface add : (Ljava/lang/Object;)Z
    //   4964: pop
    //   4965: goto -> 4899
    //   4968: aload #4
    //   4970: astore_3
    //   4971: goto -> 4977
    //   4974: aload #4
    //   4976: astore_3
    //   4977: aload #19
    //   4979: aload #10
    //   4981: invokevirtual zzh : (Ljava/lang/Iterable;)Lcom/google/android/gms/internal/measurement/zzbt$zzf$zza;
    //   4984: pop
    //   4985: aload_3
    //   4986: astore #4
    //   4988: goto -> 4998
    //   4991: aload #6
    //   4993: astore #8
    //   4995: aload_3
    //   4996: astore #6
    //   4998: aload #11
    //   5000: aload #19
    //   5002: invokevirtual zzb : (Lcom/google/android/gms/internal/measurement/zzbt$zzf$zza;)Lcom/google/android/gms/internal/measurement/zzbt$zza$zza;
    //   5005: pop
    //   5006: aload #9
    //   5008: iload #15
    //   5010: invokestatic valueOf : (I)Ljava/lang/Integer;
    //   5013: aload #11
    //   5015: invokevirtual zzmr : ()Lcom/google/android/gms/internal/measurement/zzgh;
    //   5018: checkcast com/google/android/gms/internal/measurement/zzez
    //   5021: checkcast com/google/android/gms/internal/measurement/zzbt$zza
    //   5024: invokeinterface put : (Ljava/lang/Object;Ljava/lang/Object;)Ljava/lang/Object;
    //   5029: pop
    //   5030: aload #14
    //   5032: iload #22
    //   5034: aload #11
    //   5036: invokevirtual zzmr : ()Lcom/google/android/gms/internal/measurement/zzgh;
    //   5039: checkcast com/google/android/gms/internal/measurement/zzez
    //   5042: checkcast com/google/android/gms/internal/measurement/zzbt$zza
    //   5045: aastore
    //   5046: aload_0
    //   5047: invokevirtual zzdo : ()Lcom/google/android/gms/measurement/internal/zzw;
    //   5050: astore #10
    //   5052: aload #11
    //   5054: invokevirtual zzgw : ()Lcom/google/android/gms/internal/measurement/zzbt$zzf;
    //   5057: astore_3
    //   5058: aload #10
    //   5060: invokevirtual zzah : ()V
    //   5063: aload #10
    //   5065: invokevirtual zzq : ()V
    //   5068: aload_1
    //   5069: invokestatic checkNotEmpty : (Ljava/lang/String;)Ljava/lang/String;
    //   5072: pop
    //   5073: aload_3
    //   5074: invokestatic checkNotNull : (Ljava/lang/Object;)Ljava/lang/Object;
    //   5077: pop
    //   5078: aload_3
    //   5079: invokevirtual toByteArray : ()[B
    //   5082: astore #11
    //   5084: new android/content/ContentValues
    //   5087: dup
    //   5088: invokespecial <init> : ()V
    //   5091: astore_3
    //   5092: aload_3
    //   5093: ldc_w 'app_id'
    //   5096: aload_1
    //   5097: invokevirtual put : (Ljava/lang/String;Ljava/lang/String;)V
    //   5100: aload_3
    //   5101: ldc_w 'audience_id'
    //   5104: iload #15
    //   5106: invokestatic valueOf : (I)Ljava/lang/Integer;
    //   5109: invokevirtual put : (Ljava/lang/String;Ljava/lang/Integer;)V
    //   5112: aload_3
    //   5113: ldc_w 'current_results'
    //   5116: aload #11
    //   5118: invokevirtual put : (Ljava/lang/String;[B)V
    //   5121: aload #10
    //   5123: invokevirtual getWritableDatabase : ()Landroid/database/sqlite/SQLiteDatabase;
    //   5126: astore #11
    //   5128: aload #11
    //   5130: ldc_w 'audience_filter_values'
    //   5133: aconst_null
    //   5134: aload_3
    //   5135: iconst_5
    //   5136: invokevirtual insertWithOnConflict : (Ljava/lang/String;Ljava/lang/String;Landroid/content/ContentValues;I)J
    //   5139: ldc2_w -1
    //   5142: lcmp
    //   5143: ifne -> 5191
    //   5146: aload #10
    //   5148: invokevirtual zzad : ()Lcom/google/android/gms/measurement/internal/zzau;
    //   5151: invokevirtual zzda : ()Lcom/google/android/gms/measurement/internal/zzaw;
    //   5154: ldc_w 'Failed to insert filter results (got -1). appId'
    //   5157: aload_1
    //   5158: invokestatic zzao : (Ljava/lang/String;)Ljava/lang/Object;
    //   5161: invokevirtual zza : (Ljava/lang/String;Ljava/lang/Object;)V
    //   5164: goto -> 5191
    //   5167: astore_3
    //   5168: goto -> 5172
    //   5171: astore_3
    //   5172: aload #10
    //   5174: invokevirtual zzad : ()Lcom/google/android/gms/measurement/internal/zzau;
    //   5177: invokevirtual zzda : ()Lcom/google/android/gms/measurement/internal/zzaw;
    //   5180: ldc_w 'Error storing filter results. appId'
    //   5183: aload_1
    //   5184: invokestatic zzao : (Ljava/lang/String;)Ljava/lang/Object;
    //   5187: aload_3
    //   5188: invokevirtual zza : (Ljava/lang/String;Ljava/lang/Object;Ljava/lang/Object;)V
    //   5191: iinc #22, 1
    //   5194: aload #6
    //   5196: astore_3
    //   5197: aload #8
    //   5199: astore #6
    //   5201: goto -> 4217
    //   5204: goto -> 4217
    //   5207: aload #14
    //   5209: iload #22
    //   5211: invokestatic copyOf : ([Ljava/lang/Object;I)[Ljava/lang/Object;
    //   5214: checkcast [Lcom/google/android/gms/internal/measurement/zzbt$zza;
    //   5217: areturn
    // Exception table:
    //   from	to	target	type
    //   1011	1018	1047	android/database/sqlite/SQLiteException
    //   1018	1035	1038	android/database/sqlite/SQLiteException
    //   5121	5128	5171	android/database/sqlite/SQLiteException
    //   5128	5164	5167	android/database/sqlite/SQLiteException
  }
  
  protected final boolean zzak() {
    return false;
  }
}


/* Location:              Y:\classes-dex2jar.jar!\com\google\android\gms\measurement\internal\zzo.class
 * Java compiler version: 6 (50.0)
 * JD-Core Version:       1.1.3
 */