package io.reactivex.internal.operators.flowable;

import io.reactivex.Flowable;
import io.reactivex.disposables.CompositeDisposable;
import io.reactivex.disposables.Disposable;
import io.reactivex.exceptions.Exceptions;
import io.reactivex.exceptions.MissingBackpressureException;
import io.reactivex.functions.BiFunction;
import io.reactivex.functions.Function;
import io.reactivex.internal.functions.ObjectHelper;
import io.reactivex.internal.fuseable.SimpleQueue;
import io.reactivex.internal.queue.SpscLinkedArrayQueue;
import io.reactivex.internal.subscriptions.SubscriptionHelper;
import io.reactivex.internal.util.BackpressureHelper;
import io.reactivex.internal.util.ExceptionHelper;
import io.reactivex.plugins.RxJavaPlugins;
import java.util.Iterator;
import java.util.LinkedHashMap;
import java.util.Map;
import java.util.concurrent.atomic.AtomicInteger;
import java.util.concurrent.atomic.AtomicLong;
import java.util.concurrent.atomic.AtomicReference;
import org.reactivestreams.Publisher;
import org.reactivestreams.Subscriber;
import org.reactivestreams.Subscription;

public final class FlowableJoin<TLeft, TRight, TLeftEnd, TRightEnd, R> extends AbstractFlowableWithUpstream<TLeft, R> {
  final Function<? super TLeft, ? extends Publisher<TLeftEnd>> leftEnd;
  
  final Publisher<? extends TRight> other;
  
  final BiFunction<? super TLeft, ? super TRight, ? extends R> resultSelector;
  
  final Function<? super TRight, ? extends Publisher<TRightEnd>> rightEnd;
  
  public FlowableJoin(Flowable<TLeft> paramFlowable, Publisher<? extends TRight> paramPublisher, Function<? super TLeft, ? extends Publisher<TLeftEnd>> paramFunction, Function<? super TRight, ? extends Publisher<TRightEnd>> paramFunction1, BiFunction<? super TLeft, ? super TRight, ? extends R> paramBiFunction) {
    super(paramFlowable);
    this.other = paramPublisher;
    this.leftEnd = paramFunction;
    this.rightEnd = paramFunction1;
    this.resultSelector = paramBiFunction;
  }
  
  protected void subscribeActual(Subscriber<? super R> paramSubscriber) {
    JoinSubscription<TLeft, TRight, TLeftEnd, TRightEnd, R> joinSubscription = new JoinSubscription<TLeft, TRight, TLeftEnd, TRightEnd, R>(paramSubscriber, this.leftEnd, this.rightEnd, this.resultSelector);
    paramSubscriber.onSubscribe(joinSubscription);
    FlowableGroupJoin.LeftRightSubscriber leftRightSubscriber2 = new FlowableGroupJoin.LeftRightSubscriber(joinSubscription, true);
    joinSubscription.disposables.add(leftRightSubscriber2);
    FlowableGroupJoin.LeftRightSubscriber leftRightSubscriber1 = new FlowableGroupJoin.LeftRightSubscriber(joinSubscription, false);
    joinSubscription.disposables.add(leftRightSubscriber1);
    this.source.subscribe(leftRightSubscriber2);
    this.other.subscribe((Subscriber)leftRightSubscriber1);
  }
  
  static final class JoinSubscription<TLeft, TRight, TLeftEnd, TRightEnd, R> extends AtomicInteger implements Subscription, FlowableGroupJoin.JoinSupport {
    static final Integer LEFT_CLOSE = Integer.valueOf(3);
    
    static final Integer LEFT_VALUE = Integer.valueOf(1);
    
    static final Integer RIGHT_CLOSE = Integer.valueOf(4);
    
    static final Integer RIGHT_VALUE = Integer.valueOf(2);
    
    private static final long serialVersionUID = -6071216598687999801L;
    
    final AtomicInteger active;
    
    final Subscriber<? super R> actual;
    
    volatile boolean cancelled;
    
    final CompositeDisposable disposables;
    
    final AtomicReference<Throwable> error;
    
    final Function<? super TLeft, ? extends Publisher<TLeftEnd>> leftEnd;
    
    int leftIndex;
    
    final Map<Integer, TLeft> lefts;
    
    final SpscLinkedArrayQueue<Object> queue;
    
    final AtomicLong requested;
    
    final BiFunction<? super TLeft, ? super TRight, ? extends R> resultSelector;
    
    final Function<? super TRight, ? extends Publisher<TRightEnd>> rightEnd;
    
    int rightIndex;
    
    final Map<Integer, TRight> rights;
    
    static {
    
    }
    
    JoinSubscription(Subscriber<? super R> param1Subscriber, Function<? super TLeft, ? extends Publisher<TLeftEnd>> param1Function, Function<? super TRight, ? extends Publisher<TRightEnd>> param1Function1, BiFunction<? super TLeft, ? super TRight, ? extends R> param1BiFunction) {
      this.actual = param1Subscriber;
      this.requested = new AtomicLong();
      this.disposables = new CompositeDisposable();
      this.queue = new SpscLinkedArrayQueue(Flowable.bufferSize());
      this.lefts = new LinkedHashMap<Integer, TLeft>();
      this.rights = new LinkedHashMap<Integer, TRight>();
      this.error = new AtomicReference<Throwable>();
      this.leftEnd = param1Function;
      this.rightEnd = param1Function1;
      this.resultSelector = param1BiFunction;
      this.active = new AtomicInteger(2);
    }
    
    public void cancel() {
      if (this.cancelled)
        return; 
      this.cancelled = true;
      cancelAll();
      if (getAndIncrement() == 0)
        this.queue.clear(); 
    }
    
    void cancelAll() {
      this.disposables.dispose();
    }
    
    void drain() {
      if (getAndIncrement() != 0)
        return; 
      SpscLinkedArrayQueue<Object> spscLinkedArrayQueue = this.queue;
      Subscriber<? super R> subscriber = this.actual;
      int i = 1;
      while (true) {
        int j;
        Iterator<FlowableGroupJoin.LeftRightEndSubscriber> iterator;
        boolean bool;
        if (this.cancelled) {
          spscLinkedArrayQueue.clear();
          return;
        } 
        if ((Throwable)this.error.get() != null) {
          spscLinkedArrayQueue.clear();
          cancelAll();
          errorAll(subscriber);
          return;
        } 
        if (this.active.get() == 0) {
          j = 1;
        } else {
          j = 0;
        } 
        Integer integer = (Integer)spscLinkedArrayQueue.poll();
        if (integer == null) {
          bool = true;
        } else {
          bool = false;
        } 
        if (j && bool) {
          this.lefts.clear();
          this.rights.clear();
          this.disposables.dispose();
          subscriber.onComplete();
          return;
        } 
        if (bool) {
          j = addAndGet(-i);
          i = j;
          if (j == 0)
            return; 
          continue;
        } 
        object = spscLinkedArrayQueue.poll();
        if (integer == LEFT_VALUE) {
          j = this.leftIndex;
          this.leftIndex = j + 1;
          this.lefts.put(Integer.valueOf(j), (TLeft)object);
          try {
            Publisher publisher = (Publisher)ObjectHelper.requireNonNull(this.leftEnd.apply(object), "The leftEnd returned a null Publisher");
            FlowableGroupJoin.LeftRightEndSubscriber leftRightEndSubscriber = new FlowableGroupJoin.LeftRightEndSubscriber(this, true, j);
            this.disposables.add(leftRightEndSubscriber);
            publisher.subscribe((Subscriber)leftRightEndSubscriber);
            if ((Throwable)this.error.get() != null) {
              spscLinkedArrayQueue.clear();
              cancelAll();
              errorAll(subscriber);
              return;
            } 
            long l1 = this.requested.get();
            iterator = this.rights.values().iterator();
            long l2 = 0L;
            while (iterator.hasNext()) {
              leftRightEndSubscriber = iterator.next();
              try {
                Object object1 = ObjectHelper.requireNonNull(this.resultSelector.apply(object, leftRightEndSubscriber), "The resultSelector returned a null value");
                if (l2 != l1) {
                  subscriber.onNext(object1);
                  l2++;
                  continue;
                } 
                ExceptionHelper.addThrowable(this.error, (Throwable)new MissingBackpressureException("Could not emit value due to lack of requests"));
                spscLinkedArrayQueue.clear();
                cancelAll();
                errorAll(subscriber);
                return;
              } catch (Throwable throwable) {
                fail(throwable, subscriber, (SimpleQueue<?>)spscLinkedArrayQueue);
                return;
              } 
            } 
            if (l2 != 0L)
              BackpressureHelper.produced(this.requested, l2); 
          } catch (Throwable null) {
            fail((Throwable)object, subscriber, (SimpleQueue<?>)spscLinkedArrayQueue);
            return;
          } 
          continue;
        } 
        if (iterator == RIGHT_VALUE) {
          j = this.rightIndex;
          this.rightIndex = j + 1;
          this.rights.put(Integer.valueOf(j), (TRight)object);
          try {
            Publisher publisher = (Publisher)ObjectHelper.requireNonNull(this.rightEnd.apply(object), "The rightEnd returned a null Publisher");
            FlowableGroupJoin.LeftRightEndSubscriber leftRightEndSubscriber = new FlowableGroupJoin.LeftRightEndSubscriber(this, false, j);
            this.disposables.add(leftRightEndSubscriber);
            publisher.subscribe((Subscriber)leftRightEndSubscriber);
            if ((Throwable)this.error.get() != null) {
              spscLinkedArrayQueue.clear();
              cancelAll();
              errorAll(subscriber);
              return;
            } 
            long l1 = this.requested.get();
            iterator = this.lefts.values().iterator();
            long l2 = 0L;
            while (iterator.hasNext()) {
              leftRightEndSubscriber = iterator.next();
              try {
                Object object1 = ObjectHelper.requireNonNull(this.resultSelector.apply(leftRightEndSubscriber, object), "The resultSelector returned a null value");
                if (l2 != l1) {
                  subscriber.onNext(object1);
                  l2++;
                  continue;
                } 
                ExceptionHelper.addThrowable(this.error, (Throwable)new MissingBackpressureException("Could not emit value due to lack of requests"));
                spscLinkedArrayQueue.clear();
                cancelAll();
                errorAll(subscriber);
                return;
              } catch (Throwable throwable) {
                fail(throwable, subscriber, (SimpleQueue<?>)spscLinkedArrayQueue);
                return;
              } 
            } 
            if (l2 != 0L)
              BackpressureHelper.produced(this.requested, l2); 
          } catch (Throwable object) {
            fail((Throwable)object, subscriber, (SimpleQueue<?>)spscLinkedArrayQueue);
            return;
          } 
          continue;
        } 
        if (iterator == LEFT_CLOSE) {
          object = object;
          this.lefts.remove(Integer.valueOf(((FlowableGroupJoin.LeftRightEndSubscriber)object).index));
          this.disposables.remove((Disposable)object);
          continue;
        } 
        if (iterator == RIGHT_CLOSE) {
          object = object;
          this.rights.remove(Integer.valueOf(((FlowableGroupJoin.LeftRightEndSubscriber)object).index));
          this.disposables.remove((Disposable)object);
        } 
      } 
    }
    
    void errorAll(Subscriber<?> param1Subscriber) {
      Throwable throwable = ExceptionHelper.terminate(this.error);
      this.lefts.clear();
      this.rights.clear();
      param1Subscriber.onError(throwable);
    }
    
    void fail(Throwable param1Throwable, Subscriber<?> param1Subscriber, SimpleQueue<?> param1SimpleQueue) {
      Exceptions.throwIfFatal(param1Throwable);
      ExceptionHelper.addThrowable(this.error, param1Throwable);
      param1SimpleQueue.clear();
      cancelAll();
      errorAll(param1Subscriber);
    }
    
    public void innerClose(boolean param1Boolean, FlowableGroupJoin.LeftRightEndSubscriber param1LeftRightEndSubscriber) {
      // Byte code:
      //   0: aload_0
      //   1: monitorenter
      //   2: aload_0
      //   3: getfield queue : Lio/reactivex/internal/queue/SpscLinkedArrayQueue;
      //   6: astore_3
      //   7: iload_1
      //   8: ifeq -> 19
      //   11: getstatic io/reactivex/internal/operators/flowable/FlowableJoin$JoinSubscription.LEFT_CLOSE : Ljava/lang/Integer;
      //   14: astore #4
      //   16: goto -> 24
      //   19: getstatic io/reactivex/internal/operators/flowable/FlowableJoin$JoinSubscription.RIGHT_CLOSE : Ljava/lang/Integer;
      //   22: astore #4
      //   24: aload_3
      //   25: aload #4
      //   27: aload_2
      //   28: invokevirtual offer : (Ljava/lang/Object;Ljava/lang/Object;)Z
      //   31: pop
      //   32: aload_0
      //   33: monitorexit
      //   34: aload_0
      //   35: invokevirtual drain : ()V
      //   38: return
      //   39: astore_2
      //   40: aload_0
      //   41: monitorexit
      //   42: aload_2
      //   43: athrow
      // Exception table:
      //   from	to	target	type
      //   2	7	39	finally
      //   11	16	39	finally
      //   19	24	39	finally
      //   24	34	39	finally
      //   40	42	39	finally
    }
    
    public void innerCloseError(Throwable param1Throwable) {
      if (ExceptionHelper.addThrowable(this.error, param1Throwable)) {
        drain();
      } else {
        RxJavaPlugins.onError(param1Throwable);
      } 
    }
    
    public void innerComplete(FlowableGroupJoin.LeftRightSubscriber param1LeftRightSubscriber) {
      this.disposables.delete(param1LeftRightSubscriber);
      this.active.decrementAndGet();
      drain();
    }
    
    public void innerError(Throwable param1Throwable) {
      if (ExceptionHelper.addThrowable(this.error, param1Throwable)) {
        this.active.decrementAndGet();
        drain();
      } else {
        RxJavaPlugins.onError(param1Throwable);
      } 
    }
    
    public void innerValue(boolean param1Boolean, Object param1Object) {
      // Byte code:
      //   0: aload_0
      //   1: monitorenter
      //   2: aload_0
      //   3: getfield queue : Lio/reactivex/internal/queue/SpscLinkedArrayQueue;
      //   6: astore_3
      //   7: iload_1
      //   8: ifeq -> 19
      //   11: getstatic io/reactivex/internal/operators/flowable/FlowableJoin$JoinSubscription.LEFT_VALUE : Ljava/lang/Integer;
      //   14: astore #4
      //   16: goto -> 24
      //   19: getstatic io/reactivex/internal/operators/flowable/FlowableJoin$JoinSubscription.RIGHT_VALUE : Ljava/lang/Integer;
      //   22: astore #4
      //   24: aload_3
      //   25: aload #4
      //   27: aload_2
      //   28: invokevirtual offer : (Ljava/lang/Object;Ljava/lang/Object;)Z
      //   31: pop
      //   32: aload_0
      //   33: monitorexit
      //   34: aload_0
      //   35: invokevirtual drain : ()V
      //   38: return
      //   39: astore_2
      //   40: aload_0
      //   41: monitorexit
      //   42: aload_2
      //   43: athrow
      // Exception table:
      //   from	to	target	type
      //   2	7	39	finally
      //   11	16	39	finally
      //   19	24	39	finally
      //   24	34	39	finally
      //   40	42	39	finally
    }
    
    public void request(long param1Long) {
      if (SubscriptionHelper.validate(param1Long))
        BackpressureHelper.add(this.requested, param1Long); 
    }
  }
}


/* Location:              Y:\classes2-dex2jar.jar!\io\reactivex\internal\operators\flowable\FlowableJoin.class
 * Java compiler version: 6 (50.0)
 * JD-Core Version:       1.1.3
 */